Workbook

Sheet Cover
A1: BINGHATTI HOLDING
A2: Escrow release against debt maturities — a register-based liquidity model
A4: Prepared by | B4: DPI
A5: Register read date | B5: =Simulator!$C$3 -> 46275
A6: Financials as at | B6: 30 June 2026 (interim), FY2025 audited
A7: Currency and units | B7: AED millions, unless a cell says otherwise
A8: Active scenario | B8: =Scenarios!$C$3 -> Base
A10: THE QUESTION
A11: Binghatti has AED 11,623m of sukuk and bank debt maturing between now and 2031. Can cash released from construction escrow, net of the cost of building the towers and of servicing the debt, meet each maturity as it falls?
A13: WHAT THE PUBLIC REGISTER CURRENTLY SUPPORTS — A CONDITIONAL FINDING, NOT A VERDICT
A14: ="On the data the Dubai Land Department register holds today, and on three assumptions set out below that we have had to derive rather than obtain, "&COUNTIF($F$16:$F$23,"<1")&" of the eight maturities to 2031 are not met from modelled cash, short by AED "&TEXT($G$24,"#,##0")&_xlfn._LONGTEXT(" m in total. Read that as conditional. Each of the three assumptions, moved on its own within a plausible range, reverses it: see the box below. The table is ordered by maturity date; cash available is the modelled balance in the maturity month before tha","t principal is paid, after the cost of completing the towers and all profit and interest payments. Sukuk carry their actual coupons; the bank rate is backed out of reported finance cost.") -> On the data the Dubai Land Department register holds today, and on three assumptions set out below that we have had to derive rather than obtain, 2 of the eight maturities to 2031 are not met from modelled cash, short by AED 551 m in total. Read that as conditional. Each of the three assumptions, moved on its own within a plausible range, reverses it: see the box below. The table is ordered by maturity date; cash available is the modelled balance in the maturity month before that principal is paid, after the cost of completing the towers and all profit and interest payments. Sukuk carry their actual coupons; the bank rate is backed out of reported finance cost.
A15: Instrument | B15: Maturity | C15: Amount | D15: Rate | E15: Cash available | F15: Coverage | G15: Shortfall | H15: Rate source
A16: =INDEX('Cash flow'!$A$94:$A$101,MATCH($B16,'Cash flow'!$B$94:$B$101,0)) -> Secured bank debt — due H2 2026 | B16: =SMALL('Cash flow'!$B$94:$B$101,ROW()-15) -> 46387 | C16: =INDEX('Cash flow'!$C$94:$C$101,MATCH($B16,'Cash flow'!$B$94:$B$101,0)) -> 1031.9725 | D16: =INDEX('Cash flow'!$D$32:$D$39,MATCH($B16,'Cash flow'!$B$94:$B$101,0)) -> 0.097691709 | E16: =INDEX('Cash flow'!$E$94:$E$101,MATCH($B16,'Cash flow'!$B$94:$B$101,0)) -> 843.54181 | F16: =INDEX('Cash flow'!$F$94:$F$101,MATCH($B16,'Cash flow'!$B$94:$B$101,0)) -> 0.81740725 | G16: =INDEX('Cash flow'!$G$94:$G$101,MATCH($B16,'Cash flow'!$B$94:$B$101,0)) -> 188.43069 | H16: =INDEX('Cash flow'!$H$32:$H$39,MATCH($B16,'Cash flow'!$B$94:$B$101,0)) -> derived, section 3b
A17: =INDEX('Cash flow'!$A$94:$A$101,MATCH($B17,'Cash flow'!$B$94:$B$101,0)) -> 9.625% sukuk due 28 Feb 2027 | B17: =SMALL('Cash flow'!$B$94:$B$101,ROW()-15) -> 46446 | C17: =INDEX('Cash flow'!$C$94:$C$101,MATCH($B17,'Cash flow'!$B$94:$B$101,0)) -> 1836.25 | D17: =INDEX('Cash flow'!$D$32:$D$39,MATCH($B17,'Cash flow'!$B$94:$B$101,0)) -> 0.09625 | E17: =INDEX('Cash flow'!$E$94:$E$101,MATCH($B17,'Cash flow'!$B$94:$B$101,0)) -> 1473.7013 | F17: =INDEX('Cash flow'!$F$94:$F$101,MATCH($B17,'Cash flow'!$B$94:$B$101,0)) -> 0.80256025 | G17: =INDEX('Cash flow'!$G$94:$G$101,MATCH($B17,'Cash flow'!$B$94:$B$101,0)) -> 362.54875 | H17: =INDEX('Cash flow'!$H$32:$H$39,MATCH($B17,'Cash flow'!$B$94:$B$101,0)) -> actual coupon, offering circular
A18: =INDEX('Cash flow'!$A$94:$A$101,MATCH($B18,'Cash flow'!$B$94:$B$101,0)) -> Secured bank debt — due H1 2027 | B18: =SMALL('Cash flow'!$B$94:$B$101,ROW()-15) -> 46568 | C18: =INDEX('Cash flow'!$C$94:$C$101,MATCH($B18,'Cash flow'!$B$94:$B$101,0)) -> 690.43 | D18: =INDEX('Cash flow'!$D$32:$D$39,MATCH($B18,'Cash flow'!$B$94:$B$101,0)) -> 0.097691709 | E18: =INDEX('Cash flow'!$E$94:$E$101,MATCH($B18,'Cash flow'!$B$94:$B$101,0)) -> 7244.6114 | F18: =INDEX('Cash flow'!$F$94:$F$101,MATCH($B18,'Cash flow'!$B$94:$B$101,0)) -> 10.492898 | G18: =INDEX('Cash flow'!$G$94:$G$101,MATCH($B18,'Cash flow'!$B$94:$B$101,0)) -> 0 | H18: =INDEX('Cash flow'!$H$32:$H$39,MATCH($B18,'Cash flow'!$B$94:$B$101,0)) -> derived, section 3b
A19: =INDEX('Cash flow'!$A$94:$A$101,MATCH($B19,'Cash flow'!$B$94:$B$101,0)) -> Secured bank debt — due H2 2027 | B19: =SMALL('Cash flow'!$B$94:$B$101,ROW()-15) -> 46752 | C19: =INDEX('Cash flow'!$C$94:$C$101,MATCH($B19,'Cash flow'!$B$94:$B$101,0)) -> 1182.545 | D19: =INDEX('Cash flow'!$D$32:$D$39,MATCH($B19,'Cash flow'!$B$94:$B$101,0)) -> 0.097691709 | E19: =INDEX('Cash flow'!$E$94:$E$101,MATCH($B19,'Cash flow'!$B$94:$B$101,0)) -> 14295.373 | F19: =INDEX('Cash flow'!$F$94:$F$101,MATCH($B19,'Cash flow'!$B$94:$B$101,0)) -> 12.08865 | G19: =INDEX('Cash flow'!$G$94:$G$101,MATCH($B19,'Cash flow'!$B$94:$B$101,0)) -> 0 | H19: =INDEX('Cash flow'!$H$32:$H$39,MATCH($B19,'Cash flow'!$B$94:$B$101,0)) -> derived, section 3b
A20: =INDEX('Cash flow'!$A$94:$A$101,MATCH($B20,'Cash flow'!$B$94:$B$101,0)) -> Secured bank debt — due 2028 | B20: =SMALL('Cash flow'!$B$94:$B$101,ROW()-15) -> 46934 | C20: =INDEX('Cash flow'!$C$94:$C$101,MATCH($B20,'Cash flow'!$B$94:$B$101,0)) -> 1373.515 | D20: =INDEX('Cash flow'!$D$32:$D$39,MATCH($B20,'Cash flow'!$B$94:$B$101,0)) -> 0.097691709 | E20: =INDEX('Cash flow'!$E$94:$E$101,MATCH($B20,'Cash flow'!$B$94:$B$101,0)) -> 14322.187 | F20: =INDEX('Cash flow'!$F$94:$F$101,MATCH($B20,'Cash flow'!$B$94:$B$101,0)) -> 10.427397 | G20: =INDEX('Cash flow'!$G$94:$G$101,MATCH($B20,'Cash flow'!$B$94:$B$101,0)) -> 0 | H20: =INDEX('Cash flow'!$H$32:$H$39,MATCH($B20,'Cash flow'!$B$94:$B$101,0)) -> derived, section 3b
A21: =INDEX('Cash flow'!$A$94:$A$101,MATCH($B21,'Cash flow'!$B$94:$B$101,0)) -> 7.75% green sukuk due 2 Jul 2029 | B21: =SMALL('Cash flow'!$B$94:$B$101,ROW()-15) -> 47301 | C21: =INDEX('Cash flow'!$C$94:$C$101,MATCH($B21,'Cash flow'!$B$94:$B$101,0)) -> 1836.25 | D21: =INDEX('Cash flow'!$D$32:$D$39,MATCH($B21,'Cash flow'!$B$94:$B$101,0)) -> 0.0775 | E21: =INDEX('Cash flow'!$E$94:$E$101,MATCH($B21,'Cash flow'!$B$94:$B$101,0)) -> 13876.29 | F21: =INDEX('Cash flow'!$F$94:$F$101,MATCH($B21,'Cash flow'!$B$94:$B$101,0)) -> 7.5568632 | G21: =INDEX('Cash flow'!$G$94:$G$101,MATCH($B21,'Cash flow'!$B$94:$B$101,0)) -> 0 | H21: =INDEX('Cash flow'!$H$32:$H$39,MATCH($B21,'Cash flow'!$B$94:$B$101,0)) -> actual coupon, offering circular
A22: =INDEX('Cash flow'!$A$94:$A$101,MATCH($B22,'Cash flow'!$B$94:$B$101,0)) -> 8.125% sukuk due 7 Aug 2030 | B22: =SMALL('Cash flow'!$B$94:$B$101,ROW()-15) -> 47702 | C22: =INDEX('Cash flow'!$C$94:$C$101,MATCH($B22,'Cash flow'!$B$94:$B$101,0)) -> 1836.25 | D22: =INDEX('Cash flow'!$D$32:$D$39,MATCH($B22,'Cash flow'!$B$94:$B$101,0)) -> 0.08125 | E22: =INDEX('Cash flow'!$E$94:$E$101,MATCH($B22,'Cash flow'!$B$94:$B$101,0)) -> 11897.477 | F22: =INDEX('Cash flow'!$F$94:$F$101,MATCH($B22,'Cash flow'!$B$94:$B$101,0)) -> 6.4792249 | G22: =INDEX('Cash flow'!$G$94:$G$101,MATCH($B22,'Cash flow'!$B$94:$B$101,0)) -> 0 | H22: =INDEX('Cash flow'!$H$32:$H$39,MATCH($B22,'Cash flow'!$B$94:$B$101,0)) -> actual coupon, offering circular
A23: =INDEX('Cash flow'!$A$94:$A$101,MATCH($B23,'Cash flow'!$B$94:$B$101,0)) -> 8.375% sukuk due 12 Aug 2031 | B23: =SMALL('Cash flow'!$B$94:$B$101,ROW()-15) -> 48072 | C23: =INDEX('Cash flow'!$C$94:$C$101,MATCH($B23,'Cash flow'!$B$94:$B$101,0)) -> 1836.25 | D23: =INDEX('Cash flow'!$D$32:$D$39,MATCH($B23,'Cash flow'!$B$94:$B$101,0)) -> 0.08375 | E23: =INDEX('Cash flow'!$E$94:$E$101,MATCH($B23,'Cash flow'!$B$94:$B$101,0)) -> 9907.4408 | F23: =INDEX('Cash flow'!$F$94:$F$101,MATCH($B23,'Cash flow'!$B$94:$B$101,0)) -> 5.3954749 | G23: =INDEX('Cash flow'!$G$94:$G$101,MATCH($B23,'Cash flow'!$B$94:$B$101,0)) -> 0 | H23: =INDEX('Cash flow'!$H$32:$H$39,MATCH($B23,'Cash flow'!$B$94:$B$101,0)) -> actual coupon, offering circular
A24: Total | C24: =SUM(C16:C23) -> 11623.462 | D24: =IF(C24>0,SUMPRODUCT(C16:C23,D16:D23)/C24,"") -> 0.089474199 | G24: =SUM(G16:G23) -> 550.97944
A26: {=IF(COUNTIF($F$16:$F$23,"<1")=0,"No modelled shortfall on any maturity to 2031","Total shortfall, last affected maturity "&TEXT(MAX(($G$16:$G$23>0)*$B$16:$B$23),"mmm yyyy"))} -> Total shortfall, last affected maturity Feb 2027 | B26: =G24 -> 550.97944 | C26: AED m
A27: Maturities covered, of eight | B27: =COUNTIF($F$16:$F$23,">=1") -> 6 | C27: {=COUNTIF($F$16:$F$23,"<1")&IF(COUNTIF($F$16:$F$23,"<1")=1," not covered, first failing "," not covered, first failing ")&TEXT(MIN(IF($G$16:$G$23>0,$B$16:$B$23)),"mmm yyyy")} -> 2 not covered, first failing Dec 2026
A28: Deepest cash point on the path | B28: ='Cash flow'!$B$11 -> -362.54875 | C28: ="AED m, in "&TEXT('Cash flow'!$B$12,"mmm yyyy") -> AED m, in Feb 2027
A29: Cash at end 2027, once the handovers land | B29: ='Cash flow'!$B$13 -> 13112.828 | C29: ="AED m, after "&TEXT('Cash flow'!$D$89,"0")&" of the 32 live towers complete" -> AED m, after 24 of the 32 live towers complete
A31: THE THREE ASSUMPTIONS THAT EACH REVERSE THIS ON THEIR OWN
A32: Not three combined. Any one of them, moved alone within a range the evidence allows, covers every maturity and removes the shortfall entirely. None is a disclosed figure.
A33: Assumption | B33: Used here | C33: Reverses at | D33: Where it comes from, and what would settle it
A34: Register progress readings | B34: ='Cash flow'!$B$127&" of 32 towers on the 15 Jun read" -> 14 of 32 towers on the 15 Jun read | C34: +15 points | D34: The June dump showed Binghatti Apex at 45% certified two months after it had completed. Understated progress makes this model too pessimistic. A refreshed extract covering all 68 projects settles it and costs nothing but time.
A35: Cost to complete | B35: =TEXT(Scenarios!$F$15,"0.0%")&" of contracted value" -> 55.0% of contracted value | C35: =TEXT('Break-even'!$B$13,"0.0%") -> 52.5% | D35: Inferred from the reported gross margin of 44 to 45 per cent, not disclosed. Any real cost-to-complete data from the issuer replaces it.
A36: Cash received since 30 June | B36: ="AED "&TEXT(Dashboard!$D$5,"#,##0")&" m, register-supported" -> AED 293 m, register-supported | C36: AED 1,800 m as claimed | D36: The company's own figure, unsourced and untraceable to any filing. The register confirms one handover, not three. An investor relations enquiry settles it.
A38: HOW TO READ THIS
A39: {=_xlfn.LET(_xlpm.lastd,MAX(('Cash flow'!$G$94:$G$101>0)*'Cash flow'!$B$94:$B$101),"The shortfall sits on the two nearest maturities. Everything after "&TEXT(_xlpm.lastd,"mmm yyyy")&" is covered on this basis, because "&TEXT('Cash flow'!$D$89,"0")&" of the 32 live towers are modelled to complete during 2027, releasing AED "&TEXT('Cash flow'!$D$77,"#,##0")&_xlfn._LONGTEXT(" m of escrow in that year. The 2029, 2030 and 2031 sukuk are then met from cash accumulated in 2027 and 2028 rather than from new escrow, since release is nil from 2029 once the present pipeline is finished. So the back end depends on that handover wave a","rriving on something close to schedule, and the front end depends on the three assumptions above. Neither dependency is resolved by this workbook."))} -> The shortfall sits on the two nearest maturities. Everything after Feb 2027 is covered on this basis, because 24 of the 32 live towers are modelled to complete during 2027, releasing AED 27,419 m of escrow in that year. The 2029, 2030 and 2031 sukuk are then met from cash accumulated in 2027 and 2028 rather than from new escrow, since release is nil from 2029 once the present pipeline is finished. So the back end depends on that handover wave arriving on something close to schedule, and the front end depends on the three assumptions above. Neither dependency is resolved by this workbook.
A40: ="For contrast, the Dashboard's escrow headroom measure reads "&TEXT(Dashboard!$F$17,"0.00")&"x on the February 2027 sukuk. That measure credits the whole escrow release against debt and deducts neither the cost of building the towers nor any profit payments. It is a diagnostic, not the cash test; the table above is what binds." -> For contrast, the Dashboard's escrow headroom measure reads 3.79x on the February 2027 sukuk. That measure credits the whole escrow release against debt and deducts neither the cost of building the towers nor any profit payments. It is a diagnostic, not the cash test; the table above is what binds.
A50: CONTENTS
A51: How to use | B51: Start here. What you may change, what to read, how to interpret coverage.
A52: Model map | B52: How the sheets connect and the arithmetic step by step.
A53: Dashboard | B53: Escrow release against each maturity date, all four scenarios, with charts.
A54: Break-even | B54: How far handovers must slip, or cancellations rise, before coverage fails.
A55: Cash flow | B55: The full maturity stack to 2031 after construction cost and debt service. Read this one.
A56: Handover check | B56: Tests the AED 1.8 bn handover claim against the DLD register. Sets the figure in Dashboard D5.
A57: Scenarios | B57: The only inputs the model reads. Four columns; pick one in cell B3.
A58: Simulator | B58: The escrow engine. One row per live project, 28 months across.
A59: Debt | B59: Every instrument, the maturity wall, and the bank covenants.
A60: Financials | B60: Standardised statements and the ratios computed from them.
A61: Bonds | B61: Sukuk pricing, yield and spread at indicative bank quotes.
A62: Projects | B62: The full Dubai Land Department register extract, all 68 projects.
... A64: Change log | B64: Every change made to this workbook, why, and how to reverse it.
A66: WHAT THIS MODEL IS — AND IS NOT
A67: It is | B67: Arithmetic on the Dubai Land Department project register and the issuer's own filed figures and disclosed payment terms. Every number is a register fact, a filed figure, or a formula you can trace to one of those.
A68: It is not | B68: A forecast, a rating, a recommendation, or a view on the credit. DPI expresses no opinion on Binghatti Holding or its securities.
A69: Read the table above as | B69: The cash test, and the binding answer. The Dashboard's coverage ratio is a headroom indicator only: it credits the whole escrow release against debt and deducts neither construction cost nor debt service.
A71: THE SIX CAVEATS THAT MATTER MOST
A72: 1 | B72: ="The public register is stale for "&'Cash flow'!$B$127&_xlfn._LONGTEXT(" of the 32 live towers, which still carry the 15 June reading. That dump is demonstrably wrong: it showed Binghatti Apex at 45% certified two months after Apex had completed. Because cost to complete is charged on the progress still to be earned, understa","ted progress makes this model too pessimistic. Adding fifteen certified points to those fourteen towers is enough on its own to cover the February 2027 sukuk and remove the whole shortfall. See Cash flow section 10. This is the largest single uncertainty ","here.") -> The public register is stale for 14 of the 32 live towers, which still carry the 15 June reading. That dump is demonstrably wrong: it showed Binghatti Apex at 45% certified two months after Apex had completed. Because cost to complete is charged on the progress still to be earned, understated progress makes this model too pessimistic. Adding fifteen certified points to those fourteen towers is enough on its own to cover the February 2027 sukuk and remove the whole shortfall. See Cash flow section 10. This is the largest single uncertainty here.
A73: 2 | B73: ="Cost to complete is derived, not disclosed. At "&TEXT(Scenarios!$F$15,"0%")&" of contracted value it is inferred from the reported gross margin, which runs 44 to 45 per cent. The shortfall moves directly with it: this is the single input most worth replacing with real cost-to-complete data. Set it on Scenarios row 15." -> Cost to complete is derived, not disclosed. At 55% of contracted value it is inferred from the reported gross margin, which runs 44 to 45 per cent. The shortfall moves directly with it: this is the single input most worth replacing with real cost-to-complete data. Set it on Scenarios row 15.
A74: 3 | B74: The answer is driven by handover timing. A tower at 30% certified whose registered completion date has already passed will not hand over before February whatever the plan says, and 24 of the 32 live towers are modelled to complete during 2027. The delay assumption is where this model lives or dies. See Break-even.
A75: 4 | B75: The payment-plan shape is an assumption, not a disclosure. The issuer discloses roughly 70% collected during construction; the 10 / 60 / 30 booking / progress / handover split used here is a reasonable reading of that, not a filed term. Change it on Scenarios if you know the actual plans.
A76: 5 | B76: ="The bank rate is backed out, not quoted. The four sukuk carry their actual coupons from the offering circulars. The four bank tranches have no disclosed rate, so "&TEXT('Cash flow'!$B$51,"0.00%")&" is inferred from reported finance cost less sukuk profit. It sits above EIBOR plus the quoted margin because reported finance cost also carries fees and issue-cost amortisation; treat it as an upper bound and switch bases on Cash flow row 22." -> The bank rate is backed out, not quoted. The four sukuk carry their actual coupons from the offering circulars. The four bank tranches have no disclosed rate, so 9.77% is inferred from reported finance cost less sukuk profit. It sits above EIBOR plus the quoted margin because reported finance cost also carries fees and issue-cost amortisation; treat it as an upper bound and switch bases on Cash flow row 22.
A77: 6 | B77: No new presales are assumed after the register read date. Escrow release is nil from 2029 because the present pipeline is finished, so the 2029, 2030 and 2031 sukuk are met entirely from cash accumulated in 2027 and 2028. Real developers keep launching, so the back end is conservative on this point rather than aggressive.
A79: PRIMARY SOURCES
A80: Project data | B80: Dubai Land Department project register and transactions register. Certified progress and completion dates read 15 Jun 2026, updated by the 30 Aug 2026 extract where available. Units and sales to the register read date.
A81: Financials | B81: Binghatti Holding interim consolidated FS 30 June 2026; FY2025 audited FS (LSE RNS 9968Q); H1 2026 results presentation.
A82: Debt and pricing | B82: Issuer filings and presentations; DIB indicative sukuk price list (4 Sep 2026). Bank quotes are indicative levels, not traded prices.
A83: Ratings | B83: Moody's Ba3, on review for downgrade (11 Aug 2026). Fitch BB-, Rating Watch Negative (Mar 2026). S&P not rated.
A84: Full list and links | B84: Ratings & sources tab, including four gaps we could not close.
A86: KNOWN DATA GAPS IN THIS BUILD
A87: • Project 4043 (بالم 01 من بن غاطي) carries zero units, zero sales and zero ticket on the register, so it contributes nothing to modelled release. Coverage is understated to that extent.
A88: • FY2024 finance cost is not in the data, so FY2024 interest cover reads "n/a" on the Financials sheet.
A89: • Debt falling due within twelve months is not broken out for FY2024 or FY2025, so that liquidity ratio is blank for both years.
A90: ="• The AED 1.8 bn said to have been received from three handovers after 30 June 2026 is unsourced. The Handover check tab tests it against the register and supports about AED "&TEXT('Handover check'!$B$28,"#,##0")&" m, which is what Dashboard D5 now carries. Taking the full AED 1,800 m at face value would remove the shortfall entirely, so it remains the most consequential unverified figure here." -> • The AED 1.8 bn said to have been received from three handovers after 30 June 2026 is unsourced. The Handover check tab tests it against the register and supports about AED 293 m, which is what Dashboard D5 now carries. Taking the full AED 1,800 m at face value would remove the shortfall entirely, so it remains the most consequential unverified figure here.
A91: • Sukuk offering circulars not reviewed: call, change-of-control and cross-default terms are unverified.
A93: This workbook is provided for information only. It is not investment advice, not an offer, and not a recommendation. Figures derived from a public register are subject to that register's own accuracy and update lag. Recipients should form their own view and verify every figure against primary sources before acting.

Sheet How to use
A1: HOW TO USE THIS MODEL
A2: Five minutes to the answer, then everything you may change and how to read the output.
A4: 1. THE SIX-MINUTE PATH
A5: Step | B5: Where | C5: What to do
A6: 1 | B6: Cover, rows 15 to 24 | C6: Read the maturity table. Eight instruments to 2031, ordered by date, with coverage and shortfall on each. Anything below 1.00x cannot be met from modelled cash. This is the answer; everything else explains it.
A7: 2 | B7: Cash flow, rows 64 to 77 | C7: Read the annual summary. Escrow release, retention, construction cost, debt service and closing cash by year to 2031. The lowest-cash row shows the trough inside each year, which the year-end balance hides.
A8: 3 | B8: Break-even | C8: Read how much handover delay or cancellation it takes to push coverage to 1.0x. This is the number to argue about.
A9: 4 | B9: Dashboard, rows 16 to 28 | C9: Read escrow coverage by maturity date across all four scenarios. Treat it as headroom before construction cost and debt service, not as the cash test; the caveat under the verdict band says so.
A10: 5 | B10: Dashboard, rows 66 to 76 | C10: Look at the ten towers doing the most work. Check certified % against registered date: a tower at 30% with its date already passed is not handing over in February.
A11: 6 | B11: Scenarios, cell B3 | C11: Type 1, 2, 3 or 4 to switch the active scenario. Everything on the Simulator, Dashboard and Cash flow follows that one cell. Break-even deliberately does not.
A12: 2. EVERY CELL YOU MAY CHANGE
A13: Blue text means an input. Black means a formula. Green means it is pulled from another sheet. If a cell is not listed here, changing it will break something.
A14: Sheet | B14: Cell | C14: Input | D14: Current | E14: Notes
A15: Scenarios | B15: B3 | C15: Active scenario, 1 to 4 | D15: =Scenarios!$B$3 -> 1 | E15: The master switch. 1 Base, 2 Delayed handovers, 3 Cancellation spike, 4 Price cut.
A16: Scenarios | B16: B5:E19 | C16: The fourteen assumptions, four columns | D16: — | E16: Overwrite any column with your own view. Column F resolves whichever is active; do not edit column F. Rows 15 to 19 are the newer inputs: cost to complete, EIBOR, bank margin, the refinancing toggle and the refinancing spread.
A17: Dashboard | B17: D5 | C17: Cash received since balance sheet date | D17: =Dashboard!$D$5 -> 292.5759 | E17: Defaults to zero. Fills the gap between the 30 Jun 2026 opening cash and the 10 Sep 2026 register date, which neither figure covers. The AED 1.8 bn attributed to three handovers is UNSOURCED in this workbook — see the gaps list on Ratings & sources — and entering it removes the entire modelled shortfall. Verify before use, and remember gross receipts are not all free cash.
A18: Dashboard | B18: B97 | C18: Dubai registered sales, all developers, 12m | D18: =Dashboard!$B$97 -> 187123 | E18: Denominator for the market-share calibration check only. Does not affect coverage or the cash flow.
A19: Simulator | B19: C3 | C19: Register read date | D19: =Simulator!$C$3 -> 46275 | E19: Month 1 of the monthly grids is the month after this date. Changing it re-dates the whole projection, on both the Simulator and the Cash flow sheet.
A20: Simulator | B20: D8:I39 | C20: Per-project register facts | D20: — | E20: Units, sold units, average ticket, certified %, registered completion date. Change these if you have a better read than the register.
A21: Debt | B21: Instrument rows 6 to 13 | C21: Amounts, coupons and maturity dates | D21: — | E21: Sukuk coupons are real and are used directly. Bank rows carry no coupon, so they take the derived rate. Adding a facility here flows through to the Dashboard, the Cash flow schedule and the coverage table.
A22: Break-even | B22: B28:B34, C27:I27 | C22: Grid axis ranges | D22: — | E22: Widen or narrow the delay and cancellation axes without touching the arithmetic. The working block below the grid re-derives itself.
A23: Cash flow | B23: B22 | C23: Bank rate basis | D23: ='Cash flow'!$B$22 -> Implied | E23: Type Implied to use the rate backed out of reported finance cost, or Quoted to use EIBOR plus the margin from the financing notes. The derivation is visible in section 3b of that sheet.
A24: Cash flow | B24: B25 and B26 | C24: Retention lag and horizon | D24: — | E24: Months after completion until RERA retention releases, and how many months the engine runs. The horizon is 64 so the 2031 sukuk falls inside it; shortening it will cut maturities off the end of the coverage table.
A26: 3. THE FOURTEEN ASSUMPTIONS, AND WHICH ONES ACTUALLY MOVE THE ANSWER
A27: Assumption | B27: Base | C27: Sensitivity | D27: Why it matters
A28: =Scenarios!$A$5 -> Handover delay added to every registered completion date (months) | B28: =Scenarios!$B$5 -> 0 | C28: High | D28: The single most powerful input. Every month of delay pushes certified progress, and therefore released cash, to the right. Switching to the Delayed scenario cuts the February release by roughly 45%.
A29: =Scenarios!$A$6 -> Months to completion for projects already past their registered date | B29: =Scenarios!$B$6 -> 6 | C29: High | D29: Applies to towers whose registered date has already passed, so the register gives no usable date. Several large towers sit here.
A30: =Scenarios!$A$7 -> Months to completion for projects with no registered date | B30: =Scenarios!$B$7 -> 24 | C30: Low | D30: Only four active towers carry no date at all, and at 24 months out they contribute almost nothing before February 2027.
A31: =Scenarios!$A$8 -> Cancellation rate — share of contracted value that is never collected | B31: =Scenarios!$B$8 -> 0 | C31: Medium | D31: Scales the remaining collections on every project linearly. Material, but less violent than delay because it does not change timing.
A32: =Scenarios!$A$9 -> Sell-through of unsold units before completion | B32: =Scenarios!$B$9 -> 0.6 | C32: Low | D32: Only 1,429 of 23,645 registered units are unsold, so future sales are a rounding item over this horizon.
A33: =Scenarios!$A$10 -> Price change on those future sales | B33: =Scenarios!$B$10 -> 0 | C33: Low | D33: Applies only to those same 1,429 unsold units.
A34: =Scenarios!$A$11 -> Share of price collected at sale (booking) | B34: =Scenarios!$B$11 -> 0.1 | C34: Medium | D34: Booking cash is already collected on sold units, so a higher booking share front-loads release. This is an assumption, not a filed term.
A35: =Scenarios!$A$12 -> Share of price collected at handover | B35: =Scenarios!$B$12 -> 0.3 | C35: High | D35: The handover instalment only lands at completion. A large handover share means cash arrives after February for any tower not finishing first.
A36: =Scenarios!$A$13 -> RERA escrow retention held until one year after completion | B36: =Scenarios!$B$13 -> 0.05 | C36: Low | D36: A flat 5% haircut on everything released.
A37: =Scenarios!$A$14 -> Maximum certified progress per month (percentage points) | B37: =Scenarios!$B$14 -> 8 | C37: Medium | D37: Binds on towers the model would otherwise certify implausibly fast. Lowering it slows release on the low-progress towers.
A38: Cost to complete, share of contracted value | B38: =Scenarios!$B$15 -> 0.55 | C38: High | D38: New, and now one of the two most powerful inputs. Escrow release is gross; this is what the towers cost to finish, deducted as certified progress is earned. The whole near-term shortfall moves with it. Derived from the reported gross margin, not disclosed.
A39: 3M EIBOR assumption for bank debt | B39: =Scenarios!$B$16 -> 0.042 | C39: Low | D39: Only used when the bank rate basis on the Cash flow sheet is set to Quoted. On the default Implied basis the bank rate is backed out of reported finance cost and this input is ignored.
A40: Bank margin over EIBOR | B40: =Scenarios!$B$17 -> 0.0238 | C40: Low | D40: As above: the quoted-basis alternative only. Midpoint of the 2.00 to 2.75 per cent range in the financing notes.
A41: Refinance sukuk at maturity, and the refinancing spread | B41: =Scenarios!$B$18 -> No | C41: High | D41: No is the hard test: every maturity must be met from cash. Switching to Yes rolls each sukuk instead of repaying it, which lifts February 2027 coverage above 1.0x and leaves only the December 2026 bank maturity short. The spread on the row below prices the replacement.
A43: 4. HOW TO READ THE TWO COVERAGE MEASURES
A44: There are two, they answer different questions, and they disagree. Measure A, on the Dashboard: ( cash outside escrow + modelled escrow release by the date ) ÷ debt falling due by that date. Measure B, on the Cash flow sheet and the Cover: modelled cash in the maturity month, after construction cost and all debt service ÷ the principal then due.
A46: Measure A, headroom | B46: ="Reads "&TEXT(Dashboard!$F$17,"0.00")&_xlfn._LONGTEXT("x on the February 2027 sukuk. It deducts neither the cost of building the towers nor any profit or interest payment, so it overstates what is available. Useful for ranking scenarios against each other and for seeing how much slack the escrow pool carries."," Not a repayment test. It lives in section 1 of the Dashboard.") -> Reads 3.79x on the February 2027 sukuk. It deducts neither the cost of building the towers nor any profit or interest payment, so it overstates what is available. Useful for ranking scenarios against each other and for seeing how much slack the escrow pool carries. Not a repayment test. It lives in section 1 of the Dashboard.
A47: Measure B, the cash test | B47: ="Reads "&TEXT('Cash flow'!$F$94,"0.00")&"x on the same sukuk, and below 1.00x on the December 2026 bank maturity too. This is the binding number. It is what the Cover table and the maturity coverage table both report." -> Reads 0.80x on the same sukuk, and below 1.00x on the December 2026 bank maturity too. This is the binding number. It is what the Cover table and the maturity coverage table both report.
A48: Why they differ | B48: ="Escrow release to February 2027 is AED "&TEXT(Dashboard!$E$17,"#,##0")&" m gross. Against that sit construction cost and roughly AED "&TEXT('Cash flow'!$F$40,"#,##0")&" m a year of debt service. Measure A ignores both; measure B does not. Escrow money is released to build, so measure B is the one to take to a credit committee." -> Escrow release to February 2027 is AED 10,189 m gross. Against that sit construction cost and roughly AED 1,040 m a year of debt service. Measure A ignores both; measure B does not. Escrow money is released to build, so measure B is the one to take to a credit committee.
A49: What both exclude | B49: New borrowing, asset sales, shareholder support, land sales, the reported multibillion-dollar pact, and any presales launched after the register read date. All of these could help; none are modelled.
A51: 5. THINGS TO CHECK BEFORE YOU TRUST A NUMBER
A52: • Certified % against registered date, tower by tower. This is the assumption the whole model rests on, and it is observable.
A53: • Whether the ten towers the issuer itself names as funding the February maturity are the same ten the model picks out on Dashboard rows 66 to 76.
A54: • The payment-plan split on Scenarios rows 11 and 12 against actual sale-and-purchase agreements, if you can see them.
A55: • The cost-to-complete ratio on Scenarios row 15 against any real construction-cost data you hold. It is inferred from the gross margin and it drives the entire near-term shortfall.
A56: • The 24 towers the model has completing during 2027. That single wave funds every maturity from mid-2027 onward, so its timing is the main concentration risk in the credit.

Sheet Model map
A1: HOW THE WORKBOOK HANGS TOGETHER
A2: Data flows in one direction. There are no circular references and no macros.
A4: 1. THE CHAIN
A5: Projects → Simulator → Dashboard → Cash flow → Cover with Scenarios feeding the Simulator and the Cash flow sheet, Debt and Financials supplying the liability and cash side, and Break-even stress-testing the whole thing independently of the active scenario
A7: Stage | B7: Sheet | C7: What it holds | D7: Feeds
A8: Source data | B8: Projects | C8: The full Dubai Land Department register extract: 68 projects, status, units, sold units, sales value, certified progress, completion dates, resale history. Row 73 totals it. | D8: Simulator (32 live projects), Dashboard section 4
A9: Assumptions | B9: Scenarios | C9: Fourteen assumptions in four named columns. Cell B3 selects which column is active; column F resolves it. Rows 15 to 19 are the cost, rate and refinancing inputs added for the cash flow build. | D9: Every formula on the Simulator and the Cash flow sheet
A10: Engine | B10: Simulator | C10: One row per live project. Columns E–I are register facts; J–U derive contracted value, collections and release to date; V–AW run 28 monthly columns; AY–BZ recompute all four scenarios at three checkpoint dates; CA is a rank key. | D10: Dashboard, Break-even
A11: Liabilities | B11: Debt | C11: Eight instruments with amounts and maturity dates, plus the maturity wall by year and covenant headroom. | D11: Dashboard (debt due by each date)
A12: Balance sheet | B12: Financials | C12: FY2024, FY2025 and H1 2026 filed figures, and leverage computed three ways depending on how much escrow you count as cash. | D12: Dashboard (free cash), Debt (covenant tests)
A13: Market | B13: Bonds | C13: Sukuk price, yield and spread at indicative bank quotes. | D13: Reference only — nothing downstream depends on it
A14: Headroom | B14: Dashboard | C14: Escrow coverage by maturity date across all four scenarios, the monthly release and running-cash path, the towers doing the most work, register-level calibration checks, and three charts. Coverage here is before construction cost and debt service. | D14: Cash flow (opening cash), Break-even (tie-out check)
A15: Cash test | B15: Cash flow | C15: A second escrow engine running 64 months instead of 28, so the 2029, 2030 and 2031 sukuk fall inside the horizon. Adds the two things the Dashboard leaves out: cost to complete, and debt service at each instrument's own rate. Section 3b backs the bank rate out of reported finance cost. Section 6 is the coverage table for all eight maturities. | D15: Cover (the maturity table and every headline figure on it)
A16: Stress | B16: Break-even | C16: Recomputes February 2027 coverage across a grid of handover delay against cancellation rate, independently of the active scenario. | D16: Cover (the 1.0x delay threshold)
A17: Provenance | B17: Ratings & sources | C17: Rating actions with agency rationale, filings with links, and four gaps we could not close. | D17: Nothing — documentation only
A19: 2. THE ARITHMETIC, STEP BY STEP
A20: Steps 1 to 8 are the escrow engine on the Simulator: one column each, applied to all 32 live projects. Steps 9 to 14 are the cash test on the Cash flow sheet, which extends the same arithmetic to 64 months and then deducts what the Dashboard leaves out. The figures in the fourth column are live.
A21: Step
A22: Size the contract | B22: J | C22: sold units × average registered ticket | D22: =Simulator!$J$40 -> 37362.292 | E22: Average ticket is registered off-plan sales value divided by number of sales. Resales of the same unit are not separated out.
A23: Adjust for cancellations and future sales | B23: P | C23: J × (1 − cancellation) + unsold units × ticket × sell-through × (1 + price change) | D23: =Simulator!$P$40 -> 40988.809 | E23: Higher than J on the Base scenario because 1,429 unsold units are credited at a 60% sell-through and no cancellations.
A24: Apply the payment plan | B24: U | C24: J × [ booking% + (1 − booking% − handover%) × certified% ] | D24: =Simulator!$U$40 -> 10645.046 | E24: Collected from buyers to date. Booking cash is in regardless of progress; the middle slice tracks certified construction; the handover slice only lands at completion.
A25: Convert collections to released cash | B25: Q | C25: U × min(1, certified% ) × (1 − retention) | D25: =Simulator!$Q$40 -> 4153.2762 | E25: This is the heart of the model. Escrow does not hand over what buyers paid: RERA releases funds in step with certified progress, less a 5% retention. Multiplying by progress a second time is why collections of AED 10.6 bn have released only AED 4.2 bn — and why roughly AED 10.2 bn is still sitting in escrow.
A26: Date the completion | B26: M | C26: registered date + delay; if the date has passed, today + 6 months; if there is no date, today + 24 months | D26: — | E26: A registered date in the past tells you nothing, so the model substitutes a fixed runway. Four active towers carry no date at all.
A27: Derive the build pace | B27: O | C27: min( cap, (100 − certified%) ÷ months to completion ) | D27: — | E27: Percentage points of certification per month. The cap stops the model certifying a tower faster than it could physically be built.
A28: Run it forward 28 months | B28: V:AW | C28: re-run steps 3 and 4 at certified% + pace × month, then subtract release to date; floored at zero | D28: =Simulator!$T$40 -> 34786.092 | E28: Oct 2026 to Jan 2029. Row 40 totals across projects, row 41 differences it into a monthly figure. The total shown here is cumulative release by Dec 2028.
A29: Snapshot the checkpoints | B29: R, S, T | C29: months 5, 15 and 27 of the grid | D29: =Simulator!$R$40 -> 10188.657 | E29: Feb 2027, Dec 2027, Dec 2028. The figure shown is the February 2027 release — the number the coverage ratio turns on.
A30: Test headroom | B30: Dashboard F17 | C30: ( free cash + release by the date ) ÷ debt due by the date | D30: =Dashboard!$F$17 -> 3.7916279 | E30: Measure A. Above 1.0x means modelled sources exceed the debt due on these assumptions. It deducts no construction cost and no debt service, so it is a headroom indicator, not a repayment test.
A31: Extend the horizon | B31: Cash flow C57:BN59 | C31: re-run the release arithmetic for 64 months instead of 28 | D31: ='Cash flow'!$B$104 -> 0 | E31: Oct 2026 to Jan 2032, so the 2029, 2030 and 2031 sukuk fall inside the model. The figure shown is the tie-out check: at month 28 this engine and the Simulator agree to zero.
A32: Recover the retention | B32: Cash flow row 61 | C32: retention × effective contracted value, credited 12 months after each tower completes | D32: =SUM('Cash flow'!$C$62:$BN$62) -> 2049.4404 | E32: The Simulator writes this off because it releases beyond its 28-month horizon. Over 64 months most of it comes back.
A33: Deduct the cost of building | B33: Cash flow row 63 | C33: effective contracted value × cost ratio × ( certified% now − certified% then ) | D33: =SUM('Cash flow'!$C$64:$BN$64) -> 15555.128 | E33: Incurred in step with certified progress, because that is what escrow releases against. Past cost is sunk and is not charged again. This is the deduction that reverses the near-term answer.
A34: Deduct debt service | B34: Cash flow rows 65 to 68 | C34: sukuk profit at actual coupons + bank interest at the derived rate + principal at each maturity | D34: ='Cash flow'!$F$40 -> 1040 | E34: The figure shown is annual profit and interest, which ties exactly to the finance cost the company reported. Principal is repaid gross, with refinancing proceeds shown separately when the toggle is on.
A35: Test the cash | B35: Cash flow F94:F101 | C35: modelled cash in the maturity month, before that principal is paid ÷ the principal then due | D35: =SUM('Cash flow'!$G$94:$G$101) -> 550.97944 | E35: Measure B, and the binding answer. The figure shown is the total modelled shortfall in AED m, all of it falling before March 2027. This is what the Cover reports.
A37: 3. CONVENTIONS
A38: Blue text | B38: An input. Yours to change.
A39: Black text | B39: A formula calculated on the same sheet.
A40: Green text | B40: Pulled from another sheet in this workbook.
A41: Yellow fill | B41: A key assumption that deserves your attention.
A42: Orange fill | B42: A caveat or a threshold breach.
A43: Grouped columns | B43: Simulator columns AY to BZ carry the four-scenario engine. They are grouped, not hidden: use the plus and minus toggle above the column letters.
A44: Units | B44: AED millions throughout, except average ticket (AED) and certified progress (percentage points, 0–100 not 0–1).
A45: Dates | B45: Real Excel dates, displayed dd mmm yyyy. The register read date on Simulator C3 anchors everything.
A47: 4. WHAT DEPENDS ON WHAT — IF YOU CHANGE ONE THING
A48: If you change | B48: These recalculate
A49: Scenarios B3 (active scenario) | B49: Simulator columns J through AW and CA, the Cash flow monthly engine and its coverage table, the Cover maturity table, and every Dashboard section except section 1 rows 17 to 28, which always show all four scenarios regardless. Break-even deliberately does not move.
A50: Any of the fourteen assumptions | B50: The same, plus the matching scenario block on Simulator AY to BZ and the Dashboard's all-scenario table. Cost to complete, the rate inputs and the refinancing toggle affect the Cash flow sheet and the Cover but not the Simulator or the Dashboard.
A51: A per-project register fact | B51: That project's whole row, the totals on Simulator row 40, all four scenario blocks, every Dashboard figure, the whole Cash flow engine and coverage table, the Cover, and the Break-even grid.
A52: Simulator C3 (read date) | B52: The month headers on both monthly grids, every projected completion date, the retention release timing, and therefore the entire projection on the Simulator and the Cash flow sheet.
A53: A Debt instrument, rate or date | B53: Debt due by each checkpoint, all coverage ratios, the monthly debt column, the Cash flow debt service schedule and both coverage measures, the Cover maturity table, and the Break-even grid.
A54: Dashboard D5 (cash received) | B54: The free-cash side of every coverage ratio, the Dashboard running-cash path, and the opening cash balance the Cash flow sheet starts from, which shifts every closing balance and every coverage figure on the Cover.
A55: Break-even axis ranges | B55: The Break-even grid and its three readouts. The Cover's 1.0x delay threshold reads from those readouts, so it moves too.
A56: Cash flow B22 (bank rate basis) | B56: The four bank tranche rates, all debt service, both the annual summary and the coverage table, and every headline figure on the Cover. Nothing on the Simulator, Dashboard or Break-even changes.

Sheet Dashboard
A1: Binghatti Holding — liquidity against maturities, from the register
A2: Can the escrow release from towers under construction, plus the cash the company holds outside escrow, meet the debt falling due? Every number below is a register fact, a filed figure, or arithmetic on the scenario inputs. DPI expresses no view.
A3: As of | B3: =Simulator!$C$3 -> 46275
A4: Active scenario | B4: =Scenarios!$C$3 -> Base | C4: change on the Scenarios sheet, cell B3
A5: Cash outside escrow, AED m (30 Jun 2026) | B5: =Financials!D19 -> 394 | C5: plus received since, AED m: | D5: ='Handover check'!B28 -> 292.5759 | E5: =_xlfn._LONGTEXT("Cash received after the 30 Jun 2026 balance sheet date, which the opening balance cannot see. The AED 1.8 bn attributed to three handovers is unsourced. Tested against the register on the Handover check tab: one confirmed handover, Binghatti Pinnacle, sup","porting AED ")&TEXT('Handover check'!$B$28,"#,##0")&" m. That figure is entered here. Entering 1,800 instead would remove the shortfall entirely." -> Cash received after the 30 Jun 2026 balance sheet date, which the opening balance cannot see. The AED 1.8 bn attributed to three handovers is unsourced. Tested against the register on the Handover check tab: one confirmed handover, Binghatti Pinnacle, supporting AED 293 m. That figure is entered here. Entering 1,800 instead would remove the shortfall entirely.
A6: Legend | B6: blue = input you can change | D6: green = pulled from another sheet
A8: THE VERDICT — CAN EACH MATURITY BE MET FROM CASH?
A9: {=_xlfn.LET(_xlpm.n,$E$12,_xlpm.g,$F$12,_xlpm.c,$C$12,_xlpm.lastd,MAX(('Cash flow'!$G$94:$G$101>0)*'Cash flow'!$B$94:$B$101),IF(_xlpm.n=0,"On the "&$G$12&" case every maturity to 2031 is met from modelled cash, the 9.625% sukuk due 28 February 2027 covered "&TEXT(_xlpm.c,"0.00")&" times over. Conditional on the three assumptions listed on the Cover.","On the "&$G$12&" case and the register as it stands, the 9.625% sukuk due 28 February 2027 is not met from modelled cash: "&TEXT(_xlpm.c,"0.00")&"x, short AED "&TEXT($D$12,"#,##0")&" m. "&_xlpm.n&" of the eight maturities to 2031 fall short, AED "&TEXT(_xlpm.g,"#,##0")&" m in total, the last maturing "&TEXT(_xlpm.lastd,"mmm yyyy")&". Treat this as conditional: three derived assumptions, listed on the Cover, each reverse it on their own."))} -> On the Base case and the register as it stands, the 9.625% sukuk due 28 February 2027 is not met from modelled cash: 0.80x, short AED 363 m. 2 of the eight maturities to 2031 fall short, AED 551 m in total, the last maturing Feb 2027. Treat this as conditional: three derived assumptions, listed on the Cover, each reverse it on their own.
A11: Principal due 28 Feb 2027 | B11: Cash available then | C11: Coverage, cash test | D11: Shortfall on that sukuk | E11: Maturities short, of eight | F11: Total shortfall to 2031 | G11: Active scenario
A12: ='Cash flow'!$C$94 -> 1836.25 | B12: ='Cash flow'!$E$94 -> 1473.7013 | C12: ='Cash flow'!$F$94 -> 0.80256025 | D12: ='Cash flow'!$G$94 -> 362.54875 | E12: =COUNTIF('Cash flow'!$F$94:$F$101,"<1") -> 2 | F12: =SUM('Cash flow'!$G$94:$G$101) -> 550.97944 | G12: =$B$4 -> Base
A13: ="Section 1 below is a different and weaker measure: escrow release against debt, before construction cost and debt service. On that basis the February sukuk reads "&TEXT($F$17,"0.00")&"x. It is a headroom diagnostic, useful for ranking scenarios, and it is not the repayment test. The cash test above and on the Cover is what binds." -> Section 1 below is a different and weaker measure: escrow release against debt, before construction cost and debt service. On that basis the February sukuk reads 3.79x. It is a headroom diagnostic, useful for ranking scenarios, and it is not the repayment test. The cash test above and on the Cover is what binds. | I13: CHART DATA — formulas only, no new inputs
A15: 1. ESCROW HEADROOM BY MATURITY DATE, ALL FOUR SCENARIOS — BEFORE CONSTRUCTION COST AND DEBT SERVICE | I15: Scenario | J15: Coverage at 28 Feb 2027
A16: Date | B16: Debt due by then (AED m) | C16: Cash outside escrow + received | D16: Scenario | E16: Modelled escrow release by then | F16: Headroom (x) | G16: Gap on this measure (AED m) | I16: =$D$17 -> Base | J16: =$F$17 -> 3.7916279
A17: 28 Feb 2027 — 9.625% sukuk | B17: =SUMIFS(Debt!$E$6:$E$13,Debt!$H$6:$H$13,"<="&DATE(2027,2,28)) -> 2868.2225 | C17: =$B$5+$D$5 -> 686.5759 | D17: Base | E17: =Simulator!BC40 -> 10188.657 | F17: =IF(B17>0,(C17+E17)/B17,"") -> 3.7916279 | G17: =MAX(0,B17-C17-E17) -> 0 | I17: =$D$18 -> Delayed handovers | J17: =$F$18 -> 2.1844842
B18: =SUMIFS(Debt!$E$6:$E$13,Debt!$H$6:$H$13,"<="&DATE(2027,2,28)) -> 2868.2225 | C18: =$B$5+$D$5 -> 686.5759 | D18: Delayed handovers | E18: =Simulator!BJ40 -> 5579.0108 | F18: =IF(B18>0,(C18+E18)/B18,"") -> 2.1844842 | G18: =MAX(0,B18-C18-E18) -> 0 | I18: =$D$19 -> Cancellation spike | J18: =$F$19 -> 2.9663109
B19: =SUMIFS(Debt!$E$6:$E$13,Debt!$H$6:$H$13,"<="&DATE(2027,2,28)) -> 2868.2225 | C19: =$B$5+$D$5 -> 686.5759 | D19: Cancellation spike | E19: =Simulator!BQ40 -> 7821.4639 | F19: =IF(B19>0,(C19+E19)/B19,"") -> 2.9663109 | G19: =MAX(0,B19-C19-E19) -> 0 | I19: =$D$20 -> Price cut | J19: =$F$20 -> 3.4916259
B20: =SUMIFS(Debt!$E$6:$E$13,Debt!$H$6:$H$13,"<="&DATE(2027,2,28)) -> 2868.2225 | C20: =$B$5+$D$5 -> 686.5759 | D20: Price cut | E20: =Simulator!BX40 -> 9328.184 | F20: =IF(B20>0,(C20+E20)/B20,"") -> 3.4916259 | G20: =MAX(0,B20-C20-E20) -> 0
A21: 31 Dec 2027 | B21: =SUMIFS(Debt!$E$6:$E$13,Debt!$H$6:$H$13,"<="&DATE(2027,12,31)) -> 4741.1975 | C21: =$B$5+$D$5 -> 686.5759 | D21: Base | E21: =Simulator!BD40 -> 32644.325 | F21: =IF(B21>0,(C21+E21)/B21,"") -> 7.0300595 | G21: =MAX(0,B21-C21-E21) -> 0
B22: =SUMIFS(Debt!$E$6:$E$13,Debt!$H$6:$H$13,"<="&DATE(2027,12,31)) -> 4741.1975 | C22: =$B$5+$D$5 -> 686.5759 | D22: Delayed handovers | E22: =Simulator!BK40 -> 28475.065 | F22: =IF(B22>0,(C22+E22)/B22,"") -> 6.1506909 | G22: =MAX(0,B22-C22-E22) -> 0 | I22: Delay (months) | J22: No cancellations | K22: 15% cancellations
B23: =SUMIFS(Debt!$E$6:$E$13,Debt!$H$6:$H$13,"<="&DATE(2027,12,31)) -> 4741.1975 | C23: =$B$5+$D$5 -> 686.5759 | D23: Cancellation spike | E23: =Simulator!BR40 -> 26501.314 | F23: =IF(B23>0,(C23+E23)/B23,"") -> 5.7343931 | G23: =MAX(0,B23-C23-E23) -> 0 | I23: ='Break-even'!$B$36 -> 0 | J23: ='Break-even'!$C$36 -> 3.7916279 | K23: ='Break-even'!$F$36 -> 3.1277083
B24: =SUMIFS(Debt!$E$6:$E$13,Debt!$H$6:$H$13,"<="&DATE(2027,12,31)) -> 4741.1975 | C24: =$B$5+$D$5 -> 686.5759 | D24: Price cut | E24: =Simulator!BY40 -> 30464.424 | F24: =IF(B24>0,(C24+E24)/B24,"") -> 6.5702811 | G24: =MAX(0,B24-C24-E24) -> 0 | I24: ='Break-even'!$B$37 -> 5 | J24: ='Break-even'!$C$37 -> 2.7709491 | K24: ='Break-even'!$F$37 -> 2.2433021
A25: 31 Dec 2028 | B25: =SUMIFS(Debt!$E$6:$E$13,Debt!$H$6:$H$13,"<="&DATE(2028,12,31)) -> 6114.7125 | C25: =$B$5+$D$5 -> 686.5759 | D25: Base | E25: =Simulator!BE40 -> 34786.092 | F25: =IF(B25>0,(C25+E25)/B25,"") -> 5.8011996 | G25: =MAX(0,B25-C25-E25) -> 0 | I25: ='Break-even'!$B$38 -> 10 | J25: ='Break-even'!$C$38 -> 1.9757644 | K25: ='Break-even'!$F$38 -> 1.5555883
B26: =SUMIFS(Debt!$E$6:$E$13,Debt!$H$6:$H$13,"<="&DATE(2028,12,31)) -> 6114.7125 | C26: =$B$5+$D$5 -> 686.5759 | D26: Delayed handovers | E26: =Simulator!BL40 -> 32269.986 | F26: =IF(B26>0,(C26+E26)/B26,"") -> 5.3897156 | G26: =MAX(0,B26-C26-E26) -> 0 | I26: ='Break-even'!$B$39 -> 15 | J26: ='Break-even'!$C$39 -> 1.4956877 | K26: ='Break-even'!$F$39 -> 1.1410835
B27: =SUMIFS(Debt!$E$6:$E$13,Debt!$H$6:$H$13,"<="&DATE(2028,12,31)) -> 6114.7125 | C27: =$B$5+$D$5 -> 686.5759 | D27: Cancellation spike | E27: =Simulator!BS40 -> 28313.568 | F27: =IF(B27>0,(C27+E27)/B27,"") -> 4.7426832 | G27: =MAX(0,B27-C27-E27) -> 0 | I27: ='Break-even'!$B$40 -> 20 | J27: ='Break-even'!$C$40 -> 1.238056 | K27: ='Break-even'!$F$40 -> 0.92079571
B28: =SUMIFS(Debt!$E$6:$E$13,Debt!$H$6:$H$13,"<="&DATE(2028,12,31)) -> 6114.7125 | C28: =$B$5+$D$5 -> 686.5759 | D28: Price cut | E28: =Simulator!BZ40 -> 32494.604 | F28: =IF(B28>0,(C28+E28)/B28,"") -> 5.4264498 | G28: =MAX(0,B28-C28-E28) -> 0 | I28: ='Break-even'!$B$41 -> 25 | J28: ='Break-even'!$C$41 -> 1.0774232 | K28: ='Break-even'!$F$41 -> 0.78464204
A29: =_xlfn._LONGTEXT("This section is the headroom measure, not the cash test. Debt due is cumulative from today to the date shown, so the Feb-2027 line includes the bank debt the accounts place in H2 2026. Headroom above 1.0x means modelled escrow release plus free cash excee","ds what is due, before any deduction for building the towers or servicing the debt. On the cash test the same February maturity reads ")&TEXT($C$12,"0.00")&"x. Use this section to compare scenarios; use the Cash flow sheet to answer whether a maturity can be paid." -> This section is the headroom measure, not the cash test. Debt due is cumulative from today to the date shown, so the Feb-2027 line includes the bank debt the accounts place in H2 2026. Headroom above 1.0x means modelled escrow release plus free cash exceeds what is due, before any deduction for building the towers or servicing the debt. On the cash test the same February maturity reads 0.80x. Use this section to compare scenarios; use the Cash flow sheet to answer whether a maturity can be paid. | I29: ='Break-even'!$B$42 -> 30 | J29: ='Break-even'!$C$42 -> 0.96774187 | K29: ='Break-even'!$F$42 -> 0.69176633
A32: 2. Monthly escrow release, active scenario (AED m)
A33: Month | B33: Cumulative release | C33: In the month | D33: Debt falling due in the month | E33: Running cash after debt (from free cash) | I33: Month | J33: Cumulative escrow release | K33: Cumulative debt due | L33: Cash net
A34: 46296 | B34: =Simulator!V40 -> 1771.9373 | C34: =Simulator!V41 -> 1771.9373 | D34: =SUMPRODUCT((YEAR(Debt!$H$6:$H$13)=2026)*(MONTH(Debt!$H$6:$H$13)=10)*Debt!$E$6:$E$13) -> 0 | E34: =$B$5+$D$5+B34-SUM($D$34:D34) -> 2458.5132 | I34: =$A34 -> 46296 | J34: =$B34 -> 1771.9373 | K34: =SUM($D$34:$D34) -> 0 | L34: =INDEX('Cash flow'!$C$71:$BN$71,MATCH($I34,'Cash flow'!$C$58:$BN$58,0)) -> 768.98975
A35: 46327 | B35: =Simulator!W40 -> 3371.8109 | C35: =Simulator!W41 -> 1599.8736 | D35: =SUMPRODUCT((YEAR(Debt!$H$6:$H$13)=2026)*(MONTH(Debt!$H$6:$H$13)=11)*Debt!$E$6:$E$13) -> 0 | E35: =$B$5+$D$5+B35-SUM($D$34:D35) -> 4058.3868 | I35: =$A35 -> 46327 | J35: =$B35 -> 3371.8109 | K35: =SUM($D$34:$D35) -> 0 | L35: =INDEX('Cash flow'!$C$71:$BN$71,MATCH($I35,'Cash flow'!$C$58:$BN$58,0)) -> 679.3399
A36: 46357 | B36: =Simulator!X40 -> 5225.5363 | C36: =Simulator!X41 -> 1853.7254 | D36: =SUMPRODUCT((YEAR(Debt!$H$6:$H$13)=2026)*(MONTH(Debt!$H$6:$H$13)=12)*Debt!$E$6:$E$13) -> 1031.9725 | E36: =$B$5+$D$5+B36-SUM($D$34:D36) -> 4880.1397 | I36: =$A36 -> 46357 | J36: =$B36 -> 5225.5363 | K36: =SUM($D$34:$D36) -> 1031.9725 | L36: =INDEX('Cash flow'!$C$71:$BN$71,MATCH($I36,'Cash flow'!$C$58:$BN$58,0)) -> -188.43069
A37: 46388 | B37: =Simulator!Y40 -> 7333.1135 | C37: =Simulator!Y41 -> 2107.5771 | D37: =SUMPRODUCT((YEAR(Debt!$H$6:$H$13)=2027)*(MONTH(Debt!$H$6:$H$13)=1)*Debt!$E$6:$E$13) -> 0 | E37: =$B$5+$D$5+B37-SUM($D$34:D37) -> 6987.7169 | I37: =$A37 -> 46388 | J37: =$B37 -> 7333.1135 | K37: =SUM($D$34:$D37) -> 1031.9725 | L37: =INDEX('Cash flow'!$C$71:$BN$71,MATCH($I37,'Cash flow'!$C$58:$BN$58,0)) -> 238.02424
A38: 46419 | B38: =Simulator!Z40 -> 10188.657 | C38: =Simulator!Z41 -> 2855.5431 | D38: =SUMPRODUCT((YEAR(Debt!$H$6:$H$13)=2027)*(MONTH(Debt!$H$6:$H$13)=2)*Debt!$E$6:$E$13) -> 1836.25 | E38: =$B$5+$D$5+B38-SUM($D$34:D38) -> 8007.01 | I38: =$A38 -> 46419 | J38: =$B38 -> 10188.657 | K38: =SUM($D$34:$D38) -> 2868.2225 | L38: =INDEX('Cash flow'!$C$71:$BN$71,MATCH($I38,'Cash flow'!$C$58:$BN$58,0)) -> -362.54875
A39: 46447 | B39: =Simulator!AA40 -> 13785.522 | C39: =Simulator!AA41 -> 3596.8651 | D39: =SUMPRODUCT((YEAR(Debt!$H$6:$H$13)=2027)*(MONTH(Debt!$H$6:$H$13)=3)*Debt!$E$6:$E$13) -> 0 | E39: =$B$5+$D$5+B39-SUM($D$34:D39) -> 11603.875 | I39: =$A39 -> 46447 | J39: =$B39 -> 13785.522 | K39: =SUM($D$34:$D39) -> 2868.2225 | L39: =INDEX('Cash flow'!$C$71:$BN$71,MATCH($I39,'Cash flow'!$C$58:$BN$58,0)) -> 1665.9322
A40: 46478 | B40: =Simulator!AB40 -> 16841.512 | C40: =Simulator!AB41 -> 3055.9904 | D40: =SUMPRODUCT((YEAR(Debt!$H$6:$H$13)=2027)*(MONTH(Debt!$H$6:$H$13)=4)*Debt!$E$6:$E$13) -> 0 | E40: =$B$5+$D$5+B40-SUM($D$34:D40) -> 14659.865 | I40: =$A40 -> 46478 | J40: =$B40 -> 16841.512 | K40: =SUM($D$34:$D40) -> 2868.2225 | L40: =INDEX('Cash flow'!$C$71:$BN$71,MATCH($I40,'Cash flow'!$C$58:$BN$58,0)) -> 3338.8422
A41: 46508 | B41: =Simulator!AC40 -> 19403.154 | C41: =Simulator!AC41 -> 2561.6423 | D41: =SUMPRODUCT((YEAR(Debt!$H$6:$H$13)=2027)*(MONTH(Debt!$H$6:$H$13)=5)*Debt!$E$6:$E$13) -> 0 | E41: =$B$5+$D$5+B41-SUM($D$34:D41) -> 17221.508 | I41: =$A41 -> 46508 | J41: =$B41 -> 19403.154 | K41: =SUM($D$34:$D41) -> 2868.2225 | L41: =INDEX('Cash flow'!$C$71:$BN$71,MATCH($I41,'Cash flow'!$C$58:$BN$58,0)) -> 4579.8307
A42: 46539 | B42: =Simulator!AD40 -> 23171.799 | C42: =Simulator!AD41 -> 3768.6449 | D42: =SUMPRODUCT((YEAR(Debt!$H$6:$H$13)=2027)*(MONTH(Debt!$H$6:$H$13)=6)*Debt!$E$6:$E$13) -> 690.43 | E42: =$B$5+$D$5+B42-SUM($D$34:D42) -> 20299.723 | I42: =$A42 -> 46539 | J42: =$B42 -> 23171.799 | K42: =SUM($D$34:$D42) -> 3558.6525 | L42: =INDEX('Cash flow'!$C$71:$BN$71,MATCH($I42,'Cash flow'!$C$58:$BN$58,0)) -> 6554.1814
A43: 46569 | B43: =Simulator!AE40 -> 28729.544 | C43: =Simulator!AE41 -> 5557.7445 | D43: =SUMPRODUCT((YEAR(Debt!$H$6:$H$13)=2027)*(MONTH(Debt!$H$6:$H$13)=7)*Debt!$E$6:$E$13) -> 0 | E43: =$B$5+$D$5+B43-SUM($D$34:D43) -> 25857.467 | I43: =$A43 -> 46569 | J43: =$B43 -> 28729.544 | K43: =SUM($D$34:$D43) -> 3558.6525 | L43: =INDEX('Cash flow'!$C$71:$BN$71,MATCH($I43,'Cash flow'!$C$58:$BN$58,0)) -> 11190.92
A44: 46600 | B44: =Simulator!AF40 -> 29440.238 | C44: =Simulator!AF41 -> 710.69414 | D44: =SUMPRODUCT((YEAR(Debt!$H$6:$H$13)=2027)*(MONTH(Debt!$H$6:$H$13)=8)*Debt!$E$6:$E$13) -> 0 | E44: =$B$5+$D$5+B44-SUM($D$34:D44) -> 26568.161 | I44: =$A44 -> 46600 | J44: =$B44 -> 29440.238 | K44: =SUM($D$34:$D44) -> 3558.6525 | L44: =INDEX('Cash flow'!$C$71:$BN$71,MATCH($I44,'Cash flow'!$C$58:$BN$58,0)) -> 11515.358
A45: 46631 | B45: =Simulator!AG40 -> 30069.004 | C45: =Simulator!AG41 -> 628.76576 | D45: =SUMPRODUCT((YEAR(Debt!$H$6:$H$13)=2027)*(MONTH(Debt!$H$6:$H$13)=9)*Debt!$E$6:$E$13) -> 0 | E45: =$B$5+$D$5+B45-SUM($D$34:D45) -> 27196.927 | I45: =$A45 -> 46631 | J45: =$B45 -> 30069.004 | K45: =SUM($D$34:$D45) -> 3558.6525 | L45: =INDEX('Cash flow'!$C$71:$BN$71,MATCH($I45,'Cash flow'!$C$58:$BN$58,0)) -> 11760.234
A46: 46661 | B46: =Simulator!AH40 -> 31816.731 | C46: =Simulator!AH41 -> 1747.727 | D46: =SUMPRODUCT((YEAR(Debt!$H$6:$H$13)=2027)*(MONTH(Debt!$H$6:$H$13)=10)*Debt!$E$6:$E$13) -> 0 | E46: =$B$5+$D$5+B46-SUM($D$34:D46) -> 28944.654 | I46: =$A46 -> 46661 | J46: =$B46 -> 31816.731 | K46: =SUM($D$34:$D46) -> 3558.6525 | L46: =INDEX('Cash flow'!$C$71:$BN$71,MATCH($I46,'Cash flow'!$C$58:$BN$58,0)) -> 13375.566
A47: 46692 | B47: =Simulator!AI40 -> 32543.032 | C47: =Simulator!AI41 -> 726.30125 | D47: =SUMPRODUCT((YEAR(Debt!$H$6:$H$13)=2027)*(MONTH(Debt!$H$6:$H$13)=11)*Debt!$E$6:$E$13) -> 0 | E47: =$B$5+$D$5+B47-SUM($D$34:D47) -> 29670.955 | I47: =$A47 -> 46692 | J47: =$B47 -> 32543.032 | K47: =SUM($D$34:$D47) -> 3558.6525 | L47: =INDEX('Cash flow'!$C$71:$BN$71,MATCH($I47,'Cash flow'!$C$58:$BN$58,0)) -> 13919.136
A48: 46722 | B48: =Simulator!AJ40 -> 32644.325 | C48: =Simulator!AJ41 -> 101.29279 | D48: =SUMPRODUCT((YEAR(Debt!$H$6:$H$13)=2027)*(MONTH(Debt!$H$6:$H$13)=12)*Debt!$E$6:$E$13) -> 1182.545 | E48: =$B$5+$D$5+B48-SUM($D$34:D48) -> 28589.703 | I48: =$A48 -> 46722 | J48: =$B48 -> 32644.325 | K48: =SUM($D$34:$D48) -> 4741.1975 | L48: =INDEX('Cash flow'!$C$71:$BN$71,MATCH($I48,'Cash flow'!$C$58:$BN$58,0)) -> 13112.828
A49: 46753 | B49: =Simulator!AK40 -> 32749.436 | C49: =Simulator!AK41 -> 105.1113 | D49: =SUMPRODUCT((YEAR(Debt!$H$6:$H$13)=2028)*(MONTH(Debt!$H$6:$H$13)=1)*Debt!$E$6:$E$13) -> 0 | E49: =$B$5+$D$5+B49-SUM($D$34:D49) -> 28694.814 | I49: =$A49 -> 46753 | J49: =$B49 -> 32749.436 | K49: =SUM($D$34:$D49) -> 4741.1975 | L49: =INDEX('Cash flow'!$C$71:$BN$71,MATCH($I49,'Cash flow'!$C$58:$BN$58,0)) -> 13108.384
A50: 46784 | B50: =Simulator!AL40 -> 32858.366 | C50: =Simulator!AL41 -> 108.92982 | D50: =SUMPRODUCT((YEAR(Debt!$H$6:$H$13)=2028)*(MONTH(Debt!$H$6:$H$13)=2)*Debt!$E$6:$E$13) -> 0 | E50: =$B$5+$D$5+B50-SUM($D$34:D50) -> 28803.744 | I50: =$A50 -> 46784 | J50: =$B50 -> 32858.366 | K50: =SUM($D$34:$D50) -> 4741.1975 | L50: =INDEX('Cash flow'!$C$71:$BN$71,MATCH($I50,'Cash flow'!$C$58:$BN$58,0)) -> 13138.29
A51: 46813 | B51: =Simulator!AM40 -> 32971.114 | C51: =Simulator!AM41 -> 112.74834 | D51: =SUMPRODUCT((YEAR(Debt!$H$6:$H$13)=2028)*(MONTH(Debt!$H$6:$H$13)=3)*Debt!$E$6:$E$13) -> 0 | E51: =$B$5+$D$5+B51-SUM($D$34:D51) -> 28916.493 | I51: =$A51 -> 46813 | J51: =$B51 -> 32971.114 | K51: =SUM($D$34:$D51) -> 4741.1975 | L51: =INDEX('Cash flow'!$C$71:$BN$71,MATCH($I51,'Cash flow'!$C$58:$BN$58,0)) -> 14204.682
A52: 46844 | B52: =Simulator!AN40 -> 33087.681 | C52: =Simulator!AN41 -> 116.56686 | D52: =SUMPRODUCT((YEAR(Debt!$H$6:$H$13)=2028)*(MONTH(Debt!$H$6:$H$13)=4)*Debt!$E$6:$E$13) -> 0 | E52: =$B$5+$D$5+B52-SUM($D$34:D52) -> 29033.059 | I52: =$A52 -> 46844 | J52: =$B52 -> 33087.681 | K52: =SUM($D$34:$D52) -> 4741.1975 | L52: =INDEX('Cash flow'!$C$71:$BN$71,MATCH($I52,'Cash flow'!$C$58:$BN$58,0)) -> 14211.694
A53: 46874 | B53: =Simulator!AO40 -> 33208.066 | C53: =Simulator!AO41 -> 120.38538 | D53: =SUMPRODUCT((YEAR(Debt!$H$6:$H$13)=2028)*(MONTH(Debt!$H$6:$H$13)=5)*Debt!$E$6:$E$13) -> 0 | E53: =$B$5+$D$5+B53-SUM($D$34:D53) -> 29153.445 | I53: =$A53 -> 46874 | J53: =$B53 -> 33208.066 | K53: =SUM($D$34:$D53) -> 4741.1975 | L53: =INDEX('Cash flow'!$C$71:$BN$71,MATCH($I53,'Cash flow'!$C$58:$BN$58,0)) -> 14267.809
A54: 46905 | B54: =Simulator!AP40 -> 33332.27 | C54: =Simulator!AP41 -> 124.2039 | D54: =SUMPRODUCT((YEAR(Debt!$H$6:$H$13)=2028)*(MONTH(Debt!$H$6:$H$13)=6)*Debt!$E$6:$E$13) -> 1373.515 | E54: =$B$5+$D$5+B54-SUM($D$34:D54) -> 27904.134 | I54: =$A54 -> 46905 | J54: =$B54 -> 33332.27 | K54: =SUM($D$34:$D54) -> 6114.7125 | L54: =INDEX('Cash flow'!$C$71:$BN$71,MATCH($I54,'Cash flow'!$C$58:$BN$58,0)) -> 12948.672
A55: 46935 | B55: =Simulator!AQ40 -> 33460.293 | C55: =Simulator!AQ41 -> 128.02242 | D55: =SUMPRODUCT((YEAR(Debt!$H$6:$H$13)=2028)*(MONTH(Debt!$H$6:$H$13)=7)*Debt!$E$6:$E$13) -> 0 | E55: =$B$5+$D$5+B55-SUM($D$34:D55) -> 28032.156 | I55: =$A55 -> 46935 | J55: =$B55 -> 33460.293 | K55: =SUM($D$34:$D55) -> 6114.7125 | L55: =INDEX('Cash flow'!$C$71:$BN$71,MATCH($I55,'Cash flow'!$C$58:$BN$58,0)) -> 13032.251
A56: 46966 | B56: =Simulator!AR40 -> 33592.134 | C56: =Simulator!AR41 -> 131.84094 | D56: =SUMPRODUCT((YEAR(Debt!$H$6:$H$13)=2028)*(MONTH(Debt!$H$6:$H$13)=8)*Debt!$E$6:$E$13) -> 0 | E56: =$B$5+$D$5+B56-SUM($D$34:D56) -> 28163.997 | I56: =$A56 -> 46966 | J56: =$B56 -> 33592.134 | K56: =SUM($D$34:$D56) -> 6114.7125 | L56: =INDEX('Cash flow'!$C$71:$BN$71,MATCH($I56,'Cash flow'!$C$58:$BN$58,0)) -> 13065.719
A57: 46997 | B57: =Simulator!AS40 -> 34786.092 | C57: =Simulator!AS41 -> 1193.9583 | D57: =SUMPRODUCT((YEAR(Debt!$H$6:$H$13)=2028)*(MONTH(Debt!$H$6:$H$13)=9)*Debt!$E$6:$E$13) -> 0 | E57: =$B$5+$D$5+B57-SUM($D$34:D57) -> 29357.955 | I57: =$A57 -> 46997 | J57: =$B57 -> 34786.092 | K57: =SUM($D$34:$D57) -> 6114.7125 | L57: =INDEX('Cash flow'!$C$71:$BN$71,MATCH($I57,'Cash flow'!$C$58:$BN$58,0)) -> 14161.304
A58: 47027 | B58: =Simulator!AT40 -> 34786.092 | C58: =Simulator!AT41 -> 0 | D58: =SUMPRODUCT((YEAR(Debt!$H$6:$H$13)=2028)*(MONTH(Debt!$H$6:$H$13)=10)*Debt!$E$6:$E$13) -> 0 | E58: =$B$5+$D$5+B58-SUM($D$34:D58) -> 29357.955 | I58: =$A58 -> 47027 | J58: =$B58 -> 34786.092 | K58: =SUM($D$34:$D58) -> 6114.7125 | L58: =INDEX('Cash flow'!$C$71:$BN$71,MATCH($I58,'Cash flow'!$C$58:$BN$58,0)) -> 14124.196
A59: 47058 | B59: =Simulator!AU40 -> 34786.092 | C59: =Simulator!AU41 -> 0 | D59: =SUMPRODUCT((YEAR(Debt!$H$6:$H$13)=2028)*(MONTH(Debt!$H$6:$H$13)=11)*Debt!$E$6:$E$13) -> 0 | E59: =$B$5+$D$5+B59-SUM($D$34:D59) -> 29357.955 | I59: =$A59 -> 47058 | J59: =$B59 -> 34786.092 | K59: =SUM($D$34:$D59) -> 6114.7125 | L59: =INDEX('Cash flow'!$C$71:$BN$71,MATCH($I59,'Cash flow'!$C$58:$BN$58,0)) -> 14173.15
A60: 47088 | B60: =Simulator!AV40 -> 34786.092 | C60: =Simulator!AV41 -> 0 | D60: =SUMPRODUCT((YEAR(Debt!$H$6:$H$13)=2028)*(MONTH(Debt!$H$6:$H$13)=12)*Debt!$E$6:$E$13) -> 0 | E60: =$B$5+$D$5+B60-SUM($D$34:D60) -> 29357.955 | I60: =$A60 -> 47088 | J60: =$B60 -> 34786.092 | K60: =SUM($D$34:$D60) -> 6114.7125 | L60: =INDEX('Cash flow'!$C$71:$BN$71,MATCH($I60,'Cash flow'!$C$58:$BN$58,0)) -> 14136.043
A61: 47119 | B61: =Simulator!AW40 -> 34786.092 | C61: =Simulator!AW41 -> 0 | D61: =SUMPRODUCT((YEAR(Debt!$H$6:$H$13)=2029)*(MONTH(Debt!$H$6:$H$13)=1)*Debt!$E$6:$E$13) -> 0 | E61: =$B$5+$D$5+B61-SUM($D$34:D61) -> 29357.955 | I61: =$A61 -> 47119 | J61: =$B61 -> 34786.092 | K61: =SUM($D$34:$D61) -> 6114.7125 | L61: =INDEX('Cash flow'!$C$71:$BN$71,MATCH($I61,'Cash flow'!$C$58:$BN$58,0)) -> 14098.935
A62: Running cash assumes no other operating inflow or outflow — no land purchases, no construction spend outside escrow, no new borrowing. It isolates one question: do handovers alone cover maturities?
A65: 3. The towers that matter most before 28 Feb 2027 — largest modelled release, active scenario
A66: Project | B66: Status | C66: Certified % | D66: Registered completion | E66: Projected completion | F66: Sold % | G66: Release by 28 Feb 2027 (AED m)
A67: =INDEX(Simulator!$B$8:$B$39,MATCH(LARGE(Simulator!$CA$8:$CA$39,1),Simulator!$CA$8:$CA$39,0)) -> Mercedes-Benz Places | Binghatti | B67: =INDEX(Simulator!$C$8:$C$39,MATCH(LARGE(Simulator!$CA$8:$CA$39,1),Simulator!$CA$8:$CA$39,0)) -> Active | C67: =INDEX(Simulator!$H$8:$H$39,MATCH(LARGE(Simulator!$CA$8:$CA$39,1),Simulator!$CA$8:$CA$39,0)) -> 65 | D67: =INDEX(Simulator!$I$8:$I$39,MATCH(LARGE(Simulator!$CA$8:$CA$39,1),Simulator!$CA$8:$CA$39,0)) -> 46387 | E67: =INDEX(Simulator!$M$8:$M$39,MATCH(LARGE(Simulator!$CA$8:$CA$39,1),Simulator!$CA$8:$CA$39,0)) -> 46387 | F67: =INDEX(Simulator!$L$8:$L$39,MATCH(LARGE(Simulator!$CA$8:$CA$39,1),Simulator!$CA$8:$CA$39,0)) -> 0.71779141 | G67: =INDEX(Simulator!$R$8:$R$39,MATCH(LARGE(Simulator!$CA$8:$CA$39,1),Simulator!$CA$8:$CA$39,0)) -> 1570.7806
A68: =INDEX(Simulator!$B$8:$B$39,MATCH(LARGE(Simulator!$CA$8:$CA$39,2),Simulator!$CA$8:$CA$39,0)) -> Binghatti Skyrise | B68: =INDEX(Simulator!$C$8:$C$39,MATCH(LARGE(Simulator!$CA$8:$CA$39,2),Simulator!$CA$8:$CA$39,0)) -> Active | C68: =INDEX(Simulator!$H$8:$H$39,MATCH(LARGE(Simulator!$CA$8:$CA$39,2),Simulator!$CA$8:$CA$39,0)) -> 22 | D68: =INDEX(Simulator!$I$8:$I$39,MATCH(LARGE(Simulator!$CA$8:$CA$39,2),Simulator!$CA$8:$CA$39,0)) -> 46387 | E68: =INDEX(Simulator!$M$8:$M$39,MATCH(LARGE(Simulator!$CA$8:$CA$39,2),Simulator!$CA$8:$CA$39,0)) -> 46387 | F68: =INDEX(Simulator!$L$8:$L$39,MATCH(LARGE(Simulator!$CA$8:$CA$39,2),Simulator!$CA$8:$CA$39,0)) -> 0.99009901 | G68: =INDEX(Simulator!$R$8:$R$39,MATCH(LARGE(Simulator!$CA$8:$CA$39,2),Simulator!$CA$8:$CA$39,0)) -> 1237.48
A69: =INDEX(Simulator!$B$8:$B$39,MATCH(LARGE(Simulator!$CA$8:$CA$39,3),Simulator!$CA$8:$CA$39,0)) -> Bugatti Residences by Binghatti | B69: =INDEX(Simulator!$C$8:$C$39,MATCH(LARGE(Simulator!$CA$8:$CA$39,3),Simulator!$CA$8:$CA$39,0)) -> Active | C69: =INDEX(Simulator!$H$8:$H$39,MATCH(LARGE(Simulator!$CA$8:$CA$39,3),Simulator!$CA$8:$CA$39,0)) -> 20.04 | D69: =INDEX(Simulator!$I$8:$I$39,MATCH(LARGE(Simulator!$CA$8:$CA$39,3),Simulator!$CA$8:$CA$39,0)) -> 46022 | E69: =INDEX(Simulator!$M$8:$M$39,MATCH(LARGE(Simulator!$CA$8:$CA$39,3),Simulator!$CA$8:$CA$39,0)) -> 46456 | F69: =INDEX(Simulator!$L$8:$L$39,MATCH(LARGE(Simulator!$CA$8:$CA$39,3),Simulator!$CA$8:$CA$39,0)) -> 0.58947368 | G69: =INDEX(Simulator!$R$8:$R$39,MATCH(LARGE(Simulator!$CA$8:$CA$39,3),Simulator!$CA$8:$CA$39,0)) -> 1193.2996
A70: =INDEX(Simulator!$B$8:$B$39,MATCH(LARGE(Simulator!$CA$8:$CA$39,4),Simulator!$CA$8:$CA$39,0)) -> Burj Binghatti Jacob & Co. Residences | B70: =INDEX(Simulator!$C$8:$C$39,MATCH(LARGE(Simulator!$CA$8:$CA$39,4),Simulator!$CA$8:$CA$39,0)) -> Active | C70: =INDEX(Simulator!$H$8:$H$39,MATCH(LARGE(Simulator!$CA$8:$CA$39,4),Simulator!$CA$8:$CA$39,0)) -> 35 | D70: =INDEX(Simulator!$I$8:$I$39,MATCH(LARGE(Simulator!$CA$8:$CA$39,4),Simulator!$CA$8:$CA$39,0)) -> 46203 | E70: =INDEX(Simulator!$M$8:$M$39,MATCH(LARGE(Simulator!$CA$8:$CA$39,4),Simulator!$CA$8:$CA$39,0)) -> 46456 | F70: =INDEX(Simulator!$L$8:$L$39,MATCH(LARGE(Simulator!$CA$8:$CA$39,4),Simulator!$CA$8:$CA$39,0)) -> 0.73684211 | G70: =INDEX(Simulator!$R$8:$R$39,MATCH(LARGE(Simulator!$CA$8:$CA$39,4),Simulator!$CA$8:$CA$39,0)) -> 767.01656
A71: =INDEX(Simulator!$B$8:$B$39,MATCH(LARGE(Simulator!$CA$8:$CA$39,5),Simulator!$CA$8:$CA$39,0)) -> One by Binghatti | B71: =INDEX(Simulator!$C$8:$C$39,MATCH(LARGE(Simulator!$CA$8:$CA$39,5),Simulator!$CA$8:$CA$39,0)) -> Active | C71: =INDEX(Simulator!$H$8:$H$39,MATCH(LARGE(Simulator!$CA$8:$CA$39,5),Simulator!$CA$8:$CA$39,0)) -> 50 | D71: =INDEX(Simulator!$I$8:$I$39,MATCH(LARGE(Simulator!$CA$8:$CA$39,5),Simulator!$CA$8:$CA$39,0)) -> 46172 | E71: =INDEX(Simulator!$M$8:$M$39,MATCH(LARGE(Simulator!$CA$8:$CA$39,5),Simulator!$CA$8:$CA$39,0)) -> 46456 | F71: =INDEX(Simulator!$L$8:$L$39,MATCH(LARGE(Simulator!$CA$8:$CA$39,5),Simulator!$CA$8:$CA$39,0)) -> 0.84860558 | G71: =INDEX(Simulator!$R$8:$R$39,MATCH(LARGE(Simulator!$CA$8:$CA$39,5),Simulator!$CA$8:$CA$39,0)) -> 748.16614
A72: =INDEX(Simulator!$B$8:$B$39,MATCH(LARGE(Simulator!$CA$8:$CA$39,6),Simulator!$CA$8:$CA$39,0)) -> Binghatti Aquarise | B72: =INDEX(Simulator!$C$8:$C$39,MATCH(LARGE(Simulator!$CA$8:$CA$39,6),Simulator!$CA$8:$CA$39,0)) -> Active | C72: =INDEX(Simulator!$H$8:$H$39,MATCH(LARGE(Simulator!$CA$8:$CA$39,6),Simulator!$CA$8:$CA$39,0)) -> 21 | D72: =INDEX(Simulator!$I$8:$I$39,MATCH(LARGE(Simulator!$CA$8:$CA$39,6),Simulator!$CA$8:$CA$39,0)) -> 46326 | E72: =INDEX(Simulator!$M$8:$M$39,MATCH(LARGE(Simulator!$CA$8:$CA$39,6),Simulator!$CA$8:$CA$39,0)) -> 46326 | F72: =INDEX(Simulator!$L$8:$L$39,MATCH(LARGE(Simulator!$CA$8:$CA$39,6),Simulator!$CA$8:$CA$39,0)) -> 0.8270202 | G72: =INDEX(Simulator!$R$8:$R$39,MATCH(LARGE(Simulator!$CA$8:$CA$39,6),Simulator!$CA$8:$CA$39,0)) -> 694.17355
A73: =INDEX(Simulator!$B$8:$B$39,MATCH(LARGE(Simulator!$CA$8:$CA$39,7),Simulator!$CA$8:$CA$39,0)) -> Binghatti Hillviews | B73: =INDEX(Simulator!$C$8:$C$39,MATCH(LARGE(Simulator!$CA$8:$CA$39,7),Simulator!$CA$8:$CA$39,0)) -> Active | C73: =INDEX(Simulator!$H$8:$H$39,MATCH(LARGE(Simulator!$CA$8:$CA$39,7),Simulator!$CA$8:$CA$39,0)) -> 33 | D73: =INDEX(Simulator!$I$8:$I$39,MATCH(LARGE(Simulator!$CA$8:$CA$39,7),Simulator!$CA$8:$CA$39,0)) -> 46113 | E73: =INDEX(Simulator!$M$8:$M$39,MATCH(LARGE(Simulator!$CA$8:$CA$39,7),Simulator!$CA$8:$CA$39,0)) -> 46456 | F73: =INDEX(Simulator!$L$8:$L$39,MATCH(LARGE(Simulator!$CA$8:$CA$39,7),Simulator!$CA$8:$CA$39,0)) -> 0.99301587 | G73: =INDEX(Simulator!$R$8:$R$39,MATCH(LARGE(Simulator!$CA$8:$CA$39,7),Simulator!$CA$8:$CA$39,0)) -> 520.36501
A74: =INDEX(Simulator!$B$8:$B$39,MATCH(LARGE(Simulator!$CA$8:$CA$39,8),Simulator!$CA$8:$CA$39,0)) -> Binghatti Elite | B74: =INDEX(Simulator!$C$8:$C$39,MATCH(LARGE(Simulator!$CA$8:$CA$39,8),Simulator!$CA$8:$CA$39,0)) -> Active | C74: =INDEX(Simulator!$H$8:$H$39,MATCH(LARGE(Simulator!$CA$8:$CA$39,8),Simulator!$CA$8:$CA$39,0)) -> 53 | D74: =INDEX(Simulator!$I$8:$I$39,MATCH(LARGE(Simulator!$CA$8:$CA$39,8),Simulator!$CA$8:$CA$39,0)) -> 46203 | E74: =INDEX(Simulator!$M$8:$M$39,MATCH(LARGE(Simulator!$CA$8:$CA$39,8),Simulator!$CA$8:$CA$39,0)) -> 46456 | F74: =INDEX(Simulator!$L$8:$L$39,MATCH(LARGE(Simulator!$CA$8:$CA$39,8),Simulator!$CA$8:$CA$39,0)) -> 1 | G74: =INDEX(Simulator!$R$8:$R$39,MATCH(LARGE(Simulator!$CA$8:$CA$39,8),Simulator!$CA$8:$CA$39,0)) -> 405.96458
A75: =INDEX(Simulator!$B$8:$B$39,MATCH(LARGE(Simulator!$CA$8:$CA$39,9),Simulator!$CA$8:$CA$39,0)) -> Binghatti Skyhall | B75: =INDEX(Simulator!$C$8:$C$39,MATCH(LARGE(Simulator!$CA$8:$CA$39,9),Simulator!$CA$8:$CA$39,0)) -> Active | C75: =INDEX(Simulator!$H$8:$H$39,MATCH(LARGE(Simulator!$CA$8:$CA$39,9),Simulator!$CA$8:$CA$39,0)) -> 31 | D75: =INDEX(Simulator!$I$8:$I$39,MATCH(LARGE(Simulator!$CA$8:$CA$39,9),Simulator!$CA$8:$CA$39,0)) -> 46265 | E75: =INDEX(Simulator!$M$8:$M$39,MATCH(LARGE(Simulator!$CA$8:$CA$39,9),Simulator!$CA$8:$CA$39,0)) -> 46456 | F75: =INDEX(Simulator!$L$8:$L$39,MATCH(LARGE(Simulator!$CA$8:$CA$39,9),Simulator!$CA$8:$CA$39,0)) -> 0.9010989 | G75: =INDEX(Simulator!$R$8:$R$39,MATCH(LARGE(Simulator!$CA$8:$CA$39,9),Simulator!$CA$8:$CA$39,0)) -> 281.7441
A76: =INDEX(Simulator!$B$8:$B$39,MATCH(LARGE(Simulator!$CA$8:$CA$39,10),Simulator!$CA$8:$CA$39,0)) -> Binghatti Ruby | B76: =INDEX(Simulator!$C$8:$C$39,MATCH(LARGE(Simulator!$CA$8:$CA$39,10),Simulator!$CA$8:$CA$39,0)) -> Active | C76: =INDEX(Simulator!$H$8:$H$39,MATCH(LARGE(Simulator!$CA$8:$CA$39,10),Simulator!$CA$8:$CA$39,0)) -> 46 | D76: =INDEX(Simulator!$I$8:$I$39,MATCH(LARGE(Simulator!$CA$8:$CA$39,10),Simulator!$CA$8:$CA$39,0)) -> 46081 | E76: =INDEX(Simulator!$M$8:$M$39,MATCH(LARGE(Simulator!$CA$8:$CA$39,10),Simulator!$CA$8:$CA$39,0)) -> 46456 | F76: =INDEX(Simulator!$L$8:$L$39,MATCH(LARGE(Simulator!$CA$8:$CA$39,10),Simulator!$CA$8:$CA$39,0)) -> 0.95382166 | G76: =INDEX(Simulator!$R$8:$R$39,MATCH(LARGE(Simulator!$CA$8:$CA$39,10),Simulator!$CA$8:$CA$39,0)) -> 270.22984
A77: Set the certified % against the date: a tower at 30% with its registered date passed will not hand over before February whatever the plan says; one at 99% is paperwork. The ten towers the issuer itself names as funding the maturity are the ones to check here first.
A80: 4. Register facts, issuer level, and one calibration check
A81: Projects on the register | B81: =COUNTA(Projects!A5:A72) -> 68
A82: of which live (active, pending, not started) | B82: =COUNTIF(Projects!D5:D72,"<>Finished") -> 32
A83: Registered units, live projects | B83: =Simulator!E40 -> 23645
A84: Sold units, live projects | B84: =Simulator!F40 -> 22216
A85: Contracted value, live projects (AED m) | B85: =Simulator!J40 -> 37362.292
A86: Estimated collected to date (AED m) | B86: =Simulator!U40 -> 10645.046
A87: Estimated released from escrow to date (AED m) | B87: =Simulator!Q40 -> 4153.2762
A88: implied still held in escrow — model | B88: =Simulator!U40-Simulator!Q40 -> 6491.7698
A89: reported in escrow, 30 Jun 2026 — accounts | B89: =Financials!D11 -> 10184
A90: Live projects past their registered completion date | B90: =COUNTIFS(Projects!D5:D72,"<>Finished",Projects!F5:F72,"<"&$B$3) -> 17 | C90: The model holds less in escrow than the accounts report: certified % is the June register reading for most towers, so collections since then are not yet in it, and the accounts include finished towers awaiting release. Read the release figures as conservative by roughly that gap.
A91: Units in those projects | B91: =SUMIFS(Projects!I5:I72,Projects!D5:D72,"<>Finished",Projects!F5:F72,"<"&$B$3) -> 10363
A92: Registered sales, last 12 months | B92: =Projects!M73 -> 13300
A93: value (AED m) | B93: =Projects!N73 -> 22385.652
A94: share of all Dubai sales | B94: =IF($B$97>0,Projects!M73/$B$97,"") -> 0.071076244 | C94: Dubai registered 187,123 sales in the twelve months to the as-of date (register).
A95: Resales in Binghatti buildings, 24 months | B95: =Projects!S73 -> 397
A96: of which at a loss | B96: =Projects!T73/Projects!S73 -> 0.3627204
A97: Dubai registered sales, all developers, 12m | B97: 187123
A98: Sources: Dubai Land Department transactions and project registers (open data, read daily; attribution: DLD / data.dubai); Binghatti Holding audited FY2025 and reviewed H1 2026 accounts; offering circulars; Moody's and Fitch public releases; indicative bank price run 4 Sep 2026. Prepared by Dubai Property Intelligence. General information about a developer's published finances and its projects on the public register; not a recommendation to buy, sell or hold any security.
A101: Coverage credits the whole modelled escrow release against debt | B101: Cash RERA releases to a developer funds construction; it is not earmarked for bondholders. A tower that releases AED 500m still has to be built. Treat coverage as headroom, and anything under about 1.5x as tight.
A102: Sources not modelled | B102: New borrowing, refinancing, asset or land sales, shareholder support, the "multibillion-dollar pact" reported 1 Sep 2026, and cash from the already-completed portfolio. All could help; none are counted.
A103: The payment-plan split is an assumption | B103: The issuer discloses roughly 70% collected during construction. The 10 / 60 / 30 booking / progress / handover shape is a reading of that, not a filed term. Change it on Scenarios rows 11 and 12.
A104: Handover timing drives everything | B104: A tower at 30% certified whose registered date has passed will not hand over by February. Check certified % against date on rows 66–76 before trusting any coverage figure.
A105: Project 4043 contributes nothing | B105: بالم 01 من بن غاطي carries zero units, zero sales and zero average ticket on the register, so it releases nothing in the model. Coverage is understated to that extent.
A106: Two Financials ratios are blank | B106: FY2024 finance cost is not in the data, so FY2024 interest cover reads "n/a"; debt due within twelve months is not broken out for FY2024 or FY2025, so that liquidity ratio is blank for both.
A107: Prices are indicative | B107: Sukuk levels on the Bonds sheet are bank indications from 4 Sep 2026, not traded prices. Offering circulars were not reviewed, so call, change-of-control and cross-default terms are unverified.
A109: 6. CHARTS

Sheet Break-even
A1: BREAK-EVEN — HOW FAR CAN HANDOVERS SLIP BEFORE ESCROW HEADROOM FAILS?
A2: February 2027 escrow headroom across a grid of handover delay against cancellation rate, independent of whichever scenario is active. Headroom is escrow release plus free cash against debt due, before construction cost and debt service. For whether the maturity can actually be paid, see the cash test above and the Cash flow sheet.
A4: 1. WHAT THIS SHEET DOES
A5: It re-runs the escrow model from first principles for every combination of two variables, and reports the resulting coverage of the 28 February 2027 maturity. Everything else is held at the Base column of the Scenarios sheet, so switching the active scenario does not move this grid.
A6: One difference from the Scenarios delay input: there, delay shifts only registered completion dates, so towers whose date has already passed are unaffected. Here delay shifts every tower, including those on the fallback runway. That makes the axis a genuine stress rather than one that leaves part of the portfolio immune.
A7: 2. THE CASH TEST — READ THIS BEFORE THE GRID BELOW
A8: This sheet measures escrow headroom: escrow release plus free cash against debt due, before the cost of building the towers and before debt service. On that measure the February 2027 sukuk does not fail until handovers slip a long way. On the cash test, which deducts both and is the binding answer on the Cover and the Cash flow sheet, it is already short today. Both numbers are shown here so the sheet cannot be read in isolation.
A9: Measure | B9: Value | C9: Note
A10: Escrow headroom, 28 Feb 2027 (this sheet, base corner) | B10: =$C$36 -> 3.7916279 | C10: The top-left cell of the grid below. Ties to Dashboard section 1.
A11: Cash-test coverage, 28 Feb 2027 | B11: ='Cash flow'!$F$94 -> 0.80256025 | C11: After construction cost and debt service. This is the binding measure.
A12: Cash-test shortfall on that sukuk | B12: ='Cash flow'!$G$94 -> 362.54875 | C12: AED m. New money, an asset sale or a refinancing of this size closes it.
A13: Cost to complete that would bring the cash test to 1.00x | B13: =IF('Cash flow'!$G$63>0,Scenarios!$F$15-'Cash flow'!$G$94/('Cash flow'!$G$63/Scenarios!$F$15),"") -> 0.52492756 | C13: ="Against "&TEXT(Scenarios!$F$15,"0.0%")&" assumed. Cost is the one input that flips the answer within a few percentage points, which is why it is the first thing to replace with real data." -> Against 55.0% assumed. Cost is the one input that flips the answer within a few percentage points, which is why it is the first thing to replace with real data.
A14: Handover delay that breaks the headroom measure | B14: =$B$45 -> 28.529461 | C14: Months. This is the grid's answer, on the weaker measure. It does not mean the February sukuk is safe for that long.
A16: 3. HELD FIXED
A17: Input | B17: Value | C17: Source
A18: Sell-through of unsold units | B18: =Scenarios!$B$9 -> 0.6 | C18: Scenarios, Base column
A19: Price change on future sales | B19: =Scenarios!$B$10 -> 0 | C19: Scenarios, Base column
A20: Share collected at booking | B20: =Scenarios!$B$11 -> 0.1 | C20: Scenarios, Base column
A21: Share collected at handover | B21: =Scenarios!$B$12 -> 0.3 | C21: Scenarios, Base column
A22: RERA escrow retention | B22: =Scenarios!$B$13 -> 0.05 | C22: Scenarios, Base column
A23: Maximum certified progress per month (pts) | B23: =Scenarios!$B$14 -> 8 | C23: Scenarios, Base column
A24: Runway for towers past their registered date (months) | B24: =Scenarios!$B$6 -> 6 | C24: Scenarios, Base column
A25: Runway for towers with no registered date (months) | B25: =Scenarios!$B$7 -> 24 | C25: Scenarios, Base column
A26: Register read date | B26: =Simulator!$C$3 -> 46275 | C26: Simulator
A27: Checkpoint — months after read date | B27: 5 | C27: Month 5 of the grid is February 2027
A28: Cash outside escrow, plus any received | B28: =Dashboard!$C$17 -> 686.5759 | C28: Dashboard
A29: Debt due by 28 Feb 2027 | B29: =Dashboard!$B$17 -> 2868.2225 | C29: Debt, instruments dated on or before 28 Feb 2027
A32: 4. FEBRUARY 2027 ESCROW HEADROOM GRID
A33: Escrow headroom on the 28 February 2027 maturity. Cells at or below 1.00x mean escrow release plus free cash no longer covers the debt due even before construction cost. The top-left cell is the Base case and ties exactly to Dashboard section 1. Remember that on the cash test this maturity is already below 1.00x at zero delay.
B35: Delay (months) \ Cancellation rate | C35: 0 | D35: 0.05 | E35: 0.1 | F35: 0.15 | G35: 0.2 | H35: 0.25 | I35: 0.3
B36: 0 | C36: {=_xlfn.LET(_xlpm.rf,INDEX($F$57:$L$88,0,MATCH($B36,$F$56:$L$56,0)),_xlpm.x,($C$57:$C$88*(1-C$35)+$D$57:$D$88)*_xlpm.rf-$E$57:$E$88,_xlpm.rel,SUMPRODUCT(_xlpm.x*(_xlpm.x>0)),($B$28+_xlpm.rel)/$B$29)} -> 3.7916279 | D36: {=_xlfn.LET(_xlpm.rf,INDEX($F$57:$L$88,0,MATCH($B36,$F$56:$L$56,0)),_xlpm.x,($C$57:$C$88*(1-D$35)+$D$57:$D$88)*_xlpm.rf-$E$57:$E$88,_xlpm.rel,SUMPRODUCT(_xlpm.x*(_xlpm.x>0)),($B$28+_xlpm.rel)/$B$29)} -> 3.5666075 | E36: {=_xlfn.LET(_xlpm.rf,INDEX($F$57:$L$88,0,MATCH($B36,$F$56:$L$56,0)),_xlpm.x,($C$57:$C$88*(1-E$35)+$D$57:$D$88)*_xlpm.rf-$E$57:$E$88,_xlpm.rel,SUMPRODUCT(_xlpm.x*(_xlpm.x>0)),($B$28+_xlpm.rel)/$B$29)} -> 3.3427603 | F36: {=_xlfn.LET(_xlpm.rf,INDEX($F$57:$L$88,0,MATCH($B36,$F$56:$L$56,0)),_xlpm.x,($C$57:$C$88*(1-F$35)+$D$57:$D$88)*_xlpm.rf-$E$57:$E$88,_xlpm.rel,SUMPRODUCT(_xlpm.x*(_xlpm.x>0)),($B$28+_xlpm.rel)/$B$29)} -> 3.1277083 | G36: {=_xlfn.LET(_xlpm.rf,INDEX($F$57:$L$88,0,MATCH($B36,$F$56:$L$56,0)),_xlpm.x,($C$57:$C$88*(1-G$35)+$D$57:$D$88)*_xlpm.rf-$E$57:$E$88,_xlpm.rel,SUMPRODUCT(_xlpm.x*(_xlpm.x>0)),($B$28+_xlpm.rel)/$B$29)} -> 2.9126563 | H36: {=_xlfn.LET(_xlpm.rf,INDEX($F$57:$L$88,0,MATCH($B36,$F$56:$L$56,0)),_xlpm.x,($C$57:$C$88*(1-H$35)+$D$57:$D$88)*_xlpm.rf-$E$57:$E$88,_xlpm.rel,SUMPRODUCT(_xlpm.x*(_xlpm.x>0)),($B$28+_xlpm.rel)/$B$29)} -> 2.6976043 | I36: {=_xlfn.LET(_xlpm.rf,INDEX($F$57:$L$88,0,MATCH($B36,$F$56:$L$56,0)),_xlpm.x,($C$57:$C$88*(1-I$35)+$D$57:$D$88)*_xlpm.rf-$E$57:$E$88,_xlpm.rel,SUMPRODUCT(_xlpm.x*(_xlpm.x>0)),($B$28+_xlpm.rel)/$B$29)} -> 2.4825523 | K36: 1.00x or below — modelled shortfall
B37: 5 | C37: {=_xlfn.LET(_xlpm.rf,INDEX($F$57:$L$88,0,MATCH($B37,$F$56:$L$56,0)),_xlpm.x,($C$57:$C$88*(1-C$35)+$D$57:$D$88)*_xlpm.rf-$E$57:$E$88,_xlpm.rel,SUMPRODUCT(_xlpm.x*(_xlpm.x>0)),($B$28+_xlpm.rel)/$B$29)} -> 2.7709491 | D37: {=_xlfn.LET(_xlpm.rf,INDEX($F$57:$L$88,0,MATCH($B37,$F$56:$L$56,0)),_xlpm.x,($C$57:$C$88*(1-D$35)+$D$57:$D$88)*_xlpm.rf-$E$57:$E$88,_xlpm.rel,SUMPRODUCT(_xlpm.x*(_xlpm.x>0)),($B$28+_xlpm.rel)/$B$29)} -> 2.5909188 | E37: {=_xlfn.LET(_xlpm.rf,INDEX($F$57:$L$88,0,MATCH($B37,$F$56:$L$56,0)),_xlpm.x,($C$57:$C$88*(1-E$35)+$D$57:$D$88)*_xlpm.rf-$E$57:$E$88,_xlpm.rel,SUMPRODUCT(_xlpm.x*(_xlpm.x>0)),($B$28+_xlpm.rel)/$B$29)} -> 2.4134341 | F37: {=_xlfn.LET(_xlpm.rf,INDEX($F$57:$L$88,0,MATCH($B37,$F$56:$L$56,0)),_xlpm.x,($C$57:$C$88*(1-F$35)+$D$57:$D$88)*_xlpm.rf-$E$57:$E$88,_xlpm.rel,SUMPRODUCT(_xlpm.x*(_xlpm.x>0)),($B$28+_xlpm.rel)/$B$29)} -> 2.2433021 | G37: {=_xlfn.LET(_xlpm.rf,INDEX($F$57:$L$88,0,MATCH($B37,$F$56:$L$56,0)),_xlpm.x,($C$57:$C$88*(1-G$35)+$D$57:$D$88)*_xlpm.rf-$E$57:$E$88,_xlpm.rel,SUMPRODUCT(_xlpm.x*(_xlpm.x>0)),($B$28+_xlpm.rel)/$B$29)} -> 2.0731701 | H37: {=_xlfn.LET(_xlpm.rf,INDEX($F$57:$L$88,0,MATCH($B37,$F$56:$L$56,0)),_xlpm.x,($C$57:$C$88*(1-H$35)+$D$57:$D$88)*_xlpm.rf-$E$57:$E$88,_xlpm.rel,SUMPRODUCT(_xlpm.x*(_xlpm.x>0)),($B$28+_xlpm.rel)/$B$29)} -> 1.9069999 | I37: {=_xlfn.LET(_xlpm.rf,INDEX($F$57:$L$88,0,MATCH($B37,$F$56:$L$56,0)),_xlpm.x,($C$57:$C$88*(1-I$35)+$D$57:$D$88)*_xlpm.rf-$E$57:$E$88,_xlpm.rel,SUMPRODUCT(_xlpm.x*(_xlpm.x>0)),($B$28+_xlpm.rel)/$B$29)} -> 1.7478787 | K37: 1.00x to 1.50x — tight
B38: 10 | C38: {=_xlfn.LET(_xlpm.rf,INDEX($F$57:$L$88,0,MATCH($B38,$F$56:$L$56,0)),_xlpm.x,($C$57:$C$88*(1-C$35)+$D$57:$D$88)*_xlpm.rf-$E$57:$E$88,_xlpm.rel,SUMPRODUCT(_xlpm.x*(_xlpm.x>0)),($B$28+_xlpm.rel)/$B$29)} -> 1.9757644 | D38: {=_xlfn.LET(_xlpm.rf,INDEX($F$57:$L$88,0,MATCH($B38,$F$56:$L$56,0)),_xlpm.x,($C$57:$C$88*(1-D$35)+$D$57:$D$88)*_xlpm.rf-$E$57:$E$88,_xlpm.rel,SUMPRODUCT(_xlpm.x*(_xlpm.x>0)),($B$28+_xlpm.rel)/$B$29)} -> 1.8313953 | E38: {=_xlfn.LET(_xlpm.rf,INDEX($F$57:$L$88,0,MATCH($B38,$F$56:$L$56,0)),_xlpm.x,($C$57:$C$88*(1-E$35)+$D$57:$D$88)*_xlpm.rf-$E$57:$E$88,_xlpm.rel,SUMPRODUCT(_xlpm.x*(_xlpm.x>0)),($B$28+_xlpm.rel)/$B$29)} -> 1.6900852 | F38: {=_xlfn.LET(_xlpm.rf,INDEX($F$57:$L$88,0,MATCH($B38,$F$56:$L$56,0)),_xlpm.x,($C$57:$C$88*(1-F$35)+$D$57:$D$88)*_xlpm.rf-$E$57:$E$88,_xlpm.rel,SUMPRODUCT(_xlpm.x*(_xlpm.x>0)),($B$28+_xlpm.rel)/$B$29)} -> 1.5555883 | G38: {=_xlfn.LET(_xlpm.rf,INDEX($F$57:$L$88,0,MATCH($B38,$F$56:$L$56,0)),_xlpm.x,($C$57:$C$88*(1-G$35)+$D$57:$D$88)*_xlpm.rf-$E$57:$E$88,_xlpm.rel,SUMPRODUCT(_xlpm.x*(_xlpm.x>0)),($B$28+_xlpm.rel)/$B$29)} -> 1.424231 | H38: {=_xlfn.LET(_xlpm.rf,INDEX($F$57:$L$88,0,MATCH($B38,$F$56:$L$56,0)),_xlpm.x,($C$57:$C$88*(1-H$35)+$D$57:$D$88)*_xlpm.rf-$E$57:$E$88,_xlpm.rel,SUMPRODUCT(_xlpm.x*(_xlpm.x>0)),($B$28+_xlpm.rel)/$B$29)} -> 1.3007349 | I38: {=_xlfn.LET(_xlpm.rf,INDEX($F$57:$L$88,0,MATCH($B38,$F$56:$L$56,0)),_xlpm.x,($C$57:$C$88*(1-I$35)+$D$57:$D$88)*_xlpm.rf-$E$57:$E$88,_xlpm.rel,SUMPRODUCT(_xlpm.x*(_xlpm.x>0)),($B$28+_xlpm.rel)/$B$29)} -> 1.1772387 | K38: above 1.50x — headroom
B39: 15 | C39: {=_xlfn.LET(_xlpm.rf,INDEX($F$57:$L$88,0,MATCH($B39,$F$56:$L$56,0)),_xlpm.x,($C$57:$C$88*(1-C$35)+$D$57:$D$88)*_xlpm.rf-$E$57:$E$88,_xlpm.rel,SUMPRODUCT(_xlpm.x*(_xlpm.x>0)),($B$28+_xlpm.rel)/$B$29)} -> 1.4956877 | D39: {=_xlfn.LET(_xlpm.rf,INDEX($F$57:$L$88,0,MATCH($B39,$F$56:$L$56,0)),_xlpm.x,($C$57:$C$88*(1-D$35)+$D$57:$D$88)*_xlpm.rf-$E$57:$E$88,_xlpm.rel,SUMPRODUCT(_xlpm.x*(_xlpm.x>0)),($B$28+_xlpm.rel)/$B$29)} -> 1.373091 | E39: {=_xlfn.LET(_xlpm.rf,INDEX($F$57:$L$88,0,MATCH($B39,$F$56:$L$56,0)),_xlpm.x,($C$57:$C$88*(1-E$35)+$D$57:$D$88)*_xlpm.rf-$E$57:$E$88,_xlpm.rel,SUMPRODUCT(_xlpm.x*(_xlpm.x>0)),($B$28+_xlpm.rel)/$B$29)} -> 1.2538219 | F39: {=_xlfn.LET(_xlpm.rf,INDEX($F$57:$L$88,0,MATCH($B39,$F$56:$L$56,0)),_xlpm.x,($C$57:$C$88*(1-F$35)+$D$57:$D$88)*_xlpm.rf-$E$57:$E$88,_xlpm.rel,SUMPRODUCT(_xlpm.x*(_xlpm.x>0)),($B$28+_xlpm.rel)/$B$29)} -> 1.1410835 | G39: {=_xlfn.LET(_xlpm.rf,INDEX($F$57:$L$88,0,MATCH($B39,$F$56:$L$56,0)),_xlpm.x,($C$57:$C$88*(1-G$35)+$D$57:$D$88)*_xlpm.rf-$E$57:$E$88,_xlpm.rel,SUMPRODUCT(_xlpm.x*(_xlpm.x>0)),($B$28+_xlpm.rel)/$B$29)} -> 1.0373765 | H39: {=_xlfn.LET(_xlpm.rf,INDEX($F$57:$L$88,0,MATCH($B39,$F$56:$L$56,0)),_xlpm.x,($C$57:$C$88*(1-H$35)+$D$57:$D$88)*_xlpm.rf-$E$57:$E$88,_xlpm.rel,SUMPRODUCT(_xlpm.x*(_xlpm.x>0)),($B$28+_xlpm.rel)/$B$29)} -> 0.93529373 | I39: {=_xlfn.LET(_xlpm.rf,INDEX($F$57:$L$88,0,MATCH($B39,$F$56:$L$56,0)),_xlpm.x,($C$57:$C$88*(1-I$35)+$D$57:$D$88)*_xlpm.rf-$E$57:$E$88,_xlpm.rel,SUMPRODUCT(_xlpm.x*(_xlpm.x>0)),($B$28+_xlpm.rel)/$B$29)} -> 0.8369517
B40: 20 | C40: {=_xlfn.LET(_xlpm.rf,INDEX($F$57:$L$88,0,MATCH($B40,$F$56:$L$56,0)),_xlpm.x,($C$57:$C$88*(1-C$35)+$D$57:$D$88)*_xlpm.rf-$E$57:$E$88,_xlpm.rel,SUMPRODUCT(_xlpm.x*(_xlpm.x>0)),($B$28+_xlpm.rel)/$B$29)} -> 1.238056 | D40: {=_xlfn.LET(_xlpm.rf,INDEX($F$57:$L$88,0,MATCH($B40,$F$56:$L$56,0)),_xlpm.x,($C$57:$C$88*(1-D$35)+$D$57:$D$88)*_xlpm.rf-$E$57:$E$88,_xlpm.rel,SUMPRODUCT(_xlpm.x*(_xlpm.x>0)),($B$28+_xlpm.rel)/$B$29)} -> 1.1271342 | E40: {=_xlfn.LET(_xlpm.rf,INDEX($F$57:$L$88,0,MATCH($B40,$F$56:$L$56,0)),_xlpm.x,($C$57:$C$88*(1-E$35)+$D$57:$D$88)*_xlpm.rf-$E$57:$E$88,_xlpm.rel,SUMPRODUCT(_xlpm.x*(_xlpm.x>0)),($B$28+_xlpm.rel)/$B$29)} -> 1.0197052 | F40: {=_xlfn.LET(_xlpm.rf,INDEX($F$57:$L$88,0,MATCH($B40,$F$56:$L$56,0)),_xlpm.x,($C$57:$C$88*(1-F$35)+$D$57:$D$88)*_xlpm.rf-$E$57:$E$88,_xlpm.rel,SUMPRODUCT(_xlpm.x*(_xlpm.x>0)),($B$28+_xlpm.rel)/$B$29)} -> 0.92079571 | G40: {=_xlfn.LET(_xlpm.rf,INDEX($F$57:$L$88,0,MATCH($B40,$F$56:$L$56,0)),_xlpm.x,($C$57:$C$88*(1-G$35)+$D$57:$D$88)*_xlpm.rf-$E$57:$E$88,_xlpm.rel,SUMPRODUCT(_xlpm.x*(_xlpm.x>0)),($B$28+_xlpm.rel)/$B$29)} -> 0.83016971 | H40: {=_xlfn.LET(_xlpm.rf,INDEX($F$57:$L$88,0,MATCH($B40,$F$56:$L$56,0)),_xlpm.x,($C$57:$C$88*(1-H$35)+$D$57:$D$88)*_xlpm.rf-$E$57:$E$88,_xlpm.rel,SUMPRODUCT(_xlpm.x*(_xlpm.x>0)),($B$28+_xlpm.rel)/$B$29)} -> 0.74157034 | I40: {=_xlfn.LET(_xlpm.rf,INDEX($F$57:$L$88,0,MATCH($B40,$F$56:$L$56,0)),_xlpm.x,($C$57:$C$88*(1-I$35)+$D$57:$D$88)*_xlpm.rf-$E$57:$E$88,_xlpm.rel,SUMPRODUCT(_xlpm.x*(_xlpm.x>0)),($B$28+_xlpm.rel)/$B$29)} -> 0.65990916
B41: 25 | C41: {=_xlfn.LET(_xlpm.rf,INDEX($F$57:$L$88,0,MATCH($B41,$F$56:$L$56,0)),_xlpm.x,($C$57:$C$88*(1-C$35)+$D$57:$D$88)*_xlpm.rf-$E$57:$E$88,_xlpm.rel,SUMPRODUCT(_xlpm.x*(_xlpm.x>0)),($B$28+_xlpm.rel)/$B$29)} -> 1.0774232 | D41: {=_xlfn.LET(_xlpm.rf,INDEX($F$57:$L$88,0,MATCH($B41,$F$56:$L$56,0)),_xlpm.x,($C$57:$C$88*(1-D$35)+$D$57:$D$88)*_xlpm.rf-$E$57:$E$88,_xlpm.rel,SUMPRODUCT(_xlpm.x*(_xlpm.x>0)),($B$28+_xlpm.rel)/$B$29)} -> 0.97377804 | E41: {=_xlfn.LET(_xlpm.rf,INDEX($F$57:$L$88,0,MATCH($B41,$F$56:$L$56,0)),_xlpm.x,($C$57:$C$88*(1-E$35)+$D$57:$D$88)*_xlpm.rf-$E$57:$E$88,_xlpm.rel,SUMPRODUCT(_xlpm.x*(_xlpm.x>0)),($B$28+_xlpm.rel)/$B$29)} -> 0.87373763 | F41: {=_xlfn.LET(_xlpm.rf,INDEX($F$57:$L$88,0,MATCH($B41,$F$56:$L$56,0)),_xlpm.x,($C$57:$C$88*(1-F$35)+$D$57:$D$88)*_xlpm.rf-$E$57:$E$88,_xlpm.rel,SUMPRODUCT(_xlpm.x*(_xlpm.x>0)),($B$28+_xlpm.rel)/$B$29)} -> 0.78464204 | G41: {=_xlfn.LET(_xlpm.rf,INDEX($F$57:$L$88,0,MATCH($B41,$F$56:$L$56,0)),_xlpm.x,($C$57:$C$88*(1-G$35)+$D$57:$D$88)*_xlpm.rf-$E$57:$E$88,_xlpm.rel,SUMPRODUCT(_xlpm.x*(_xlpm.x>0)),($B$28+_xlpm.rel)/$B$29)} -> 0.70114627 | H41: {=_xlfn.LET(_xlpm.rf,INDEX($F$57:$L$88,0,MATCH($B41,$F$56:$L$56,0)),_xlpm.x,($C$57:$C$88*(1-H$35)+$D$57:$D$88)*_xlpm.rf-$E$57:$E$88,_xlpm.rel,SUMPRODUCT(_xlpm.x*(_xlpm.x>0)),($B$28+_xlpm.rel)/$B$29)} -> 0.62458788 | I41: {=_xlfn.LET(_xlpm.rf,INDEX($F$57:$L$88,0,MATCH($B41,$F$56:$L$56,0)),_xlpm.x,($C$57:$C$88*(1-I$35)+$D$57:$D$88)*_xlpm.rf-$E$57:$E$88,_xlpm.rel,SUMPRODUCT(_xlpm.x*(_xlpm.x>0)),($B$28+_xlpm.rel)/$B$29)} -> 0.55207544
B42: 30 | C42: {=_xlfn.LET(_xlpm.rf,INDEX($F$57:$L$88,0,MATCH($B42,$F$56:$L$56,0)),_xlpm.x,($C$57:$C$88*(1-C$35)+$D$57:$D$88)*_xlpm.rf-$E$57:$E$88,_xlpm.rel,SUMPRODUCT(_xlpm.x*(_xlpm.x>0)),($B$28+_xlpm.rel)/$B$29)} -> 0.96774187 | D42: {=_xlfn.LET(_xlpm.rf,INDEX($F$57:$L$88,0,MATCH($B42,$F$56:$L$56,0)),_xlpm.x,($C$57:$C$88*(1-D$35)+$D$57:$D$88)*_xlpm.rf-$E$57:$E$88,_xlpm.rel,SUMPRODUCT(_xlpm.x*(_xlpm.x>0)),($B$28+_xlpm.rel)/$B$29)} -> 0.8690646 | E42: {=_xlfn.LET(_xlpm.rf,INDEX($F$57:$L$88,0,MATCH($B42,$F$56:$L$56,0)),_xlpm.x,($C$57:$C$88*(1-E$35)+$D$57:$D$88)*_xlpm.rf-$E$57:$E$88,_xlpm.rel,SUMPRODUCT(_xlpm.x*(_xlpm.x>0)),($B$28+_xlpm.rel)/$B$29)} -> 0.77407284 | F42: {=_xlfn.LET(_xlpm.rf,INDEX($F$57:$L$88,0,MATCH($B42,$F$56:$L$56,0)),_xlpm.x,($C$57:$C$88*(1-F$35)+$D$57:$D$88)*_xlpm.rf-$E$57:$E$88,_xlpm.rel,SUMPRODUCT(_xlpm.x*(_xlpm.x>0)),($B$28+_xlpm.rel)/$B$29)} -> 0.69176633 | G42: {=_xlfn.LET(_xlpm.rf,INDEX($F$57:$L$88,0,MATCH($B42,$F$56:$L$56,0)),_xlpm.x,($C$57:$C$88*(1-G$35)+$D$57:$D$88)*_xlpm.rf-$E$57:$E$88,_xlpm.rel,SUMPRODUCT(_xlpm.x*(_xlpm.x>0)),($B$28+_xlpm.rel)/$B$29)} -> 0.61545804 | H42: {=_xlfn.LET(_xlpm.rf,INDEX($F$57:$L$88,0,MATCH($B42,$F$56:$L$56,0)),_xlpm.x,($C$57:$C$88*(1-H$35)+$D$57:$D$88)*_xlpm.rf-$E$57:$E$88,_xlpm.rel,SUMPRODUCT(_xlpm.x*(_xlpm.x>0)),($B$28+_xlpm.rel)/$B$29)} -> 0.54561027 | I42: {=_xlfn.LET(_xlpm.rf,INDEX($F$57:$L$88,0,MATCH($B42,$F$56:$L$56,0)),_xlpm.x,($C$57:$C$88*(1-I$35)+$D$57:$D$88)*_xlpm.rf-$E$57:$E$88,_xlpm.rel,SUMPRODUCT(_xlpm.x*(_xlpm.x>0)),($B$28+_xlpm.rel)/$B$29)} -> 0.48025351
A44: 5. BREAK-EVEN AND TIE-OUT CHECKS
A45: Handover delay that brings escrow headroom to 1.00x, with no cancellations (months) | B45: {=_xlfn.LET(_xlpm.d,$B$36:$B$42,_xlpm.c,$C$36:$C$42,_xlpm.i,MATCH(TRUE,_xlpm.c<1,0),IF(ISNA(_xlpm.i),"beyond "&MAX(_xlpm.d)&" months",INDEX(_xlpm.d,_xlpm.i-1)+(INDEX(_xlpm.c,_xlpm.i-1)-1)/(INDEX(_xlpm.c,_xlpm.i-1)-INDEX(_xlpm.c,_xlpm.i))*(INDEX(_xlpm.d,_xlpm.i)-INDEX(_xlpm.d,_xlpm.i-1))))} -> 28.529461
A46: Cancellation rate that brings escrow headroom to 1.00x, with no delay | B46: {=_xlfn.LET(_xlpm.r,$C$35:$I$35,_xlpm.c,$C$36:$I$36,_xlpm.i,MATCH(TRUE,_xlpm.c<1,0),IF(ISNA(_xlpm.i),"beyond "&TEXT(MAX(_xlpm.r),"0%"),INDEX(_xlpm.r,_xlpm.i-1)+(INDEX(_xlpm.c,_xlpm.i-1)-1)/(INDEX(_xlpm.c,_xlpm.i-1)-INDEX(_xlpm.c,_xlpm.i))*(INDEX(_xlpm.r,_xlpm.i)-INDEX(_xlpm.r,_xlpm.i-1))))} -> beyond 30%
A47: Handover delay that brings escrow headroom to 1.00x if cancellations run at 15% (months) | B47: {=_xlfn.LET(_xlpm.d,$B$36:$B$42,_xlpm.c,$F$36:$F$42,_xlpm.i,MATCH(TRUE,_xlpm.c<1,0),IF(ISNA(_xlpm.i),"beyond "&MAX(_xlpm.d)&" months",INDEX(_xlpm.d,_xlpm.i-1)+(INDEX(_xlpm.c,_xlpm.i-1)-1)/(INDEX(_xlpm.c,_xlpm.i-1)-INDEX(_xlpm.c,_xlpm.i))*(INDEX(_xlpm.d,_xlpm.i)-INDEX(_xlpm.d,_xlpm.i-1))))} -> 18.202254
A49: Check — base corner against Dashboard section 1 headroom | B49: =$C$36-Dashboard!$F$17 -> 0 | C49: Must be zero. Confirms this sheet reproduces the Dashboard headroom measure independently, from first principles.
A50: Check — contracted value against Simulator | B50: =$C$89-Simulator!$J$40 -> 0 | C50: Must be zero.
A51: Check — release to date against Simulator | B51: =$E$89-Simulator!$Q$40 -> 0 | C51: Zero while the active scenario shares the Base booking, handover and retention shares — true of all four scenarios as shipped. A non-zero figure means someone changed those terms in the active column, not that this sheet is wrong.
A52: Check — live projects included | B52: =COUNT($C$57:$C$88) -> 32 | C52: Must equal 32, the count of live projects on the Simulator.
A54: 6. WORKING — ONE ROW PER LIVE PROJECT
A55: Release factor is the share of effective contracted value that escrow has released by the checkpoint, net of retention. Contracted value, future sales value and release to date are taken from the Simulator; the release factors are recomputed here at each delay on the axis.
A56: Project no. | B56: Project | C56: Contracted value | D56: Future sales value | E56: Released to date | F56: =$B36 -> 0 | G56: =$B37 -> 5 | H56: =$B38 -> 10 | I56: =$B39 -> 15 | J56: =$B40 -> 20 | K56: =$B41 -> 25 | L56: =$B42 -> 30
A57: =Simulator!A8 -> 3165 | B57: =Simulator!B8 -> Binghatti Aurora | C57: =Simulator!J8 -> 253.10904 | D57: =Simulator!K8*Simulator!G8/1000000*$B$18*(1+$B$19) -> 13.205689 | E57: =Simulator!$J8*IF(Simulator!$H8>=100,1,$B$20+(1-$B$20-$B$21)*Simulator!$H8/100)*MIN(1,Simulator!$H8/100)*(1-$B$22) -> 29.610218 | F57: =_xlfn.LET(_xlpm.d,F$56,_xlpm.cert,Simulator!$H8,_xlpm.regd,Simulator!$I8,_xlpm.compl,IF(_xlpm.regd="",EDATE($B$26,$B$25+_xlpm.d),IF(_xlpm.regd<$B$26,EDATE($B$26,$B$24+_xlpm.d),EDATE(_xlpm.regd,_xlpm.d))),_xlpm.n,MAX(1,(YEAR(_xlpm.compl)-YEAR($B$26))*12+MONTH(_xlpm.compl)-MONTH($B$26)),_xlpm.pace,MIN($B$23,(100-_xlpm.cert)/_xlpm.n),_xlpm.c,MIN(100,_xlpm.cert+_xlpm.pace*$B$27),IF(_xlpm.c>=100,1,$B$20+(1-$B$20-$B$21)*_xlpm.c/100)*MIN(1,_xlpm.c/100)*(1-$B$22)) -> 0.41823482 | G57: =_xlfn.LET(_xlpm.d,G$56,_xlpm.cert,Simulator!$H8,_xlpm.regd,Simulator!$I8,_xlpm.compl,IF(_xlpm.regd="",EDATE($B$26,$B$25+_xlpm.d),IF(_xlpm.regd<$B$26,EDATE($B$26,$B$24+_xlpm.d),EDATE(_xlpm.regd,_xlpm.d))),_xlpm.n,MAX(1,(YEAR(_xlpm.compl)-YEAR($B$26))*12+MONTH(_xlpm.compl)-MONTH($B$26)),_xlpm.pace,MIN($B$23,(100-_xlpm.cert)/_xlpm.n),_xlpm.c,MIN(100,_xlpm.cert+_xlpm.pace*$B$27),IF(_xlpm.c>=100,1,$B$20+(1-$B$20-$B$21)*_xlpm.c/100)*MIN(1,_xlpm.c/100)*(1-$B$22)) -> 0.31128481 | H57: =_xlfn.LET(_xlpm.d,H$56,_xlpm.cert,Simulator!$H8,_xlpm.regd,Simulator!$I8,_xlpm.compl,IF(_xlpm.regd="",EDATE($B$26,$B$25+_xlpm.d),IF(_xlpm.regd<$B$26,EDATE($B$26,$B$24+_xlpm.d),EDATE(_xlpm.regd,_xlpm.d))),_xlpm.n,MAX(1,(YEAR(_xlpm.compl)-YEAR($B$26))*12+MONTH(_xlpm.compl)-MONTH($B$26)),_xlpm.pace,MIN($B$23,(100-_xlpm.cert)/_xlpm.n),_xlpm.c,MIN(100,_xlpm.cert+_xlpm.pace*$B$27),IF(_xlpm.c>=100,1,$B$20+(1-$B$20-$B$21)*_xlpm.c/100)*MIN(1,_xlpm.c/100)*(1-$B$22)) -> 0.24075551 | I57: =_xlfn.LET(_xlpm.d,I$56,_xlpm.cert,Simulator!$H8,_xlpm.regd,Simulator!$I8,_xlpm.compl,IF(_xlpm.regd="",EDATE($B$26,$B$25+_xlpm.d),IF(_xlpm.regd<$B$26,EDATE($B$26,$B$24+_xlpm.d),EDATE(_xlpm.regd,_xlpm.d))),_xlpm.n,MAX(1,(YEAR(_xlpm.compl)-YEAR($B$26))*12+MONTH(_xlpm.compl)-MONTH($B$26)),_xlpm.pace,MIN($B$23,(100-_xlpm.cert)/_xlpm.n),_xlpm.c,MIN(100,_xlpm.cert+_xlpm.pace*$B$27),IF(_xlpm.c>=100,1,$B$20+(1-$B$20-$B$21)*_xlpm.c/100)*MIN(1,_xlpm.c/100)*(1-$B$22)) -> 0.20737111 | J57: =_xlfn.LET(_xlpm.d,J$56,_xlpm.cert,Simulator!$H8,_xlpm.regd,Simulator!$I8,_xlpm.compl,IF(_xlpm.regd="",EDATE($B$26,$B$25+_xlpm.d),IF(_xlpm.regd<$B$26,EDATE($B$26,$B$24+_xlpm.d),EDATE(_xlpm.regd,_xlpm.d))),_xlpm.n,MAX(1,(YEAR(_xlpm.compl)-YEAR($B$26))*12+MONTH(_xlpm.compl)-MONTH($B$26)),_xlpm.pace,MIN($B$23,(100-_xlpm.cert)/_xlpm.n),_xlpm.c,MIN(100,_xlpm.cert+_xlpm.pace*$B$27),IF(_xlpm.c>=100,1,$B$20+(1-$B$20-$B$21)*_xlpm.c/100)*MIN(1,_xlpm.c/100)*(1-$B$22)) -> 0.18804321 | K57: =_xlfn.LET(_xlpm.d,K$56,_xlpm.cert,Simulator!$H8,_xlpm.regd,Simulator!$I8,_xlpm.compl,IF(_xlpm.regd="",EDATE($B$26,$B$25+_xlpm.d),IF(_xlpm.regd<$B$26,EDATE($B$26,$B$24+_xlpm.d),EDATE(_xlpm.regd,_xlpm.d))),_xlpm.n,MAX(1,(YEAR(_xlpm.compl)-YEAR($B$26))*12+MONTH(_xlpm.compl)-MONTH($B$26)),_xlpm.pace,MIN($B$23,(100-_xlpm.cert)/_xlpm.n),_xlpm.c,MIN(100,_xlpm.cert+_xlpm.pace*$B$27),IF(_xlpm.c>=100,1,$B$20+(1-$B$20-$B$21)*_xlpm.c/100)*MIN(1,_xlpm.c/100)*(1-$B$22)) -> 0.17547665 | L57: =_xlfn.LET(_xlpm.d,L$56,_xlpm.cert,Simulator!$H8,_xlpm.regd,Simulator!$I8,_xlpm.compl,IF(_xlpm.regd="",EDATE($B$26,$B$25+_xlpm.d),IF(_xlpm.regd<$B$26,EDATE($B$26,$B$24+_xlpm.d),EDATE(_xlpm.regd,_xlpm.d))),_xlpm.n,MAX(1,(YEAR(_xlpm.compl)-YEAR($B$26))*12+MONTH(_xlpm.compl)-MONTH($B$26)),_xlpm.pace,MIN($B$23,(100-_xlpm.cert)/_xlpm.n),_xlpm.c,MIN(100,_xlpm.cert+_xlpm.pace*$B$27),IF(_xlpm.c>=100,1,$B$20+(1-$B$20-$B$21)*_xlpm.c/100)*MIN(1,_xlpm.c/100)*(1-$B$22)) -> 0.16666529
A58: =Simulator!A9 -> 3264 | B58: =Simulator!B9 -> Binghatti Ivory | C58: =Simulator!J9 -> 542.45393 | D58: =Simulator!K9*Simulator!G9/1000000*$B$18*(1+$B$19) -> 7.0101738 | E58: =Simulator!$J9*IF(Simulator!$H9>=100,1,$B$20+(1-$B$20-$B$21)*Simulator!$H9/100)*MIN(1,Simulator!$H9/100)*(1-$B$22) -> 43.525185 | F58: =_xlfn.LET(_xlpm.d,F$56,_xlpm.cert,Simulator!$H9,_xlpm.regd,Simulator!$I9,_xlpm.compl,IF(_xlpm.regd="",EDATE($B$26,$B$25+_xlpm.d),IF(_xlpm.regd<$B$26,EDATE($B$26,$B$24+_xlpm.d),EDATE(_xlpm.regd,_xlpm.d))),_xlpm.n,MAX(1,(YEAR(_xlpm.compl)-YEAR($B$26))*12+MONTH(_xlpm.compl)-MONTH($B$26)),_xlpm.pace,MIN($B$23,(100-_xlpm.cert)/_xlpm.n),_xlpm.c,MIN(100,_xlpm.cert+_xlpm.pace*$B$27),IF(_xlpm.c>=100,1,$B$20+(1-$B$20-$B$21)*_xlpm.c/100)*MIN(1,_xlpm.c/100)*(1-$B$22)) -> 0.34669357 | G58: =_xlfn.LET(_xlpm.d,G$56,_xlpm.cert,Simulator!$H9,_xlpm.regd,Simulator!$I9,_xlpm.compl,IF(_xlpm.regd="",EDATE($B$26,$B$25+_xlpm.d),IF(_xlpm.regd<$B$26,EDATE($B$26,$B$24+_xlpm.d),EDATE(_xlpm.regd,_xlpm.d))),_xlpm.n,MAX(1,(YEAR(_xlpm.compl)-YEAR($B$26))*12+MONTH(_xlpm.compl)-MONTH($B$26)),_xlpm.pace,MIN($B$23,(100-_xlpm.cert)/_xlpm.n),_xlpm.c,MIN(100,_xlpm.cert+_xlpm.pace*$B$27),IF(_xlpm.c>=100,1,$B$20+(1-$B$20-$B$21)*_xlpm.c/100)*MIN(1,_xlpm.c/100)*(1-$B$22)) -> 0.27698845 | H58: =_xlfn.LET(_xlpm.d,H$56,_xlpm.cert,Simulator!$H9,_xlpm.regd,Simulator!$I9,_xlpm.compl,IF(_xlpm.regd="",EDATE($B$26,$B$25+_xlpm.d),IF(_xlpm.regd<$B$26,EDATE($B$26,$B$24+_xlpm.d),EDATE(_xlpm.regd,_xlpm.d))),_xlpm.n,MAX(1,(YEAR(_xlpm.compl)-YEAR($B$26))*12+MONTH(_xlpm.compl)-MONTH($B$26)),_xlpm.pace,MIN($B$23,(100-_xlpm.cert)/_xlpm.n),_xlpm.c,MIN(100,_xlpm.cert+_xlpm.pace*$B$27),IF(_xlpm.c>=100,1,$B$20+(1-$B$20-$B$21)*_xlpm.c/100)*MIN(1,_xlpm.c/100)*(1-$B$22)) -> 0.20314129 | I58: =_xlfn.LET(_xlpm.d,I$56,_xlpm.cert,Simulator!$H9,_xlpm.regd,Simulator!$I9,_xlpm.compl,IF(_xlpm.regd="",EDATE($B$26,$B$25+_xlpm.d),IF(_xlpm.regd<$B$26,EDATE($B$26,$B$24+_xlpm.d),EDATE(_xlpm.regd,_xlpm.d))),_xlpm.n,MAX(1,(YEAR(_xlpm.compl)-YEAR($B$26))*12+MONTH(_xlpm.compl)-MONTH($B$26)),_xlpm.pace,MIN($B$23,(100-_xlpm.cert)/_xlpm.n),_xlpm.c,MIN(100,_xlpm.cert+_xlpm.pace*$B$27),IF(_xlpm.c>=100,1,$B$20+(1-$B$20-$B$21)*_xlpm.c/100)*MIN(1,_xlpm.c/100)*(1-$B$22)) -> 0.16894471 | J58: =_xlfn.LET(_xlpm.d,J$56,_xlpm.cert,Simulator!$H9,_xlpm.regd,Simulator!$I9,_xlpm.compl,IF(_xlpm.regd="",EDATE($B$26,$B$25+_xlpm.d),IF(_xlpm.regd<$B$26,EDATE($B$26,$B$24+_xlpm.d),EDATE(_xlpm.regd,_xlpm.d))),_xlpm.n,MAX(1,(YEAR(_xlpm.compl)-YEAR($B$26))*12+MONTH(_xlpm.compl)-MONTH($B$26)),_xlpm.pace,MIN($B$23,(100-_xlpm.cert)/_xlpm.n),_xlpm.c,MIN(100,_xlpm.cert+_xlpm.pace*$B$27),IF(_xlpm.c>=100,1,$B$20+(1-$B$20-$B$21)*_xlpm.c/100)*MIN(1,_xlpm.c/100)*(1-$B$22)) -> 0.14943335 | K58: =_xlfn.LET(_xlpm.d,K$56,_xlpm.cert,Simulator!$H9,_xlpm.regd,Simulator!$I9,_xlpm.compl,IF(_xlpm.regd="",EDATE($B$26,$B$25+_xlpm.d),IF(_xlpm.regd<$B$26,EDATE($B$26,$B$24+_xlpm.d),EDATE(_xlpm.regd,_xlpm.d))),_xlpm.n,MAX(1,(YEAR(_xlpm.compl)-YEAR($B$26))*12+MONTH(_xlpm.compl)-MONTH($B$26)),_xlpm.pace,MIN($B$23,(100-_xlpm.cert)/_xlpm.n),_xlpm.c,MIN(100,_xlpm.cert+_xlpm.pace*$B$27),IF(_xlpm.c>=100,1,$B$20+(1-$B$20-$B$21)*_xlpm.c/100)*MIN(1,_xlpm.c/100)*(1-$B$22)) -> 0.13687945 | L58: =_xlfn.LET(_xlpm.d,L$56,_xlpm.cert,Simulator!$H9,_xlpm.regd,Simulator!$I9,_xlpm.compl,IF(_xlpm.regd="",EDATE($B$26,$B$25+_xlpm.d),IF(_xlpm.regd<$B$26,EDATE($B$26,$B$24+_xlpm.d),EDATE(_xlpm.regd,_xlpm.d))),_xlpm.n,MAX(1,(YEAR(_xlpm.compl)-YEAR($B$26))*12+MONTH(_xlpm.compl)-MONTH($B$26)),_xlpm.pace,MIN($B$23,(100-_xlpm.cert)/_xlpm.n),_xlpm.c,MIN(100,_xlpm.cert+_xlpm.pace*$B$27),IF(_xlpm.c>=100,1,$B$20+(1-$B$20-$B$21)*_xlpm.c/100)*MIN(1,_xlpm.c/100)*(1-$B$22)) -> 0.12814601
A59: =Simulator!A10 -> 2547 | B59: =Simulator!B10 -> Bugatti Residences by Binghatti | C59: =Simulator!J10 -> 3613.0509 | D59: =Simulator!K10*Simulator!G10/1000000*$B$18*(1+$B$19) -> 1509.7391 | E59: =Simulator!$J10*IF(Simulator!$H10>=100,1,$B$20+(1-$B$20-$B$21)*Simulator!$H10/100)*MIN(1,Simulator!$H10/100)*(1-$B$22) -> 151.49266 | F59: =_xlfn.LET(_xlpm.d,F$56,_xlpm.cert,Simulator!$H10,_xlpm.regd,Simulator!$I10,_xlpm.compl,IF(_xlpm.regd="",EDATE($B$26,$B$25+_xlpm.d),IF(_xlpm.regd<$B$26,EDATE($B$26,$B$24+_xlpm.d),EDATE(_xlpm.regd,_xlpm.d))),_xlpm.n,MAX(1,(YEAR(_xlpm.compl)-YEAR($B$26))*12+MONTH(_xlpm.compl)-MONTH($B$26)),_xlpm.pace,MIN($B$23,(100-_xlpm.cert)/_xlpm.n),_xlpm.c,MIN(100,_xlpm.cert+_xlpm.pace*$B$27),IF(_xlpm.c>=100,1,$B$20+(1-$B$20-$B$21)*_xlpm.c/100)*MIN(1,_xlpm.c/100)*(1-$B$22)) -> 0.26251169 | G59: =_xlfn.LET(_xlpm.d,G$56,_xlpm.cert,Simulator!$H10,_xlpm.regd,Simulator!$I10,_xlpm.compl,IF(_xlpm.regd="",EDATE($B$26,$B$25+_xlpm.d),IF(_xlpm.regd<$B$26,EDATE($B$26,$B$24+_xlpm.d),EDATE(_xlpm.regd,_xlpm.d))),_xlpm.n,MAX(1,(YEAR(_xlpm.compl)-YEAR($B$26))*12+MONTH(_xlpm.compl)-MONTH($B$26)),_xlpm.pace,MIN($B$23,(100-_xlpm.cert)/_xlpm.n),_xlpm.c,MIN(100,_xlpm.cert+_xlpm.pace*$B$27),IF(_xlpm.c>=100,1,$B$20+(1-$B$20-$B$21)*_xlpm.c/100)*MIN(1,_xlpm.c/100)*(1-$B$22)) -> 0.23478739 | H59: =_xlfn.LET(_xlpm.d,H$56,_xlpm.cert,Simulator!$H10,_xlpm.regd,Simulator!$I10,_xlpm.compl,IF(_xlpm.regd="",EDATE($B$26,$B$25+_xlpm.d),IF(_xlpm.regd<$B$26,EDATE($B$26,$B$24+_xlpm.d),EDATE(_xlpm.regd,_xlpm.d))),_xlpm.n,MAX(1,(YEAR(_xlpm.compl)-YEAR($B$26))*12+MONTH(_xlpm.compl)-MONTH($B$26)),_xlpm.pace,MIN($B$23,(100-_xlpm.cert)/_xlpm.n),_xlpm.c,MIN(100,_xlpm.cert+_xlpm.pace*$B$27),IF(_xlpm.c>=100,1,$B$20+(1-$B$20-$B$21)*_xlpm.c/100)*MIN(1,_xlpm.c/100)*(1-$B$22)) -> 0.15834224 | I59: =_xlfn.LET(_xlpm.d,I$56,_xlpm.cert,Simulator!$H10,_xlpm.regd,Simulator!$I10,_xlpm.compl,IF(_xlpm.regd="",EDATE($B$26,$B$25+_xlpm.d),IF(_xlpm.regd<$B$26,EDATE($B$26,$B$24+_xlpm.d),EDATE(_xlpm.regd,_xlpm.d))),_xlpm.n,MAX(1,(YEAR(_xlpm.compl)-YEAR($B$26))*12+MONTH(_xlpm.compl)-MONTH($B$26)),_xlpm.pace,MIN($B$23,(100-_xlpm.cert)/_xlpm.n),_xlpm.c,MIN(100,_xlpm.cert+_xlpm.pace*$B$27),IF(_xlpm.c>=100,1,$B$20+(1-$B$20-$B$21)*_xlpm.c/100)*MIN(1,_xlpm.c/100)*(1-$B$22)) -> 0.12416875 | J59: =_xlfn.LET(_xlpm.d,J$56,_xlpm.cert,Simulator!$H10,_xlpm.regd,Simulator!$I10,_xlpm.compl,IF(_xlpm.regd="",EDATE($B$26,$B$25+_xlpm.d),IF(_xlpm.regd<$B$26,EDATE($B$26,$B$24+_xlpm.d),EDATE(_xlpm.regd,_xlpm.d))),_xlpm.n,MAX(1,(YEAR(_xlpm.compl)-YEAR($B$26))*12+MONTH(_xlpm.compl)-MONTH($B$26)),_xlpm.pace,MIN($B$23,(100-_xlpm.cert)/_xlpm.n),_xlpm.c,MIN(100,_xlpm.cert+_xlpm.pace*$B$27),IF(_xlpm.c>=100,1,$B$20+(1-$B$20-$B$21)*_xlpm.c/100)*MIN(1,_xlpm.c/100)*(1-$B$22)) -> 0.10514451 | K59: =_xlfn.LET(_xlpm.d,K$56,_xlpm.cert,Simulator!$H10,_xlpm.regd,Simulator!$I10,_xlpm.compl,IF(_xlpm.regd="",EDATE($B$26,$B$25+_xlpm.d),IF(_xlpm.regd<$B$26,EDATE($B$26,$B$24+_xlpm.d),EDATE(_xlpm.regd,_xlpm.d))),_xlpm.n,MAX(1,(YEAR(_xlpm.compl)-YEAR($B$26))*12+MONTH(_xlpm.compl)-MONTH($B$26)),_xlpm.pace,MIN($B$23,(100-_xlpm.cert)/_xlpm.n),_xlpm.c,MIN(100,_xlpm.cert+_xlpm.pace*$B$27),IF(_xlpm.c>=100,1,$B$20+(1-$B$20-$B$21)*_xlpm.c/100)*MIN(1,_xlpm.c/100)*(1-$B$22)) -> 0.093125308 | L59: =_xlfn.LET(_xlpm.d,L$56,_xlpm.cert,Simulator!$H10,_xlpm.regd,Simulator!$I10,_xlpm.compl,IF(_xlpm.regd="",EDATE($B$26,$B$25+_xlpm.d),IF(_xlpm.regd<$B$26,EDATE($B$26,$B$24+_xlpm.d),EDATE(_xlpm.regd,_xlpm.d))),_xlpm.n,MAX(1,(YEAR(_xlpm.compl)-YEAR($B$26))*12+MONTH(_xlpm.compl)-MONTH($B$26)),_xlpm.pace,MIN($B$23,(100-_xlpm.cert)/_xlpm.n),_xlpm.c,MIN(100,_xlpm.cert+_xlpm.pace*$B$27),IF(_xlpm.c>=100,1,$B$20+(1-$B$20-$B$21)*_xlpm.c/100)*MIN(1,_xlpm.c/100)*(1-$B$22)) -> 0.084880879
A60: =Simulator!A11 -> 3552 | B60: =Simulator!B11 -> Binghatti Amberhall | C60: =Simulator!J11 -> 795.36649 | D60: =Simulator!K11*Simulator!G11/1000000*$B$18*(1+$B$19) -> 27.737073 | E60: =Simulator!$J11*IF(Simulator!$H11>=100,1,$B$20+(1-$B$20-$B$21)*Simulator!$H11/100)*MIN(1,Simulator!$H11/100)*(1-$B$22) -> 94.177756 | F60: =_xlfn.LET(_xlpm.d,F$56,_xlpm.cert,Simulator!$H11,_xlpm.regd,Simulator!$I11,_xlpm.compl,IF(_xlpm.regd="",EDATE($B$26,$B$25+_xlpm.d),IF(_xlpm.regd<$B$26,EDATE($B$26,$B$24+_xlpm.d),EDATE(_xlpm.regd,_xlpm.d))),_xlpm.n,MAX(1,(YEAR(_xlpm.compl)-YEAR($B$26))*12+MONTH(_xlpm.compl)-MONTH($B$26)),_xlpm.pace,MIN($B$23,(100-_xlpm.cert)/_xlpm.n),_xlpm.c,MIN(100,_xlpm.cert+_xlpm.pace*$B$27),IF(_xlpm.c>=100,1,$B$20+(1-$B$20-$B$21)*_xlpm.c/100)*MIN(1,_xlpm.c/100)*(1-$B$22)) -> 0.420888 | G60: =_xlfn.LET(_xlpm.d,G$56,_xlpm.cert,Simulator!$H11,_xlpm.regd,Simulator!$I11,_xlpm.compl,IF(_xlpm.regd="",EDATE($B$26,$B$25+_xlpm.d),IF(_xlpm.regd<$B$26,EDATE($B$26,$B$24+_xlpm.d),EDATE(_xlpm.regd,_xlpm.d))),_xlpm.n,MAX(1,(YEAR(_xlpm.compl)-YEAR($B$26))*12+MONTH(_xlpm.compl)-MONTH($B$26)),_xlpm.pace,MIN($B$23,(100-_xlpm.cert)/_xlpm.n),_xlpm.c,MIN(100,_xlpm.cert+_xlpm.pace*$B$27),IF(_xlpm.c>=100,1,$B$20+(1-$B$20-$B$21)*_xlpm.c/100)*MIN(1,_xlpm.c/100)*(1-$B$22)) -> 0.31253461 | H60: =_xlfn.LET(_xlpm.d,H$56,_xlpm.cert,Simulator!$H11,_xlpm.regd,Simulator!$I11,_xlpm.compl,IF(_xlpm.regd="",EDATE($B$26,$B$25+_xlpm.d),IF(_xlpm.regd<$B$26,EDATE($B$26,$B$24+_xlpm.d),EDATE(_xlpm.regd,_xlpm.d))),_xlpm.n,MAX(1,(YEAR(_xlpm.compl)-YEAR($B$26))*12+MONTH(_xlpm.compl)-MONTH($B$26)),_xlpm.pace,MIN($B$23,(100-_xlpm.cert)/_xlpm.n),_xlpm.c,MIN(100,_xlpm.cert+_xlpm.pace*$B$27),IF(_xlpm.c>=100,1,$B$20+(1-$B$20-$B$21)*_xlpm.c/100)*MIN(1,_xlpm.c/100)*(1-$B$22)) -> 0.24214402 | I60: =_xlfn.LET(_xlpm.d,I$56,_xlpm.cert,Simulator!$H11,_xlpm.regd,Simulator!$I11,_xlpm.compl,IF(_xlpm.regd="",EDATE($B$26,$B$25+_xlpm.d),IF(_xlpm.regd<$B$26,EDATE($B$26,$B$24+_xlpm.d),EDATE(_xlpm.regd,_xlpm.d))),_xlpm.n,MAX(1,(YEAR(_xlpm.compl)-YEAR($B$26))*12+MONTH(_xlpm.compl)-MONTH($B$26)),_xlpm.pace,MIN($B$23,(100-_xlpm.cert)/_xlpm.n),_xlpm.c,MIN(100,_xlpm.cert+_xlpm.pace*$B$27),IF(_xlpm.c>=100,1,$B$20+(1-$B$20-$B$21)*_xlpm.c/100)*MIN(1,_xlpm.c/100)*(1-$B$22)) -> 0.20880147 | J60: =_xlfn.LET(_xlpm.d,J$56,_xlpm.cert,Simulator!$H11,_xlpm.regd,Simulator!$I11,_xlpm.compl,IF(_xlpm.regd="",EDATE($B$26,$B$25+_xlpm.d),IF(_xlpm.regd<$B$26,EDATE($B$26,$B$24+_xlpm.d),EDATE(_xlpm.regd,_xlpm.d))),_xlpm.n,MAX(1,(YEAR(_xlpm.compl)-YEAR($B$26))*12+MONTH(_xlpm.compl)-MONTH($B$26)),_xlpm.pace,MIN($B$23,(100-_xlpm.cert)/_xlpm.n),_xlpm.c,MIN(100,_xlpm.cert+_xlpm.pace*$B$27),IF(_xlpm.c>=100,1,$B$20+(1-$B$20-$B$21)*_xlpm.c/100)*MIN(1,_xlpm.c/100)*(1-$B$22)) -> 0.1894888 | K60: =_xlfn.LET(_xlpm.d,K$56,_xlpm.cert,Simulator!$H11,_xlpm.regd,Simulator!$I11,_xlpm.compl,IF(_xlpm.regd="",EDATE($B$26,$B$25+_xlpm.d),IF(_xlpm.regd<$B$26,EDATE($B$26,$B$24+_xlpm.d),EDATE(_xlpm.regd,_xlpm.d))),_xlpm.n,MAX(1,(YEAR(_xlpm.compl)-YEAR($B$26))*12+MONTH(_xlpm.compl)-MONTH($B$26)),_xlpm.pace,MIN($B$23,(100-_xlpm.cert)/_xlpm.n),_xlpm.c,MIN(100,_xlpm.cert+_xlpm.pace*$B$27),IF(_xlpm.c>=100,1,$B$20+(1-$B$20-$B$21)*_xlpm.c/100)*MIN(1,_xlpm.c/100)*(1-$B$22)) -> 0.176928 | L60: =_xlfn.LET(_xlpm.d,L$56,_xlpm.cert,Simulator!$H11,_xlpm.regd,Simulator!$I11,_xlpm.compl,IF(_xlpm.regd="",EDATE($B$26,$B$25+_xlpm.d),IF(_xlpm.regd<$B$26,EDATE($B$26,$B$24+_xlpm.d),EDATE(_xlpm.regd,_xlpm.d))),_xlpm.n,MAX(1,(YEAR(_xlpm.compl)-YEAR($B$26))*12+MONTH(_xlpm.compl)-MONTH($B$26)),_xlpm.pace,MIN($B$23,(100-_xlpm.cert)/_xlpm.n),_xlpm.c,MIN(100,_xlpm.cert+_xlpm.pace*$B$27),IF(_xlpm.c>=100,1,$B$20+(1-$B$20-$B$21)*_xlpm.c/100)*MIN(1,_xlpm.c/100)*(1-$B$22)) -> 0.16811851
A61: =Simulator!A12 -> 3533 | B61: =Simulator!B12 -> Binghatti Ruby | C61: =Simulator!J12 -> 764.26949 | D61: =Simulator!K12*Simulator!G12/1000000*$B$18*(1+$B$19) -> 22.200817 | E61: =Simulator!$J12*IF(Simulator!$H12>=100,1,$B$20+(1-$B$20-$B$21)*Simulator!$H12/100)*MIN(1,Simulator!$H12/100)*(1-$B$22) -> 125.57865 | F61: =_xlfn.LET(_xlpm.d,F$56,_xlpm.cert,Simulator!$H12,_xlpm.regd,Simulator!$I12,_xlpm.compl,IF(_xlpm.regd="",EDATE($B$26,$B$25+_xlpm.d),IF(_xlpm.regd<$B$26,EDATE($B$26,$B$24+_xlpm.d),EDATE(_xlpm.regd,_xlpm.d))),_xlpm.n,MAX(1,(YEAR(_xlpm.compl)-YEAR($B$26))*12+MONTH(_xlpm.compl)-MONTH($B$26)),_xlpm.pace,MIN($B$23,(100-_xlpm.cert)/_xlpm.n),_xlpm.c,MIN(100,_xlpm.cert+_xlpm.pace*$B$27),IF(_xlpm.c>=100,1,$B$20+(1-$B$20-$B$21)*_xlpm.c/100)*MIN(1,_xlpm.c/100)*(1-$B$22)) -> 0.503272 | G61: =_xlfn.LET(_xlpm.d,G$56,_xlpm.cert,Simulator!$H12,_xlpm.regd,Simulator!$I12,_xlpm.compl,IF(_xlpm.regd="",EDATE($B$26,$B$25+_xlpm.d),IF(_xlpm.regd<$B$26,EDATE($B$26,$B$24+_xlpm.d),EDATE(_xlpm.regd,_xlpm.d))),_xlpm.n,MAX(1,(YEAR(_xlpm.compl)-YEAR($B$26))*12+MONTH(_xlpm.compl)-MONTH($B$26)),_xlpm.pace,MIN($B$23,(100-_xlpm.cert)/_xlpm.n),_xlpm.c,MIN(100,_xlpm.cert+_xlpm.pace*$B$27),IF(_xlpm.c>=100,1,$B$20+(1-$B$20-$B$21)*_xlpm.c/100)*MIN(1,_xlpm.c/100)*(1-$B$22)) -> 0.35068787 | H61: =_xlfn.LET(_xlpm.d,H$56,_xlpm.cert,Simulator!$H12,_xlpm.regd,Simulator!$I12,_xlpm.compl,IF(_xlpm.regd="",EDATE($B$26,$B$25+_xlpm.d),IF(_xlpm.regd<$B$26,EDATE($B$26,$B$24+_xlpm.d),EDATE(_xlpm.regd,_xlpm.d))),_xlpm.n,MAX(1,(YEAR(_xlpm.compl)-YEAR($B$26))*12+MONTH(_xlpm.compl)-MONTH($B$26)),_xlpm.pace,MIN($B$23,(100-_xlpm.cert)/_xlpm.n),_xlpm.c,MIN(100,_xlpm.cert+_xlpm.pace*$B$27),IF(_xlpm.c>=100,1,$B$20+(1-$B$20-$B$21)*_xlpm.c/100)*MIN(1,_xlpm.c/100)*(1-$B$22)) -> 0.28506739 | I61: =_xlfn.LET(_xlpm.d,I$56,_xlpm.cert,Simulator!$H12,_xlpm.regd,Simulator!$I12,_xlpm.compl,IF(_xlpm.regd="",EDATE($B$26,$B$25+_xlpm.d),IF(_xlpm.regd<$B$26,EDATE($B$26,$B$24+_xlpm.d),EDATE(_xlpm.regd,_xlpm.d))),_xlpm.n,MAX(1,(YEAR(_xlpm.compl)-YEAR($B$26))*12+MONTH(_xlpm.compl)-MONTH($B$26)),_xlpm.pace,MIN($B$23,(100-_xlpm.cert)/_xlpm.n),_xlpm.c,MIN(100,_xlpm.cert+_xlpm.pace*$B$27),IF(_xlpm.c>=100,1,$B$20+(1-$B$20-$B$21)*_xlpm.c/100)*MIN(1,_xlpm.c/100)*(1-$B$22)) -> 0.25337159 | J61: =_xlfn.LET(_xlpm.d,J$56,_xlpm.cert,Simulator!$H12,_xlpm.regd,Simulator!$I12,_xlpm.compl,IF(_xlpm.regd="",EDATE($B$26,$B$25+_xlpm.d),IF(_xlpm.regd<$B$26,EDATE($B$26,$B$24+_xlpm.d),EDATE(_xlpm.regd,_xlpm.d))),_xlpm.n,MAX(1,(YEAR(_xlpm.compl)-YEAR($B$26))*12+MONTH(_xlpm.compl)-MONTH($B$26)),_xlpm.pace,MIN($B$23,(100-_xlpm.cert)/_xlpm.n),_xlpm.c,MIN(100,_xlpm.cert+_xlpm.pace*$B$27),IF(_xlpm.c>=100,1,$B$20+(1-$B$20-$B$21)*_xlpm.c/100)*MIN(1,_xlpm.c/100)*(1-$B$22)) -> 0.2347812 | K61: =_xlfn.LET(_xlpm.d,K$56,_xlpm.cert,Simulator!$H12,_xlpm.regd,Simulator!$I12,_xlpm.compl,IF(_xlpm.regd="",EDATE($B$26,$B$25+_xlpm.d),IF(_xlpm.regd<$B$26,EDATE($B$26,$B$24+_xlpm.d),EDATE(_xlpm.regd,_xlpm.d))),_xlpm.n,MAX(1,(YEAR(_xlpm.compl)-YEAR($B$26))*12+MONTH(_xlpm.compl)-MONTH($B$26)),_xlpm.pace,MIN($B$23,(100-_xlpm.cert)/_xlpm.n),_xlpm.c,MIN(100,_xlpm.cert+_xlpm.pace*$B$27),IF(_xlpm.c>=100,1,$B$20+(1-$B$20-$B$21)*_xlpm.c/100)*MIN(1,_xlpm.c/100)*(1-$B$22)) -> 0.22258368 | L61: =_xlfn.LET(_xlpm.d,L$56,_xlpm.cert,Simulator!$H12,_xlpm.regd,Simulator!$I12,_xlpm.compl,IF(_xlpm.regd="",EDATE($B$26,$B$25+_xlpm.d),IF(_xlpm.regd<$B$26,EDATE($B$26,$B$24+_xlpm.d),EDATE(_xlpm.regd,_xlpm.d))),_xlpm.n,MAX(1,(YEAR(_xlpm.compl)-YEAR($B$26))*12+MONTH(_xlpm.compl)-MONTH($B$26)),_xlpm.pace,MIN($B$23,(100-_xlpm.cert)/_xlpm.n),_xlpm.c,MIN(100,_xlpm.cert+_xlpm.pace*$B$27),IF(_xlpm.c>=100,1,$B$20+(1-$B$20-$B$21)*_xlpm.c/100)*MIN(1,_xlpm.c/100)*(1-$B$22)) -> 0.21397325
A62: =Simulator!A13 -> 3192 | B62: =Simulator!B13 -> Binghatti Ghost | C62: =Simulator!J13 -> 862.56705 | D62: =Simulator!K13*Simulator!G13/1000000*$B$18*(1+$B$19) -> 67.861903 | E62: =Simulator!$J13*IF(Simulator!$H13>=100,1,$B$20+(1-$B$20-$B$21)*Simulator!$H13/100)*MIN(1,Simulator!$H13/100)*(1-$B$22) -> 563.00355 | F62: =_xlfn.LET(_xlpm.d,F$56,_xlpm.cert,Simulator!$H13,_xlpm.regd,Simulator!$I13,_xlpm.compl,IF(_xlpm.regd="",EDATE($B$26,$B$25+_xlpm.d),IF(_xlpm.regd<$B$26,EDATE($B$26,$B$24+_xlpm.d),EDATE(_xlpm.regd,_xlpm.d))),_xlpm.n,MAX(1,(YEAR(_xlpm.compl)-YEAR($B$26))*12+MONTH(_xlpm.compl)-MONTH($B$26)),_xlpm.pace,MIN($B$23,(100-_xlpm.cert)/_xlpm.n),_xlpm.c,MIN(100,_xlpm.cert+_xlpm.pace*$B$27),IF(_xlpm.c>=100,1,$B$20+(1-$B$20-$B$21)*_xlpm.c/100)*MIN(1,_xlpm.c/100)*(1-$B$22)) -> 0.66294325 | G62: =_xlfn.LET(_xlpm.d,G$56,_xlpm.cert,Simulator!$H13,_xlpm.regd,Simulator!$I13,_xlpm.compl,IF(_xlpm.regd="",EDATE($B$26,$B$25+_xlpm.d),IF(_xlpm.regd<$B$26,EDATE($B$26,$B$24+_xlpm.d),EDATE(_xlpm.regd,_xlpm.d))),_xlpm.n,MAX(1,(YEAR(_xlpm.compl)-YEAR($B$26))*12+MONTH(_xlpm.compl)-MONTH($B$26)),_xlpm.pace,MIN($B$23,(100-_xlpm.cert)/_xlpm.n),_xlpm.c,MIN(100,_xlpm.cert+_xlpm.pace*$B$27),IF(_xlpm.c>=100,1,$B$20+(1-$B$20-$B$21)*_xlpm.c/100)*MIN(1,_xlpm.c/100)*(1-$B$22)) -> 0.6582806 | H62: =_xlfn.LET(_xlpm.d,H$56,_xlpm.cert,Simulator!$H13,_xlpm.regd,Simulator!$I13,_xlpm.compl,IF(_xlpm.regd="",EDATE($B$26,$B$25+_xlpm.d),IF(_xlpm.regd<$B$26,EDATE($B$26,$B$24+_xlpm.d),EDATE(_xlpm.regd,_xlpm.d))),_xlpm.n,MAX(1,(YEAR(_xlpm.compl)-YEAR($B$26))*12+MONTH(_xlpm.compl)-MONTH($B$26)),_xlpm.pace,MIN($B$23,(100-_xlpm.cert)/_xlpm.n),_xlpm.c,MIN(100,_xlpm.cert+_xlpm.pace*$B$27),IF(_xlpm.c>=100,1,$B$20+(1-$B$20-$B$21)*_xlpm.c/100)*MIN(1,_xlpm.c/100)*(1-$B$22)) -> 0.65653632 | I62: =_xlfn.LET(_xlpm.d,I$56,_xlpm.cert,Simulator!$H13,_xlpm.regd,Simulator!$I13,_xlpm.compl,IF(_xlpm.regd="",EDATE($B$26,$B$25+_xlpm.d),IF(_xlpm.regd<$B$26,EDATE($B$26,$B$24+_xlpm.d),EDATE(_xlpm.regd,_xlpm.d))),_xlpm.n,MAX(1,(YEAR(_xlpm.compl)-YEAR($B$26))*12+MONTH(_xlpm.compl)-MONTH($B$26)),_xlpm.pace,MIN($B$23,(100-_xlpm.cert)/_xlpm.n),_xlpm.c,MIN(100,_xlpm.cert+_xlpm.pace*$B$27),IF(_xlpm.c>=100,1,$B$20+(1-$B$20-$B$21)*_xlpm.c/100)*MIN(1,_xlpm.c/100)*(1-$B$22)) -> 0.65562356 | J62: =_xlfn.LET(_xlpm.d,J$56,_xlpm.cert,Simulator!$H13,_xlpm.regd,Simulator!$I13,_xlpm.compl,IF(_xlpm.regd="",EDATE($B$26,$B$25+_xlpm.d),IF(_xlpm.regd<$B$26,EDATE($B$26,$B$24+_xlpm.d),EDATE(_xlpm.regd,_xlpm.d))),_xlpm.n,MAX(1,(YEAR(_xlpm.compl)-YEAR($B$26))*12+MONTH(_xlpm.compl)-MONTH($B$26)),_xlpm.pace,MIN($B$23,(100-_xlpm.cert)/_xlpm.n),_xlpm.c,MIN(100,_xlpm.cert+_xlpm.pace*$B$27),IF(_xlpm.c>=100,1,$B$20+(1-$B$20-$B$21)*_xlpm.c/100)*MIN(1,_xlpm.c/100)*(1-$B$22)) -> 0.65506218 | K62: =_xlfn.LET(_xlpm.d,K$56,_xlpm.cert,Simulator!$H13,_xlpm.regd,Simulator!$I13,_xlpm.compl,IF(_xlpm.regd="",EDATE($B$26,$B$25+_xlpm.d),IF(_xlpm.regd<$B$26,EDATE($B$26,$B$24+_xlpm.d),EDATE(_xlpm.regd,_xlpm.d))),_xlpm.n,MAX(1,(YEAR(_xlpm.compl)-YEAR($B$26))*12+MONTH(_xlpm.compl)-MONTH($B$26)),_xlpm.pace,MIN($B$23,(100-_xlpm.cert)/_xlpm.n),_xlpm.c,MIN(100,_xlpm.cert+_xlpm.pace*$B$27),IF(_xlpm.c>=100,1,$B$20+(1-$B$20-$B$21)*_xlpm.c/100)*MIN(1,_xlpm.c/100)*(1-$B$22)) -> 0.65468203 | L62: =_xlfn.LET(_xlpm.d,L$56,_xlpm.cert,Simulator!$H13,_xlpm.regd,Simulator!$I13,_xlpm.compl,IF(_xlpm.regd="",EDATE($B$26,$B$25+_xlpm.d),IF(_xlpm.regd<$B$26,EDATE($B$26,$B$24+_xlpm.d),EDATE(_xlpm.regd,_xlpm.d))),_xlpm.n,MAX(1,(YEAR(_xlpm.compl)-YEAR($B$26))*12+MONTH(_xlpm.compl)-MONTH($B$26)),_xlpm.pace,MIN($B$23,(100-_xlpm.cert)/_xlpm.n),_xlpm.c,MIN(100,_xlpm.cert+_xlpm.pace*$B$27),IF(_xlpm.c>=100,1,$B$20+(1-$B$20-$B$21)*_xlpm.c/100)*MIN(1,_xlpm.c/100)*(1-$B$22)) -> 0.65440754
A63: =Simulator!A14 -> 3314 | B63: =Simulator!B14 -> Binghatti Grove | C63: =Simulator!J14 -> 611.32207 | D63: =Simulator!K14*Simulator!G14/1000000*$B$18*(1+$B$19) -> 45.976869 | E63: =Simulator!$J14*IF(Simulator!$H14>=100,1,$B$20+(1-$B$20-$B$21)*Simulator!$H14/100)*MIN(1,Simulator!$H14/100)*(1-$B$22) -> 294.65235 | F63: =_xlfn.LET(_xlpm.d,F$56,_xlpm.cert,Simulator!$H14,_xlpm.regd,Simulator!$I14,_xlpm.compl,IF(_xlpm.regd="",EDATE($B$26,$B$25+_xlpm.d),IF(_xlpm.regd<$B$26,EDATE($B$26,$B$24+_xlpm.d),EDATE(_xlpm.regd,_xlpm.d))),_xlpm.n,MAX(1,(YEAR(_xlpm.compl)-YEAR($B$26))*12+MONTH(_xlpm.compl)-MONTH($B$26)),_xlpm.pace,MIN($B$23,(100-_xlpm.cert)/_xlpm.n),_xlpm.c,MIN(100,_xlpm.cert+_xlpm.pace*$B$27),IF(_xlpm.c>=100,1,$B$20+(1-$B$20-$B$21)*_xlpm.c/100)*MIN(1,_xlpm.c/100)*(1-$B$22)) -> 0.632472 | G63: =_xlfn.LET(_xlpm.d,G$56,_xlpm.cert,Simulator!$H14,_xlpm.regd,Simulator!$I14,_xlpm.compl,IF(_xlpm.regd="",EDATE($B$26,$B$25+_xlpm.d),IF(_xlpm.regd<$B$26,EDATE($B$26,$B$24+_xlpm.d),EDATE(_xlpm.regd,_xlpm.d))),_xlpm.n,MAX(1,(YEAR(_xlpm.compl)-YEAR($B$26))*12+MONTH(_xlpm.compl)-MONTH($B$26)),_xlpm.pace,MIN($B$23,(100-_xlpm.cert)/_xlpm.n),_xlpm.c,MIN(100,_xlpm.cert+_xlpm.pace*$B$27),IF(_xlpm.c>=100,1,$B$20+(1-$B$20-$B$21)*_xlpm.c/100)*MIN(1,_xlpm.c/100)*(1-$B$22)) -> 0.5615596 | H63: =_xlfn.LET(_xlpm.d,H$56,_xlpm.cert,Simulator!$H14,_xlpm.regd,Simulator!$I14,_xlpm.compl,IF(_xlpm.regd="",EDATE($B$26,$B$25+_xlpm.d),IF(_xlpm.regd<$B$26,EDATE($B$26,$B$24+_xlpm.d),EDATE(_xlpm.regd,_xlpm.d))),_xlpm.n,MAX(1,(YEAR(_xlpm.compl)-YEAR($B$26))*12+MONTH(_xlpm.compl)-MONTH($B$26)),_xlpm.pace,MIN($B$23,(100-_xlpm.cert)/_xlpm.n),_xlpm.c,MIN(100,_xlpm.cert+_xlpm.pace*$B$27),IF(_xlpm.c>=100,1,$B$20+(1-$B$20-$B$21)*_xlpm.c/100)*MIN(1,_xlpm.c/100)*(1-$B$22)) -> 0.536047 | I63: =_xlfn.LET(_xlpm.d,I$56,_xlpm.cert,Simulator!$H14,_xlpm.regd,Simulator!$I14,_xlpm.compl,IF(_xlpm.regd="",EDATE($B$26,$B$25+_xlpm.d),IF(_xlpm.regd<$B$26,EDATE($B$26,$B$24+_xlpm.d),EDATE(_xlpm.regd,_xlpm.d))),_xlpm.n,MAX(1,(YEAR(_xlpm.compl)-YEAR($B$26))*12+MONTH(_xlpm.compl)-MONTH($B$26)),_xlpm.pace,MIN($B$23,(100-_xlpm.cert)/_xlpm.n),_xlpm.c,MIN(100,_xlpm.cert+_xlpm.pace*$B$27),IF(_xlpm.c>=100,1,$B$20+(1-$B$20-$B$21)*_xlpm.c/100)*MIN(1,_xlpm.c/100)*(1-$B$22)) -> 0.52291826 | J63: =_xlfn.LET(_xlpm.d,J$56,_xlpm.cert,Simulator!$H14,_xlpm.regd,Simulator!$I14,_xlpm.compl,IF(_xlpm.regd="",EDATE($B$26,$B$25+_xlpm.d),IF(_xlpm.regd<$B$26,EDATE($B$26,$B$24+_xlpm.d),EDATE(_xlpm.regd,_xlpm.d))),_xlpm.n,MAX(1,(YEAR(_xlpm.compl)-YEAR($B$26))*12+MONTH(_xlpm.compl)-MONTH($B$26)),_xlpm.pace,MIN($B$23,(100-_xlpm.cert)/_xlpm.n),_xlpm.c,MIN(100,_xlpm.cert+_xlpm.pace*$B$27),IF(_xlpm.c>=100,1,$B$20+(1-$B$20-$B$21)*_xlpm.c/100)*MIN(1,_xlpm.c/100)*(1-$B$22)) -> 0.51491934 | K63: =_xlfn.LET(_xlpm.d,K$56,_xlpm.cert,Simulator!$H14,_xlpm.regd,Simulator!$I14,_xlpm.compl,IF(_xlpm.regd="",EDATE($B$26,$B$25+_xlpm.d),IF(_xlpm.regd<$B$26,EDATE($B$26,$B$24+_xlpm.d),EDATE(_xlpm.regd,_xlpm.d))),_xlpm.n,MAX(1,(YEAR(_xlpm.compl)-YEAR($B$26))*12+MONTH(_xlpm.compl)-MONTH($B$26)),_xlpm.pace,MIN($B$23,(100-_xlpm.cert)/_xlpm.n),_xlpm.c,MIN(100,_xlpm.cert+_xlpm.pace*$B$27),IF(_xlpm.c>=100,1,$B$20+(1-$B$20-$B$21)*_xlpm.c/100)*MIN(1,_xlpm.c/100)*(1-$B$22)) -> 0.50953548 | L63: =_xlfn.LET(_xlpm.d,L$56,_xlpm.cert,Simulator!$H14,_xlpm.regd,Simulator!$I14,_xlpm.compl,IF(_xlpm.regd="",EDATE($B$26,$B$25+_xlpm.d),IF(_xlpm.regd<$B$26,EDATE($B$26,$B$24+_xlpm.d),EDATE(_xlpm.regd,_xlpm.d))),_xlpm.n,MAX(1,(YEAR(_xlpm.compl)-YEAR($B$26))*12+MONTH(_xlpm.compl)-MONTH($B$26)),_xlpm.pace,MIN($B$23,(100-_xlpm.cert)/_xlpm.n),_xlpm.c,MIN(100,_xlpm.cert+_xlpm.pace*$B$27),IF(_xlpm.c>=100,1,$B$20+(1-$B$20-$B$21)*_xlpm.c/100)*MIN(1,_xlpm.c/100)*(1-$B$22)) -> 0.50566459
A64: =Simulator!A15 -> 3442 | B64: =Simulator!B15 -> Binghatti Haven | C64: =Simulator!J15 -> 636.31111 | D64: =Simulator!K15*Simulator!G15/1000000*$B$18*(1+$B$19) -> 24.317622 | E64: =Simulator!$J15*IF(Simulator!$H15>=100,1,$B$20+(1-$B$20-$B$21)*Simulator!$H15/100)*MIN(1,Simulator!$H15/100)*(1-$B$22) -> 255.43564 | F64: =_xlfn.LET(_xlpm.d,F$56,_xlpm.cert,Simulator!$H15,_xlpm.regd,Simulator!$I15,_xlpm.compl,IF(_xlpm.regd="",EDATE($B$26,$B$25+_xlpm.d),IF(_xlpm.regd<$B$26,EDATE($B$26,$B$24+_xlpm.d),EDATE(_xlpm.regd,_xlpm.d))),_xlpm.n,MAX(1,(YEAR(_xlpm.compl)-YEAR($B$26))*12+MONTH(_xlpm.compl)-MONTH($B$26)),_xlpm.pace,MIN($B$23,(100-_xlpm.cert)/_xlpm.n),_xlpm.c,MIN(100,_xlpm.cert+_xlpm.pace*$B$27),IF(_xlpm.c>=100,1,$B$20+(1-$B$20-$B$21)*_xlpm.c/100)*MIN(1,_xlpm.c/100)*(1-$B$22)) -> 0.616512 | G64: =_xlfn.LET(_xlpm.d,G$56,_xlpm.cert,Simulator!$H15,_xlpm.regd,Simulator!$I15,_xlpm.compl,IF(_xlpm.regd="",EDATE($B$26,$B$25+_xlpm.d),IF(_xlpm.regd<$B$26,EDATE($B$26,$B$24+_xlpm.d),EDATE(_xlpm.regd,_xlpm.d))),_xlpm.n,MAX(1,(YEAR(_xlpm.compl)-YEAR($B$26))*12+MONTH(_xlpm.compl)-MONTH($B$26)),_xlpm.pace,MIN($B$23,(100-_xlpm.cert)/_xlpm.n),_xlpm.c,MIN(100,_xlpm.cert+_xlpm.pace*$B$27),IF(_xlpm.c>=100,1,$B$20+(1-$B$20-$B$21)*_xlpm.c/100)*MIN(1,_xlpm.c/100)*(1-$B$22)) -> 0.51309547 | H64: =_xlfn.LET(_xlpm.d,H$56,_xlpm.cert,Simulator!$H15,_xlpm.regd,Simulator!$I15,_xlpm.compl,IF(_xlpm.regd="",EDATE($B$26,$B$25+_xlpm.d),IF(_xlpm.regd<$B$26,EDATE($B$26,$B$24+_xlpm.d),EDATE(_xlpm.regd,_xlpm.d))),_xlpm.n,MAX(1,(YEAR(_xlpm.compl)-YEAR($B$26))*12+MONTH(_xlpm.compl)-MONTH($B$26)),_xlpm.pace,MIN($B$23,(100-_xlpm.cert)/_xlpm.n),_xlpm.c,MIN(100,_xlpm.cert+_xlpm.pace*$B$27),IF(_xlpm.c>=100,1,$B$20+(1-$B$20-$B$21)*_xlpm.c/100)*MIN(1,_xlpm.c/100)*(1-$B$22)) -> 0.47674325 | I64: =_xlfn.LET(_xlpm.d,I$56,_xlpm.cert,Simulator!$H15,_xlpm.regd,Simulator!$I15,_xlpm.compl,IF(_xlpm.regd="",EDATE($B$26,$B$25+_xlpm.d),IF(_xlpm.regd<$B$26,EDATE($B$26,$B$24+_xlpm.d),EDATE(_xlpm.regd,_xlpm.d))),_xlpm.n,MAX(1,(YEAR(_xlpm.compl)-YEAR($B$26))*12+MONTH(_xlpm.compl)-MONTH($B$26)),_xlpm.pace,MIN($B$23,(100-_xlpm.cert)/_xlpm.n),_xlpm.c,MIN(100,_xlpm.cert+_xlpm.pace*$B$27),IF(_xlpm.c>=100,1,$B$20+(1-$B$20-$B$21)*_xlpm.c/100)*MIN(1,_xlpm.c/100)*(1-$B$22)) -> 0.45823037 | J64: =_xlfn.LET(_xlpm.d,J$56,_xlpm.cert,Simulator!$H15,_xlpm.regd,Simulator!$I15,_xlpm.compl,IF(_xlpm.regd="",EDATE($B$26,$B$25+_xlpm.d),IF(_xlpm.regd<$B$26,EDATE($B$26,$B$24+_xlpm.d),EDATE(_xlpm.regd,_xlpm.d))),_xlpm.n,MAX(1,(YEAR(_xlpm.compl)-YEAR($B$26))*12+MONTH(_xlpm.compl)-MONTH($B$26)),_xlpm.pace,MIN($B$23,(100-_xlpm.cert)/_xlpm.n),_xlpm.c,MIN(100,_xlpm.cert+_xlpm.pace*$B$27),IF(_xlpm.c>=100,1,$B$20+(1-$B$20-$B$21)*_xlpm.c/100)*MIN(1,_xlpm.c/100)*(1-$B$22)) -> 0.44701851 | K64: =_xlfn.LET(_xlpm.d,K$56,_xlpm.cert,Simulator!$H15,_xlpm.regd,Simulator!$I15,_xlpm.compl,IF(_xlpm.regd="",EDATE($B$26,$B$25+_xlpm.d),IF(_xlpm.regd<$B$26,EDATE($B$26,$B$24+_xlpm.d),EDATE(_xlpm.regd,_xlpm.d))),_xlpm.n,MAX(1,(YEAR(_xlpm.compl)-YEAR($B$26))*12+MONTH(_xlpm.compl)-MONTH($B$26)),_xlpm.pace,MIN($B$23,(100-_xlpm.cert)/_xlpm.n),_xlpm.c,MIN(100,_xlpm.cert+_xlpm.pace*$B$27),IF(_xlpm.c>=100,1,$B$20+(1-$B$20-$B$21)*_xlpm.c/100)*MIN(1,_xlpm.c/100)*(1-$B$22)) -> 0.43950159 | L64: =_xlfn.LET(_xlpm.d,L$56,_xlpm.cert,Simulator!$H15,_xlpm.regd,Simulator!$I15,_xlpm.compl,IF(_xlpm.regd="",EDATE($B$26,$B$25+_xlpm.d),IF(_xlpm.regd<$B$26,EDATE($B$26,$B$24+_xlpm.d),EDATE(_xlpm.regd,_xlpm.d))),_xlpm.n,MAX(1,(YEAR(_xlpm.compl)-YEAR($B$26))*12+MONTH(_xlpm.compl)-MONTH($B$26)),_xlpm.pace,MIN($B$23,(100-_xlpm.cert)/_xlpm.n),_xlpm.c,MIN(100,_xlpm.cert+_xlpm.pace*$B$27),IF(_xlpm.c>=100,1,$B$20+(1-$B$20-$B$21)*_xlpm.c/100)*MIN(1,_xlpm.c/100)*(1-$B$22)) -> 0.434112
A65: =Simulator!A16 -> 3195 | B65: =Simulator!B16 -> Binghatti Starlight | C65: =Simulator!J16 -> 528.92882 | D65: =Simulator!K16*Simulator!G16/1000000*$B$18*(1+$B$19) -> 28.420056 | E65: =Simulator!$J16*IF(Simulator!$H16>=100,1,$B$20+(1-$B$20-$B$21)*Simulator!$H16/100)*MIN(1,Simulator!$H16/100)*(1-$B$22) -> 151.31754 | F65: =_xlfn.LET(_xlpm.d,F$56,_xlpm.cert,Simulator!$H16,_xlpm.regd,Simulator!$I16,_xlpm.compl,IF(_xlpm.regd="",EDATE($B$26,$B$25+_xlpm.d),IF(_xlpm.regd<$B$26,EDATE($B$26,$B$24+_xlpm.d),EDATE(_xlpm.regd,_xlpm.d))),_xlpm.n,MAX(1,(YEAR(_xlpm.compl)-YEAR($B$26))*12+MONTH(_xlpm.compl)-MONTH($B$26)),_xlpm.pace,MIN($B$23,(100-_xlpm.cert)/_xlpm.n),_xlpm.c,MIN(100,_xlpm.cert+_xlpm.pace*$B$27),IF(_xlpm.c>=100,1,$B$20+(1-$B$20-$B$21)*_xlpm.c/100)*MIN(1,_xlpm.c/100)*(1-$B$22)) -> 0.59100925 | G65: =_xlfn.LET(_xlpm.d,G$56,_xlpm.cert,Simulator!$H16,_xlpm.regd,Simulator!$I16,_xlpm.compl,IF(_xlpm.regd="",EDATE($B$26,$B$25+_xlpm.d),IF(_xlpm.regd<$B$26,EDATE($B$26,$B$24+_xlpm.d),EDATE(_xlpm.regd,_xlpm.d))),_xlpm.n,MAX(1,(YEAR(_xlpm.compl)-YEAR($B$26))*12+MONTH(_xlpm.compl)-MONTH($B$26)),_xlpm.pace,MIN($B$23,(100-_xlpm.cert)/_xlpm.n),_xlpm.c,MIN(100,_xlpm.cert+_xlpm.pace*$B$27),IF(_xlpm.c>=100,1,$B$20+(1-$B$20-$B$21)*_xlpm.c/100)*MIN(1,_xlpm.c/100)*(1-$B$22)) -> 0.43897098 | H65: =_xlfn.LET(_xlpm.d,H$56,_xlpm.cert,Simulator!$H16,_xlpm.regd,Simulator!$I16,_xlpm.compl,IF(_xlpm.regd="",EDATE($B$26,$B$25+_xlpm.d),IF(_xlpm.regd<$B$26,EDATE($B$26,$B$24+_xlpm.d),EDATE(_xlpm.regd,_xlpm.d))),_xlpm.n,MAX(1,(YEAR(_xlpm.compl)-YEAR($B$26))*12+MONTH(_xlpm.compl)-MONTH($B$26)),_xlpm.pace,MIN($B$23,(100-_xlpm.cert)/_xlpm.n),_xlpm.c,MIN(100,_xlpm.cert+_xlpm.pace*$B$27),IF(_xlpm.c>=100,1,$B$20+(1-$B$20-$B$21)*_xlpm.c/100)*MIN(1,_xlpm.c/100)*(1-$B$22)) -> 0.38772966 | I65: =_xlfn.LET(_xlpm.d,I$56,_xlpm.cert,Simulator!$H16,_xlpm.regd,Simulator!$I16,_xlpm.compl,IF(_xlpm.regd="",EDATE($B$26,$B$25+_xlpm.d),IF(_xlpm.regd<$B$26,EDATE($B$26,$B$24+_xlpm.d),EDATE(_xlpm.regd,_xlpm.d))),_xlpm.n,MAX(1,(YEAR(_xlpm.compl)-YEAR($B$26))*12+MONTH(_xlpm.compl)-MONTH($B$26)),_xlpm.pace,MIN($B$23,(100-_xlpm.cert)/_xlpm.n),_xlpm.c,MIN(100,_xlpm.cert+_xlpm.pace*$B$27),IF(_xlpm.c>=100,1,$B$20+(1-$B$20-$B$21)*_xlpm.c/100)*MIN(1,_xlpm.c/100)*(1-$B$22)) -> 0.36214569 | J65: =_xlfn.LET(_xlpm.d,J$56,_xlpm.cert,Simulator!$H16,_xlpm.regd,Simulator!$I16,_xlpm.compl,IF(_xlpm.regd="",EDATE($B$26,$B$25+_xlpm.d),IF(_xlpm.regd<$B$26,EDATE($B$26,$B$24+_xlpm.d),EDATE(_xlpm.regd,_xlpm.d))),_xlpm.n,MAX(1,(YEAR(_xlpm.compl)-YEAR($B$26))*12+MONTH(_xlpm.compl)-MONTH($B$26)),_xlpm.pace,MIN($B$23,(100-_xlpm.cert)/_xlpm.n),_xlpm.c,MIN(100,_xlpm.cert+_xlpm.pace*$B$27),IF(_xlpm.c>=100,1,$B$20+(1-$B$20-$B$21)*_xlpm.c/100)*MIN(1,_xlpm.c/100)*(1-$B$22)) -> 0.34683114 | K65: =_xlfn.LET(_xlpm.d,K$56,_xlpm.cert,Simulator!$H16,_xlpm.regd,Simulator!$I16,_xlpm.compl,IF(_xlpm.regd="",EDATE($B$26,$B$25+_xlpm.d),IF(_xlpm.regd<$B$26,EDATE($B$26,$B$24+_xlpm.d),EDATE(_xlpm.regd,_xlpm.d))),_xlpm.n,MAX(1,(YEAR(_xlpm.compl)-YEAR($B$26))*12+MONTH(_xlpm.compl)-MONTH($B$26)),_xlpm.pace,MIN($B$23,(100-_xlpm.cert)/_xlpm.n),_xlpm.c,MIN(100,_xlpm.cert+_xlpm.pace*$B$27),IF(_xlpm.c>=100,1,$B$20+(1-$B$20-$B$21)*_xlpm.c/100)*MIN(1,_xlpm.c/100)*(1-$B$22)) -> 0.33664267 | L65: =_xlfn.LET(_xlpm.d,L$56,_xlpm.cert,Simulator!$H16,_xlpm.regd,Simulator!$I16,_xlpm.compl,IF(_xlpm.regd="",EDATE($B$26,$B$25+_xlpm.d),IF(_xlpm.regd<$B$26,EDATE($B$26,$B$24+_xlpm.d),EDATE(_xlpm.regd,_xlpm.d))),_xlpm.n,MAX(1,(YEAR(_xlpm.compl)-YEAR($B$26))*12+MONTH(_xlpm.compl)-MONTH($B$26)),_xlpm.pace,MIN($B$23,(100-_xlpm.cert)/_xlpm.n),_xlpm.c,MIN(100,_xlpm.cert+_xlpm.pace*$B$27),IF(_xlpm.c>=100,1,$B$20+(1-$B$20-$B$21)*_xlpm.c/100)*MIN(1,_xlpm.c/100)*(1-$B$22)) -> 0.32937771
A66: =Simulator!A17 -> 3321 | B66: =Simulator!B17 -> Binghatti Hillviews | C66: =Simulator!J17 -> 1850.1573 | D66: =Simulator!K17*Simulator!G17/1000000*$B$18*(1+$B$19) -> 7.807569 | E66: =Simulator!$J17*IF(Simulator!$H17>=100,1,$B$20+(1-$B$20-$B$21)*Simulator!$H17/100)*MIN(1,Simulator!$H17/100)*(1-$B$22) -> 172.84724 | F66: =_xlfn.LET(_xlpm.d,F$56,_xlpm.cert,Simulator!$H17,_xlpm.regd,Simulator!$I17,_xlpm.compl,IF(_xlpm.regd="",EDATE($B$26,$B$25+_xlpm.d),IF(_xlpm.regd<$B$26,EDATE($B$26,$B$24+_xlpm.d),EDATE(_xlpm.regd,_xlpm.d))),_xlpm.n,MAX(1,(YEAR(_xlpm.compl)-YEAR($B$26))*12+MONTH(_xlpm.compl)-MONTH($B$26)),_xlpm.pace,MIN($B$23,(100-_xlpm.cert)/_xlpm.n),_xlpm.c,MIN(100,_xlpm.cert+_xlpm.pace*$B$27),IF(_xlpm.c>=100,1,$B$20+(1-$B$20-$B$21)*_xlpm.c/100)*MIN(1,_xlpm.c/100)*(1-$B$22)) -> 0.373103 | G66: =_xlfn.LET(_xlpm.d,G$56,_xlpm.cert,Simulator!$H17,_xlpm.regd,Simulator!$I17,_xlpm.compl,IF(_xlpm.regd="",EDATE($B$26,$B$25+_xlpm.d),IF(_xlpm.regd<$B$26,EDATE($B$26,$B$24+_xlpm.d),EDATE(_xlpm.regd,_xlpm.d))),_xlpm.n,MAX(1,(YEAR(_xlpm.compl)-YEAR($B$26))*12+MONTH(_xlpm.compl)-MONTH($B$26)),_xlpm.pace,MIN($B$23,(100-_xlpm.cert)/_xlpm.n),_xlpm.c,MIN(100,_xlpm.cert+_xlpm.pace*$B$27),IF(_xlpm.c>=100,1,$B$20+(1-$B$20-$B$21)*_xlpm.c/100)*MIN(1,_xlpm.c/100)*(1-$B$22)) -> 0.28979114 | H66: =_xlfn.LET(_xlpm.d,H$56,_xlpm.cert,Simulator!$H17,_xlpm.regd,Simulator!$I17,_xlpm.compl,IF(_xlpm.regd="",EDATE($B$26,$B$25+_xlpm.d),IF(_xlpm.regd<$B$26,EDATE($B$26,$B$24+_xlpm.d),EDATE(_xlpm.regd,_xlpm.d))),_xlpm.n,MAX(1,(YEAR(_xlpm.compl)-YEAR($B$26))*12+MONTH(_xlpm.compl)-MONTH($B$26)),_xlpm.pace,MIN($B$23,(100-_xlpm.cert)/_xlpm.n),_xlpm.c,MIN(100,_xlpm.cert+_xlpm.pace*$B$27),IF(_xlpm.c>=100,1,$B$20+(1-$B$20-$B$21)*_xlpm.c/100)*MIN(1,_xlpm.c/100)*(1-$B$22)) -> 0.2170681 | I66: =_xlfn.LET(_xlpm.d,I$56,_xlpm.cert,Simulator!$H17,_xlpm.regd,Simulator!$I17,_xlpm.compl,IF(_xlpm.regd="",EDATE($B$26,$B$25+_xlpm.d),IF(_xlpm.regd<$B$26,EDATE($B$26,$B$24+_xlpm.d),EDATE(_xlpm.regd,_xlpm.d))),_xlpm.n,MAX(1,(YEAR(_xlpm.compl)-YEAR($B$26))*12+MONTH(_xlpm.compl)-MONTH($B$26)),_xlpm.pace,MIN($B$23,(100-_xlpm.cert)/_xlpm.n),_xlpm.c,MIN(100,_xlpm.cert+_xlpm.pace*$B$27),IF(_xlpm.c>=100,1,$B$20+(1-$B$20-$B$21)*_xlpm.c/100)*MIN(1,_xlpm.c/100)*(1-$B$22)) -> 0.18309589 | J66: =_xlfn.LET(_xlpm.d,J$56,_xlpm.cert,Simulator!$H17,_xlpm.regd,Simulator!$I17,_xlpm.compl,IF(_xlpm.regd="",EDATE($B$26,$B$25+_xlpm.d),IF(_xlpm.regd<$B$26,EDATE($B$26,$B$24+_xlpm.d),EDATE(_xlpm.regd,_xlpm.d))),_xlpm.n,MAX(1,(YEAR(_xlpm.compl)-YEAR($B$26))*12+MONTH(_xlpm.compl)-MONTH($B$26)),_xlpm.pace,MIN($B$23,(100-_xlpm.cert)/_xlpm.n),_xlpm.c,MIN(100,_xlpm.cert+_xlpm.pace*$B$27),IF(_xlpm.c>=100,1,$B$20+(1-$B$20-$B$21)*_xlpm.c/100)*MIN(1,_xlpm.c/100)*(1-$B$22)) -> 0.16359807 | K66: =_xlfn.LET(_xlpm.d,K$56,_xlpm.cert,Simulator!$H17,_xlpm.regd,Simulator!$I17,_xlpm.compl,IF(_xlpm.regd="",EDATE($B$26,$B$25+_xlpm.d),IF(_xlpm.regd<$B$26,EDATE($B$26,$B$24+_xlpm.d),EDATE(_xlpm.regd,_xlpm.d))),_xlpm.n,MAX(1,(YEAR(_xlpm.compl)-YEAR($B$26))*12+MONTH(_xlpm.compl)-MONTH($B$26)),_xlpm.pace,MIN($B$23,(100-_xlpm.cert)/_xlpm.n),_xlpm.c,MIN(100,_xlpm.cert+_xlpm.pace*$B$27),IF(_xlpm.c>=100,1,$B$20+(1-$B$20-$B$21)*_xlpm.c/100)*MIN(1,_xlpm.c/100)*(1-$B$22)) -> 0.15099943 | L66: =_xlfn.LET(_xlpm.d,L$56,_xlpm.cert,Simulator!$H17,_xlpm.regd,Simulator!$I17,_xlpm.compl,IF(_xlpm.regd="",EDATE($B$26,$B$25+_xlpm.d),IF(_xlpm.regd<$B$26,EDATE($B$26,$B$24+_xlpm.d),EDATE(_xlpm.regd,_xlpm.d))),_xlpm.n,MAX(1,(YEAR(_xlpm.compl)-YEAR($B$26))*12+MONTH(_xlpm.compl)-MONTH($B$26)),_xlpm.pace,MIN($B$23,(100-_xlpm.cert)/_xlpm.n),_xlpm.c,MIN(100,_xlpm.cert+_xlpm.pace*$B$27),IF(_xlpm.c>=100,1,$B$20+(1-$B$20-$B$21)*_xlpm.c/100)*MIN(1,_xlpm.c/100)*(1-$B$22)) -> 0.1422066
A67: =Simulator!A18 -> 3397 | B67: =Simulator!B18 -> Binghatti Twilight | C67: =Simulator!J18 -> 422.72716 | D67: =Simulator!K18*Simulator!G18/1000000*$B$18*(1+$B$19) -> 29.659083 | E67: =Simulator!$J18*IF(Simulator!$H18>=100,1,$B$20+(1-$B$20-$B$21)*Simulator!$H18/100)*MIN(1,Simulator!$H18/100)*(1-$B$22) -> 37.524645 | F67: =_xlfn.LET(_xlpm.d,F$56,_xlpm.cert,Simulator!$H18,_xlpm.regd,Simulator!$I18,_xlpm.compl,IF(_xlpm.regd="",EDATE($B$26,$B$25+_xlpm.d),IF(_xlpm.regd<$B$26,EDATE($B$26,$B$24+_xlpm.d),EDATE(_xlpm.regd,_xlpm.d))),_xlpm.n,MAX(1,(YEAR(_xlpm.compl)-YEAR($B$26))*12+MONTH(_xlpm.compl)-MONTH($B$26)),_xlpm.pace,MIN($B$23,(100-_xlpm.cert)/_xlpm.n),_xlpm.c,MIN(100,_xlpm.cert+_xlpm.pace*$B$27),IF(_xlpm.c>=100,1,$B$20+(1-$B$20-$B$21)*_xlpm.c/100)*MIN(1,_xlpm.c/100)*(1-$B$22)) -> 0.363888 | G67: =_xlfn.LET(_xlpm.d,G$56,_xlpm.cert,Simulator!$H18,_xlpm.regd,Simulator!$I18,_xlpm.compl,IF(_xlpm.regd="",EDATE($B$26,$B$25+_xlpm.d),IF(_xlpm.regd<$B$26,EDATE($B$26,$B$24+_xlpm.d),EDATE(_xlpm.regd,_xlpm.d))),_xlpm.n,MAX(1,(YEAR(_xlpm.compl)-YEAR($B$26))*12+MONTH(_xlpm.compl)-MONTH($B$26)),_xlpm.pace,MIN($B$23,(100-_xlpm.cert)/_xlpm.n),_xlpm.c,MIN(100,_xlpm.cert+_xlpm.pace*$B$27),IF(_xlpm.c>=100,1,$B$20+(1-$B$20-$B$21)*_xlpm.c/100)*MIN(1,_xlpm.c/100)*(1-$B$22)) -> 0.2853442 | H67: =_xlfn.LET(_xlpm.d,H$56,_xlpm.cert,Simulator!$H18,_xlpm.regd,Simulator!$I18,_xlpm.compl,IF(_xlpm.regd="",EDATE($B$26,$B$25+_xlpm.d),IF(_xlpm.regd<$B$26,EDATE($B$26,$B$24+_xlpm.d),EDATE(_xlpm.regd,_xlpm.d))),_xlpm.n,MAX(1,(YEAR(_xlpm.compl)-YEAR($B$26))*12+MONTH(_xlpm.compl)-MONTH($B$26)),_xlpm.pace,MIN($B$23,(100-_xlpm.cert)/_xlpm.n),_xlpm.c,MIN(100,_xlpm.cert+_xlpm.pace*$B$27),IF(_xlpm.c>=100,1,$B$20+(1-$B$20-$B$21)*_xlpm.c/100)*MIN(1,_xlpm.c/100)*(1-$B$22)) -> 0.21221456 | I67: =_xlfn.LET(_xlpm.d,I$56,_xlpm.cert,Simulator!$H18,_xlpm.regd,Simulator!$I18,_xlpm.compl,IF(_xlpm.regd="",EDATE($B$26,$B$25+_xlpm.d),IF(_xlpm.regd<$B$26,EDATE($B$26,$B$24+_xlpm.d),EDATE(_xlpm.regd,_xlpm.d))),_xlpm.n,MAX(1,(YEAR(_xlpm.compl)-YEAR($B$26))*12+MONTH(_xlpm.compl)-MONTH($B$26)),_xlpm.pace,MIN($B$23,(100-_xlpm.cert)/_xlpm.n),_xlpm.c,MIN(100,_xlpm.cert+_xlpm.pace*$B$27),IF(_xlpm.c>=100,1,$B$20+(1-$B$20-$B$21)*_xlpm.c/100)*MIN(1,_xlpm.c/100)*(1-$B$22)) -> 0.17815331 | J67: =_xlfn.LET(_xlpm.d,J$56,_xlpm.cert,Simulator!$H18,_xlpm.regd,Simulator!$I18,_xlpm.compl,IF(_xlpm.regd="",EDATE($B$26,$B$25+_xlpm.d),IF(_xlpm.regd<$B$26,EDATE($B$26,$B$24+_xlpm.d),EDATE(_xlpm.regd,_xlpm.d))),_xlpm.n,MAX(1,(YEAR(_xlpm.compl)-YEAR($B$26))*12+MONTH(_xlpm.compl)-MONTH($B$26)),_xlpm.pace,MIN($B$23,(100-_xlpm.cert)/_xlpm.n),_xlpm.c,MIN(100,_xlpm.cert+_xlpm.pace*$B$27),IF(_xlpm.c>=100,1,$B$20+(1-$B$20-$B$21)*_xlpm.c/100)*MIN(1,_xlpm.c/100)*(1-$B$22)) -> 0.15864303 | K67: =_xlfn.LET(_xlpm.d,K$56,_xlpm.cert,Simulator!$H18,_xlpm.regd,Simulator!$I18,_xlpm.compl,IF(_xlpm.regd="",EDATE($B$26,$B$25+_xlpm.d),IF(_xlpm.regd<$B$26,EDATE($B$26,$B$24+_xlpm.d),EDATE(_xlpm.regd,_xlpm.d))),_xlpm.n,MAX(1,(YEAR(_xlpm.compl)-YEAR($B$26))*12+MONTH(_xlpm.compl)-MONTH($B$26)),_xlpm.pace,MIN($B$23,(100-_xlpm.cert)/_xlpm.n),_xlpm.c,MIN(100,_xlpm.cert+_xlpm.pace*$B$27),IF(_xlpm.c>=100,1,$B$20+(1-$B$20-$B$21)*_xlpm.c/100)*MIN(1,_xlpm.c/100)*(1-$B$22)) -> 0.14605429 | L67: =_xlfn.LET(_xlpm.d,L$56,_xlpm.cert,Simulator!$H18,_xlpm.regd,Simulator!$I18,_xlpm.compl,IF(_xlpm.regd="",EDATE($B$26,$B$25+_xlpm.d),IF(_xlpm.regd<$B$26,EDATE($B$26,$B$24+_xlpm.d),EDATE(_xlpm.regd,_xlpm.d))),_xlpm.n,MAX(1,(YEAR(_xlpm.compl)-YEAR($B$26))*12+MONTH(_xlpm.compl)-MONTH($B$26)),_xlpm.pace,MIN($B$23,(100-_xlpm.cert)/_xlpm.n),_xlpm.c,MIN(100,_xlpm.cert+_xlpm.pace*$B$27),IF(_xlpm.c>=100,1,$B$20+(1-$B$20-$B$21)*_xlpm.c/100)*MIN(1,_xlpm.c/100)*(1-$B$22)) -> 0.13727781
A68: =Simulator!A19 -> 3107 | B68: =Simulator!B19 -> One by Binghatti | C68: =Simulator!J19 -> 1799.456 | D68: =Simulator!K19*Simulator!G19/1000000*$B$18*(1+$B$19) -> 192.61782 | E68: =Simulator!$J19*IF(Simulator!$H19>=100,1,$B$20+(1-$B$20-$B$21)*Simulator!$H19/100)*MIN(1,Simulator!$H19/100)*(1-$B$22) -> 341.89663 | F68: =_xlfn.LET(_xlpm.d,F$56,_xlpm.cert,Simulator!$H19,_xlpm.regd,Simulator!$I19,_xlpm.compl,IF(_xlpm.regd="",EDATE($B$26,$B$25+_xlpm.d),IF(_xlpm.regd<$B$26,EDATE($B$26,$B$24+_xlpm.d),EDATE(_xlpm.regd,_xlpm.d))),_xlpm.n,MAX(1,(YEAR(_xlpm.compl)-YEAR($B$26))*12+MONTH(_xlpm.compl)-MONTH($B$26)),_xlpm.pace,MIN($B$23,(100-_xlpm.cert)/_xlpm.n),_xlpm.c,MIN(100,_xlpm.cert+_xlpm.pace*$B$27),IF(_xlpm.c>=100,1,$B$20+(1-$B$20-$B$21)*_xlpm.c/100)*MIN(1,_xlpm.c/100)*(1-$B$22)) -> 0.5472 | G68: =_xlfn.LET(_xlpm.d,G$56,_xlpm.cert,Simulator!$H19,_xlpm.regd,Simulator!$I19,_xlpm.compl,IF(_xlpm.regd="",EDATE($B$26,$B$25+_xlpm.d),IF(_xlpm.regd<$B$26,EDATE($B$26,$B$24+_xlpm.d),EDATE(_xlpm.regd,_xlpm.d))),_xlpm.n,MAX(1,(YEAR(_xlpm.compl)-YEAR($B$26))*12+MONTH(_xlpm.compl)-MONTH($B$26)),_xlpm.pace,MIN($B$23,(100-_xlpm.cert)/_xlpm.n),_xlpm.c,MIN(100,_xlpm.cert+_xlpm.pace*$B$27),IF(_xlpm.c>=100,1,$B$20+(1-$B$20-$B$21)*_xlpm.c/100)*MIN(1,_xlpm.c/100)*(1-$B$22)) -> 0.37057851 | H68: =_xlfn.LET(_xlpm.d,H$56,_xlpm.cert,Simulator!$H19,_xlpm.regd,Simulator!$I19,_xlpm.compl,IF(_xlpm.regd="",EDATE($B$26,$B$25+_xlpm.d),IF(_xlpm.regd<$B$26,EDATE($B$26,$B$24+_xlpm.d),EDATE(_xlpm.regd,_xlpm.d))),_xlpm.n,MAX(1,(YEAR(_xlpm.compl)-YEAR($B$26))*12+MONTH(_xlpm.compl)-MONTH($B$26)),_xlpm.pace,MIN($B$23,(100-_xlpm.cert)/_xlpm.n),_xlpm.c,MIN(100,_xlpm.cert+_xlpm.pace*$B$27),IF(_xlpm.c>=100,1,$B$20+(1-$B$20-$B$21)*_xlpm.c/100)*MIN(1,_xlpm.c/100)*(1-$B$22)) -> 0.30782227 | I68: =_xlfn.LET(_xlpm.d,I$56,_xlpm.cert,Simulator!$H19,_xlpm.regd,Simulator!$I19,_xlpm.compl,IF(_xlpm.regd="",EDATE($B$26,$B$25+_xlpm.d),IF(_xlpm.regd<$B$26,EDATE($B$26,$B$24+_xlpm.d),EDATE(_xlpm.regd,_xlpm.d))),_xlpm.n,MAX(1,(YEAR(_xlpm.compl)-YEAR($B$26))*12+MONTH(_xlpm.compl)-MONTH($B$26)),_xlpm.pace,MIN($B$23,(100-_xlpm.cert)/_xlpm.n),_xlpm.c,MIN(100,_xlpm.cert+_xlpm.pace*$B$27),IF(_xlpm.c>=100,1,$B$20+(1-$B$20-$B$21)*_xlpm.c/100)*MIN(1,_xlpm.c/100)*(1-$B$22)) -> 0.2772449 | J68: =_xlfn.LET(_xlpm.d,J$56,_xlpm.cert,Simulator!$H19,_xlpm.regd,Simulator!$I19,_xlpm.compl,IF(_xlpm.regd="",EDATE($B$26,$B$25+_xlpm.d),IF(_xlpm.regd<$B$26,EDATE($B$26,$B$24+_xlpm.d),EDATE(_xlpm.regd,_xlpm.d))),_xlpm.n,MAX(1,(YEAR(_xlpm.compl)-YEAR($B$26))*12+MONTH(_xlpm.compl)-MONTH($B$26)),_xlpm.pace,MIN($B$23,(100-_xlpm.cert)/_xlpm.n),_xlpm.c,MIN(100,_xlpm.cert+_xlpm.pace*$B$27),IF(_xlpm.c>=100,1,$B$20+(1-$B$20-$B$21)*_xlpm.c/100)*MIN(1,_xlpm.c/100)*(1-$B$22)) -> 0.25921228 | K68: =_xlfn.LET(_xlpm.d,K$56,_xlpm.cert,Simulator!$H19,_xlpm.regd,Simulator!$I19,_xlpm.compl,IF(_xlpm.regd="",EDATE($B$26,$B$25+_xlpm.d),IF(_xlpm.regd<$B$26,EDATE($B$26,$B$24+_xlpm.d),EDATE(_xlpm.regd,_xlpm.d))),_xlpm.n,MAX(1,(YEAR(_xlpm.compl)-YEAR($B$26))*12+MONTH(_xlpm.compl)-MONTH($B$26)),_xlpm.pace,MIN($B$23,(100-_xlpm.cert)/_xlpm.n),_xlpm.c,MIN(100,_xlpm.cert+_xlpm.pace*$B$27),IF(_xlpm.c>=100,1,$B$20+(1-$B$20-$B$21)*_xlpm.c/100)*MIN(1,_xlpm.c/100)*(1-$B$22)) -> 0.24733611 | L68: =_xlfn.LET(_xlpm.d,L$56,_xlpm.cert,Simulator!$H19,_xlpm.regd,Simulator!$I19,_xlpm.compl,IF(_xlpm.regd="",EDATE($B$26,$B$25+_xlpm.d),IF(_xlpm.regd<$B$26,EDATE($B$26,$B$24+_xlpm.d),EDATE(_xlpm.regd,_xlpm.d))),_xlpm.n,MAX(1,(YEAR(_xlpm.compl)-YEAR($B$26))*12+MONTH(_xlpm.compl)-MONTH($B$26)),_xlpm.pace,MIN($B$23,(100-_xlpm.cert)/_xlpm.n),_xlpm.c,MIN(100,_xlpm.cert+_xlpm.pace*$B$27),IF(_xlpm.c>=100,1,$B$20+(1-$B$20-$B$21)*_xlpm.c/100)*MIN(1,_xlpm.c/100)*(1-$B$22)) -> 0.2389294
... A88: =Simulator!A39 -> 2961 | B88: =Simulator!B39 -> Binghatti Royale | C88: =Simulator!J39 -> 460.30926 | D88: =Simulator!K39*Simulator!G39/1000000*$B$18*(1+$B$19) -> 79.872477 | E88: =Simulator!$J39*IF(Simulator!$H39>=100,1,$B$20+(1-$B$20-$B$21)*Simulator!$H39/100)*MIN(1,Simulator!$H39/100)*(1-$B$22) -> 40.628234 | F88: =_xlfn.LET(_xlpm.d,F$56,_xlpm.cert,Simulator!$H39,_xlpm.regd,Simulator!$I39,_xlpm.compl,IF(_xlpm.regd="",EDATE($B$26,$B$25+_xlpm.d),IF(_xlpm.regd<$B$26,EDATE($B$26,$B$24+_xlpm.d),EDATE(_xlpm.regd,_xlpm.d))),_xlpm.n,MAX(1,(YEAR(_xlpm.compl)-YEAR($B$26))*12+MONTH(_xlpm.compl)-MONTH($B$26)),_xlpm.pace,MIN($B$23,(100-_xlpm.cert)/_xlpm.n),_xlpm.c,MIN(100,_xlpm.cert+_xlpm.pace*$B$27),IF(_xlpm.c>=100,1,$B$20+(1-$B$20-$B$21)*_xlpm.c/100)*MIN(1,_xlpm.c/100)*(1-$B$22)) -> 0.1648053 | G88: =_xlfn.LET(_xlpm.d,G$56,_xlpm.cert,Simulator!$H39,_xlpm.regd,Simulator!$I39,_xlpm.compl,IF(_xlpm.regd="",EDATE($B$26,$B$25+_xlpm.d),IF(_xlpm.regd<$B$26,EDATE($B$26,$B$24+_xlpm.d),EDATE(_xlpm.regd,_xlpm.d))),_xlpm.n,MAX(1,(YEAR(_xlpm.compl)-YEAR($B$26))*12+MONTH(_xlpm.compl)-MONTH($B$26)),_xlpm.pace,MIN($B$23,(100-_xlpm.cert)/_xlpm.n),_xlpm.c,MIN(100,_xlpm.cert+_xlpm.pace*$B$27),IF(_xlpm.c>=100,1,$B$20+(1-$B$20-$B$21)*_xlpm.c/100)*MIN(1,_xlpm.c/100)*(1-$B$22)) -> 0.14997077 | H88: =_xlfn.LET(_xlpm.d,H$56,_xlpm.cert,Simulator!$H39,_xlpm.regd,Simulator!$I39,_xlpm.compl,IF(_xlpm.regd="",EDATE($B$26,$B$25+_xlpm.d),IF(_xlpm.regd<$B$26,EDATE($B$26,$B$24+_xlpm.d),EDATE(_xlpm.regd,_xlpm.d))),_xlpm.n,MAX(1,(YEAR(_xlpm.compl)-YEAR($B$26))*12+MONTH(_xlpm.compl)-MONTH($B$26)),_xlpm.pace,MIN($B$23,(100-_xlpm.cert)/_xlpm.n),_xlpm.c,MIN(100,_xlpm.cert+_xlpm.pace*$B$27),IF(_xlpm.c>=100,1,$B$20+(1-$B$20-$B$21)*_xlpm.c/100)*MIN(1,_xlpm.c/100)*(1-$B$22)) -> 0.13991014 | I88: =_xlfn.LET(_xlpm.d,I$56,_xlpm.cert,Simulator!$H39,_xlpm.regd,Simulator!$I39,_xlpm.compl,IF(_xlpm.regd="",EDATE($B$26,$B$25+_xlpm.d),IF(_xlpm.regd<$B$26,EDATE($B$26,$B$24+_xlpm.d),EDATE(_xlpm.regd,_xlpm.d))),_xlpm.n,MAX(1,(YEAR(_xlpm.compl)-YEAR($B$26))*12+MONTH(_xlpm.compl)-MONTH($B$26)),_xlpm.pace,MIN($B$23,(100-_xlpm.cert)/_xlpm.n),_xlpm.c,MIN(100,_xlpm.cert+_xlpm.pace*$B$27),IF(_xlpm.c>=100,1,$B$20+(1-$B$20-$B$21)*_xlpm.c/100)*MIN(1,_xlpm.c/100)*(1-$B$22)) -> 0.13264956 | J88: =_xlfn.LET(_xlpm.d,J$56,_xlpm.cert,Simulator!$H39,_xlpm.regd,Simulator!$I39,_xlpm.compl,IF(_xlpm.regd="",EDATE($B$26,$B$25+_xlpm.d),IF(_xlpm.regd<$B$26,EDATE($B$26,$B$24+_xlpm.d),EDATE(_xlpm.regd,_xlpm.d))),_xlpm.n,MAX(1,(YEAR(_xlpm.compl)-YEAR($B$26))*12+MONTH(_xlpm.compl)-MONTH($B$26)),_xlpm.pace,MIN($B$23,(100-_xlpm.cert)/_xlpm.n),_xlpm.c,MIN(100,_xlpm.cert+_xlpm.pace*$B$27),IF(_xlpm.c>=100,1,$B$20+(1-$B$20-$B$21)*_xlpm.c/100)*MIN(1,_xlpm.c/100)*(1-$B$22)) -> 0.12716786 | K88: =_xlfn.LET(_xlpm.d,K$56,_xlpm.cert,Simulator!$H39,_xlpm.regd,Simulator!$I39,_xlpm.compl,IF(_xlpm.regd="",EDATE($B$26,$B$25+_xlpm.d),IF(_xlpm.regd<$B$26,EDATE($B$26,$B$24+_xlpm.d),EDATE(_xlpm.regd,_xlpm.d))),_xlpm.n,MAX(1,(YEAR(_xlpm.compl)-YEAR($B$26))*12+MONTH(_xlpm.compl)-MONTH($B$26)),_xlpm.pace,MIN($B$23,(100-_xlpm.cert)/_xlpm.n),_xlpm.c,MIN(100,_xlpm.cert+_xlpm.pace*$B$27),IF(_xlpm.c>=100,1,$B$20+(1-$B$20-$B$21)*_xlpm.c/100)*MIN(1,_xlpm.c/100)*(1-$B$22)) -> 0.1228851 | L88: =_xlfn.LET(_xlpm.d,L$56,_xlpm.cert,Simulator!$H39,_xlpm.regd,Simulator!$I39,_xlpm.compl,IF(_xlpm.regd="",EDATE($B$26,$B$25+_xlpm.d),IF(_xlpm.regd<$B$26,EDATE($B$26,$B$24+_xlpm.d),EDATE(_xlpm.regd,_xlpm.d))),_xlpm.n,MAX(1,(YEAR(_xlpm.compl)-YEAR($B$26))*12+MONTH(_xlpm.compl)-MONTH($B$26)),_xlpm.pace,MIN($B$23,(100-_xlpm.cert)/_xlpm.n),_xlpm.c,MIN(100,_xlpm.cert+_xlpm.pace*$B$27),IF(_xlpm.c>=100,1,$B$20+(1-$B$20-$B$21)*_xlpm.c/100)*MIN(1,_xlpm.c/100)*(1-$B$22)) -> 0.11944802
B89: Total, 32 live projects | C89: =SUM(C57:C88) -> 37362.292 | D89: =SUM(D57:D88) -> 3626.5163 | E89: =SUM(E57:E88) -> 4153.2762

Sheet Cash flow
A1: CASH FLOW AGAINST THE FULL MATURITY STACK
A2: Every sukuk and bank maturity to 2031, against escrow release from the delivery schedule, net of construction cost and debt service. Sixty-four months, October 2026 to January 2032.
A4: 1. WHY THIS SHEET EXISTS
A5: The Dashboard answers one question: can the 28 February 2027 sukuk be met? It can. But that maturity is AED 1,836m of a 2027 total of AED 3,709m, and three more sukuk of AED 1,836m each fall due in 2029, 2030 and 2031. The escrow engine on the Simulator runs only 28 months, so it cannot see them. This sheet rebuilds the release profile over 64 months and sets it against the whole stack.
A6: Two things the Dashboard leaves out are added here. Construction cost: escrow money is released to build, not to repay bondholders, so cost to complete is deducted as it is incurred. Debt service: the four sukuk carry coupons of 9.625%, 7.75%, 8.125% and 8.375% on AED 1,836m each, and bank debt prices over EIBOR. Neither appears anywhere else in the workbook.
A7: Retention is also recovered here. The Simulator writes off the 5% RERA retention because it releases a year after completion, beyond its horizon. Over 64 months most of it comes back, and it is credited in the month it is due.
A8: THE ANSWER — WHICH MATURITIES ARE ACTUALLY COVERED
A9: {=_xlfn.LET(_xlpm.n,COUNTIF($F$94:$F$101,"<1"),_xlpm.k,COUNTIF($F$94:$F$101,">=1"),_xlpm.g,SUMIF($F$94:$F$101,"<1",$G$94:$G$101),_xlpm.lastd,MAX(($G$94:$G$101>0)*$B$94:$B$101),IF(_xlpm.n=0,"All eight maturities to 2031 are met from modelled cash. Conditional on the three derived assumptions listed on the Cover.","On the register as it stands, "&_xlpm.n&IF(_xlpm.n=1," of"," of")&" the eight maturities to 2031 "&IF(_xlpm.n=1,"is","are")&" not met from modelled cash and "&_xlpm.k&IF(_xlpm.k=1," is"," are")&". The shortfall totals AED "&TEXT(_xlpm.g,"#,##0")&" m and falls on the earliest maturities, the last of them "&TEXT(_xlpm.lastd,"mmm yyyy")&". This is conditional: cost to complete, the bank rate and the register's progress readings are all derived rather than disclosed, and each reverses the result on its own."))} -> On the register as it stands, 2 of the eight maturities to 2031 are not met from modelled cash and 6 are. The shortfall totals AED 551 m and falls on the earliest maturities, the last of them Feb 2027. This is conditional: cost to complete, the bank rate and the register's progress readings are all derived rather than disclosed, and each reverses the result on its own.
A11: Deepest cash shortfall | B11: =MIN($C$71:$BN$71) -> -362.54875 | C11: AED m, lowest point on the whole path
A12: Month it happens | B12: =INDEX($C$58:$BN$58,1,MATCH(MIN($C$71:$BN$71),$C$71:$BN$71,0)) -> 46419 | C12: The window Moody's placed the ratings on review over
A13: Cash once the 2027 handovers land | B13: =D86 -> 13112.828 | C13: ="AED m at end 2027, after "&TEXT(D89,"0")&" towers complete in the year" -> AED m at end 2027, after 24 towers complete in the year
A14: ="Why this differs from the escrow headroom measure in Dashboard section 1, which reads "&TEXT(Dashboard!$F$17,"0.00")&_xlfn._LONGTEXT("x on the same sukuk: that ratio credits the full escrow release against debt and deducts neither construction cost nor profit payments. Escrow money is released to build. Once cost to complete and debt service are taken out, the near-term picture reverses",". The Dashboard verdict band, the Cover table and this sheet all now report the cash test and agree.") -> Why this differs from the escrow headroom measure in Dashboard section 1, which reads 3.79x on the same sukuk: that ratio credits the full escrow release against debt and deducts neither construction cost nor profit payments. Escrow money is released to build. Once cost to complete and debt service are taken out, the near-term picture reverses. The Dashboard verdict band, the Cover table and this sheet all now report the cash test and agree.
A16: 2. INPUTS, ALL PULLED LIVE
A17: Input | B17: Value | C17: Source
A18: As of date | B18: =Simulator!$C$3 -> 46275 | C18: Simulator, register read date
A19: Opening cash outside escrow | B19: =Dashboard!$C$17 -> 686.5759 | C19: Dashboard, cash outside escrow plus any received since the balance sheet date
A20: Cost to complete, share of contracted value | B20: =Scenarios!$F$15 -> 0.55 | C20: Scenarios, active column
A21: Bank rate, EIBOR plus quoted margin | B21: =Scenarios!$F$16+Scenarios!$F$17 -> 0.0658 | C21: Scenarios, active column
A22: Bank rate basis | B22: Implied | C22: Type Implied to use the rate backed out of reported finance cost in section 3b, or Quoted to use EIBOR plus the margin from the financing notes.
A23: Refinance sukuk at maturity | B23: =Scenarios!$F$18 -> No | C23: Scenarios, active column
A24: Refinancing spread over maturing coupon | B24: =Scenarios!$F$19 -> 0.02 | C24: Scenarios, active column
A25: RERA retention share | B25: =Scenarios!$F$13 -> 0.05 | C25: Scenarios, active column
A26: Months after completion until retention releases | B26: 12 | C26: RERA rule, one year after completion
A27: Horizon, months | B27: 64 | C27: Oct 2026 to Jan 2032, covering the 2031 sukuk
A29: 3. DEBT SERVICE, INSTRUMENT BY INSTRUMENT
A30: Amounts, coupons and maturity dates pulled from the Debt sheet. Bank tranches carry no stated coupon in the accounts, so they price at EIBOR plus margin. Month index counts from the as-of date; month 1 is October 2026.
A31: Instrument | B31: Type | C31: Amount | D31: Rate | E31: Maturity | F31: Annual profit | G31: Maturity month | H31: Rate source
A32: =Debt!A6 -> 9.625% sukuk due 28 Feb 2027 | B32: =Debt!C6 -> Sukuk | C32: =Debt!E6 -> 1836.25 | D32: =IF(Debt!F6="",$B$21,Debt!F6) -> 0.09625 | E32: =Debt!H6 -> 46446 | F32: =C32*D32 -> 176.73906 | G32: =(YEAR(E32)-YEAR($B$18))*12+MONTH(E32)-MONTH($B$18) -> 5 | H32: =IF(Debt!F6="","derived, section 3b","actual coupon, offering circular") -> actual coupon, offering circular
A33: =Debt!A7 -> 7.75% green sukuk due 2 Jul 2029 | B33: =Debt!C7 -> Sukuk | C33: =Debt!E7 -> 1836.25 | D33: =IF(Debt!F7="",$B$21,Debt!F7) -> 0.0775 | E33: =Debt!H7 -> 47301 | F33: =C33*D33 -> 142.30937 | G33: =(YEAR(E33)-YEAR($B$18))*12+MONTH(E33)-MONTH($B$18) -> 34 | H33: =IF(Debt!F7="","derived, section 3b","actual coupon, offering circular") -> actual coupon, offering circular
A34: =Debt!A8 -> 8.125% sukuk due 7 Aug 2030 | B34: =Debt!C8 -> Sukuk | C34: =Debt!E8 -> 1836.25 | D34: =IF(Debt!F8="",$B$21,Debt!F8) -> 0.08125 | E34: =Debt!H8 -> 47702 | F34: =C34*D34 -> 149.19531 | G34: =(YEAR(E34)-YEAR($B$18))*12+MONTH(E34)-MONTH($B$18) -> 47 | H34: =IF(Debt!F8="","derived, section 3b","actual coupon, offering circular") -> actual coupon, offering circular
A35: =Debt!A9 -> 8.375% sukuk due 12 Aug 2031 | B35: =Debt!C9 -> Sukuk | C35: =Debt!E9 -> 1836.25 | D35: =IF(Debt!F9="",$B$51,Debt!F9) -> 0.08375 | E35: =Debt!H9 -> 48072 | F35: =C35*D35 -> 153.78594 | G35: =(YEAR(E35)-YEAR($B$18))*12+MONTH(E35)-MONTH($B$18) -> 59 | H35: =IF(Debt!F9="","derived, section 3b","actual coupon, offering circular") -> actual coupon, offering circular
A36: =Debt!A10 -> Secured bank debt — due H2 2026 | B36: =Debt!C10 -> Bank | C36: =Debt!E10 -> 1031.9725 | D36: =IF(Debt!F10="",$B$51,Debt!F10) -> 0.097691709 | E36: =Debt!H10 -> 46387 | F36: =C36*D36 -> 100.81516 | G36: =(YEAR(E36)-YEAR($B$18))*12+MONTH(E36)-MONTH($B$18) -> 3 | H36: =IF(Debt!F10="","derived, section 3b","actual coupon, offering circular") -> derived, section 3b
A37: =Debt!A11 -> Secured bank debt — due H1 2027 | B37: =Debt!C11 -> Bank | C37: =Debt!E11 -> 690.43 | D37: =IF(Debt!F11="",$B$51,Debt!F11) -> 0.097691709 | E37: =Debt!H11 -> 46568 | F37: =C37*D37 -> 67.449286 | G37: =(YEAR(E37)-YEAR($B$18))*12+MONTH(E37)-MONTH($B$18) -> 9 | H37: =IF(Debt!F11="","derived, section 3b","actual coupon, offering circular") -> derived, section 3b
A38: =Debt!A12 -> Secured bank debt — due H2 2027 | B38: =Debt!C12 -> Bank | C38: =Debt!E12 -> 1182.545 | D38: =IF(Debt!F12="",$B$51,Debt!F12) -> 0.097691709 | E38: =Debt!H12 -> 46752 | F38: =C38*D38 -> 115.52484 | G38: =(YEAR(E38)-YEAR($B$18))*12+MONTH(E38)-MONTH($B$18) -> 15 | H38: =IF(Debt!F12="","derived, section 3b","actual coupon, offering circular") -> derived, section 3b
A39: =Debt!A13 -> Secured bank debt — due 2028 | B39: =Debt!C13 -> Bank | C39: =Debt!E13 -> 1373.515 | D39: =IF(Debt!F13="",$B$51,Debt!F13) -> 0.097691709 | E39: =Debt!H13 -> 46934 | F39: =C39*D39 -> 134.18103 | G39: =(YEAR(E39)-YEAR($B$18))*12+MONTH(E39)-MONTH($B$18) -> 21 | H39: =IF(Debt!F13="","derived, section 3b","actual coupon, offering circular") -> derived, section 3b
A40: Total | C40: =SUM(C32:C39) -> 11623.462 | F40: =SUM(F32:F39) -> 1040 | H40: =C40-Debt!$E$14 -> 0
A42: 3b. THE BANK RATE, BACKED OUT OF REPORTED FINANCE COST
A43: The four sukuk above use their actual coupons, taken from the offering circulars via the Debt sheet, so nothing is assumed for them. The bank tranches are the only debt without a stated rate: the accounts give amounts by period, not pricing. Rather than assume one, the rate is backed out of the finance cost the company actually reported — total finance cost less the sukuk profit run rate, over the bank debt outstanding.
A44: Step | B44: H1 2026, annualised | C44: Note
A45: Reported finance cost | B45: =Financials!$D$22 -> 1040 | C45: Financials, H1 finance cost doubled. Covers all debt, sukuk and bank together.
A46: less sukuk profit at actual coupons | B46: {=-SUMPRODUCT(($B$32:$B$35="Sukuk")*$C$32:$C$35*$D$32:$D$35)} -> -622.02969 | C46: Run rate of the four sukuk at their stated coupons. Restricted to the sukuk rows deliberately: summing the whole profit column would make the bank rate depend on itself.
A47: Implied bank finance cost | B47: =B45+B46 -> 417.97031
A48: Bank debt outstanding | B48: {=SUMPRODUCT(($B$32:$B$39="Bank")*$C$32:$C$39)} -> 4278.4625
A49: Implied bank all-in rate | B49: =IF(B48>0,B47/B48,"") -> 0.097691709 | C49: Above EIBOR plus the quoted margin, because reported finance cost also carries issue-cost amortisation and fees, and because debt grew through the period so the closing balance understates the average. Treat as an upper bound.
A50: Cross-check: EIBOR plus quoted margin | B50: =Scenarios!$F$16+Scenarios!$F$17 -> 0.0658 | C50: From the financing notes on the Debt sheet. A lower bound.
A51: Bank rate used in this model | B51: =IF($B$22="Implied",$B$49,$B$50) -> 0.097691709 | C51: Switch between the two with the Bank rate basis input in section 2.
A54: 4. MONTHLY ENGINE, OCTOBER 2026 TO JANUARY 2032
A55: One column per month. Escrow release uses the same arithmetic as the Simulator, extended past its 28-month limit; the check in section 7 confirms month 28 ties to the Simulator exactly. Retention releases twelve months after each tower completes. Construction cost is incurred in step with certified progress. Months 1 to 7 are shown; months 8 to 64 are grouped behind the plus sign above column J, since columns C to I also carry the annual summary and maturity tables below.
A57: Month index | C57: 1 | D57: =C57+1 -> 2 | E57: =D57+1 -> 3 | F57: =E57+1 -> 4 | G57: =F57+1 -> 5 | H57: =G57+1 -> 6 | I57: =H57+1 -> 7 | J57: =I57+1 -> 8 | K57: =J57+1 -> 9 | ... BN57: =BM57+1 -> 64
A58: Month | C58: =EOMONTH($B$18,C57-1)+1 -> 46296 | D58: =EOMONTH($B$18,D57-1)+1 -> 46327 | E58: =EOMONTH($B$18,E57-1)+1 -> 46357 | F58: =EOMONTH($B$18,F57-1)+1 -> 46388 | G58: =EOMONTH($B$18,G57-1)+1 -> 46419 | H58: =EOMONTH($B$18,H57-1)+1 -> 46447 | I58: =EOMONTH($B$18,I57-1)+1 -> 46478 | J58: =EOMONTH($B$18,J57-1)+1 -> 46508 | ... BN58: =EOMONTH($B$18,BN57-1)+1 -> 48214
A59: Cumulative escrow release, net of retention | C59: {=_xlfn.LET(_xlpm.m,C$57,_xlpm.cert,IF(Simulator!$H$8:$H$39+Simulator!$O$8:$O$39*_xlpm.m>100,100,Simulator!$H$8:$H$39+Simulator!$O$8:$O$39*_xlpm.m),_xlpm.cf,IF(_xlpm.cert>=100,1,Scenarios!$F$11+(1-Scenarios!$F$11-Scenarios!$F$12)*_xlpm.cert/100),_xlpm.prog,IF(_xlpm.cert/100>1,1,_xlpm.cert/100),_xlpm.rf,_xlpm.cf*_xlpm.prog*(1-Scenarios!$F$13),_xlpm.x,Simulator!$P$8:$P$39*_xlpm.rf-Simulator!$Q$8:$Q$39,SUMPRODUCT(_xlpm.x*(_xlpm.x>0)))} -> 1771.9373 | D59: {=_xlfn.LET(_xlpm.m,D$57,_xlpm.cert,IF(Simulator!$H$8:$H$39+Simulator!$O$8:$O$39*_xlpm.m>100,100,Simulator!$H$8:$H$39+Simulator!$O$8:$O$39*_xlpm.m),_xlpm.cf,IF(_xlpm.cert>=100,1,Scenarios!$F$11+(1-Scenarios!$F$11-Scenarios!$F$12)*_xlpm.cert/100),_xlpm.prog,IF(_xlpm.cert/100>1,1,_xlpm.cert/100),_xlpm.rf,_xlpm.cf*_xlpm.prog*(1-Scenarios!$F$13),_xlpm.x,Simulator!$P$8:$P$39*_xlpm.rf-Simulator!$Q$8:$Q$39,SUMPRODUCT(_xlpm.x*(_xlpm.x>0)))} -> 3371.8109 | E59: {=_xlfn.LET(_xlpm.m,E$57,_xlpm.cert,IF(Simulator!$H$8:$H$39+Simulator!$O$8:$O$39*_xlpm.m>100,100,Simulator!$H$8:$H$39+Simulator!$O$8:$O$39*_xlpm.m),_xlpm.cf,IF(_xlpm.cert>=100,1,Scenarios!$F$11+(1-Scenarios!$F$11-Scenarios!$F$12)*_xlpm.cert/100),_xlpm.prog,IF(_xlpm.cert/100>1,1,_xlpm.cert/100),_xlpm.rf,_xlpm.cf*_xlpm.prog*(1-Scenarios!$F$13),_xlpm.x,Simulator!$P$8:$P$39*_xlpm.rf-Simulator!$Q$8:$Q$39,SUMPRODUCT(_xlpm.x*(_xlpm.x>0)))} -> 5225.5363 | F59: {=_xlfn.LET(_xlpm.m,F$57,_xlpm.cert,IF(Simulator!$H$8:$H$39+Simulator!$O$8:$O$39*_xlpm.m>100,100,Simulator!$H$8:$H$39+Simulator!$O$8:$O$39*_xlpm.m),_xlpm.cf,IF(_xlpm.cert>=100,1,Scenarios!$F$11+(1-Scenarios!$F$11-Scenarios!$F$12)*_xlpm.cert/100),_xlpm.prog,IF(_xlpm.cert/100>1,1,_xlpm.cert/100),_xlpm.rf,_xlpm.cf*_xlpm.prog*(1-Scenarios!$F$13),_xlpm.x,Simulator!$P$8:$P$39*_xlpm.rf-Simulator!$Q$8:$Q$39,SUMPRODUCT(_xlpm.x*(_xlpm.x>0)))} -> 7333.1135 | G59: {=_xlfn.LET(_xlpm.m,G$57,_xlpm.cert,IF(Simulator!$H$8:$H$39+Simulator!$O$8:$O$39*_xlpm.m>100,100,Simulator!$H$8:$H$39+Simulator!$O$8:$O$39*_xlpm.m),_xlpm.cf,IF(_xlpm.cert>=100,1,Scenarios!$F$11+(1-Scenarios!$F$11-Scenarios!$F$12)*_xlpm.cert/100),_xlpm.prog,IF(_xlpm.cert/100>1,1,_xlpm.cert/100),_xlpm.rf,_xlpm.cf*_xlpm.prog*(1-Scenarios!$F$13),_xlpm.x,Simulator!$P$8:$P$39*_xlpm.rf-Simulator!$Q$8:$Q$39,SUMPRODUCT(_xlpm.x*(_xlpm.x>0)))} -> 10188.657 | H59: {=_xlfn.LET(_xlpm.m,H$57,_xlpm.cert,IF(Simulator!$H$8:$H$39+Simulator!$O$8:$O$39*_xlpm.m>100,100,Simulator!$H$8:$H$39+Simulator!$O$8:$O$39*_xlpm.m),_xlpm.cf,IF(_xlpm.cert>=100,1,Scenarios!$F$11+(1-Scenarios!$F$11-Scenarios!$F$12)*_xlpm.cert/100),_xlpm.prog,IF(_xlpm.cert/100>1,1,_xlpm.cert/100),_xlpm.rf,_xlpm.cf*_xlpm.prog*(1-Scenarios!$F$13),_xlpm.x,Simulator!$P$8:$P$39*_xlpm.rf-Simulator!$Q$8:$Q$39,SUMPRODUCT(_xlpm.x*(_xlpm.x>0)))} -> 13785.522 | I59: {=_xlfn.LET(_xlpm.m,I$57,_xlpm.cert,IF(Simulator!$H$8:$H$39+Simulator!$O$8:$O$39*_xlpm.m>100,100,Simulator!$H$8:$H$39+Simulator!$O$8:$O$39*_xlpm.m),_xlpm.cf,IF(_xlpm.cert>=100,1,Scenarios!$F$11+(1-Scenarios!$F$11-Scenarios!$F$12)*_xlpm.cert/100),_xlpm.prog,IF(_xlpm.cert/100>1,1,_xlpm.cert/100),_xlpm.rf,_xlpm.cf*_xlpm.prog*(1-Scenarios!$F$13),_xlpm.x,Simulator!$P$8:$P$39*_xlpm.rf-Simulator!$Q$8:$Q$39,SUMPRODUCT(_xlpm.x*(_xlpm.x>0)))} -> 16841.512 | J59: {=_xlfn.LET(_xlpm.m,J$57,_xlpm.cert,IF(Simulator!$H$8:$H$39+Simulator!$O$8:$O$39*_xlpm.m>100,100,Simulator!$H$8:$H$39+Simulator!$O$8:$O$39*_xlpm.m),_xlpm.cf,IF(_xlpm.cert>=100,1,Scenarios!$F$11+(1-Scenarios!$F$11-Scenarios!$F$12)*_xlpm.cert/100),_xlpm.prog,IF(_xlpm.cert/100>1,1,_xlpm.cert/100),_xlpm.rf,_xlpm.cf*_xlpm.prog*(1-Scenarios!$F$13),_xlpm.x,Simulator!$P$8:$P$39*_xlpm.rf-Simulator!$Q$8:$Q$39,SUMPRODUCT(_xlpm.x*(_xlpm.x>0)))} -> 19403.154 | ... BN59: {=_xlfn.LET(_xlpm.m,BN$57,_xlpm.cert,IF(Simulator!$H$8:$H$39+Simulator!$O$8:$O$39*_xlpm.m>100,100,Simulator!$H$8:$H$39+Simulator!$O$8:$O$39*_xlpm.m),_xlpm.cf,IF(_xlpm.cert>=100,1,Scenarios!$F$11+(1-Scenarios!$F$11-Scenarios!$F$12)*_xlpm.cert/100),_xlpm.prog,IF(_xlpm.cert/100>1,1,_xlpm.cert/100),_xlpm.rf,_xlpm.cf*_xlpm.prog*(1-Scenarios!$F$13),_xlpm.x,Simulator!$P$8:$P$39*_xlpm.rf-Simulator!$Q$8:$Q$39,SUMPRODUCT(_xlpm.x*(_xlpm.x>0)))} -> 34786.092
A60: Escrow release in month | C60: =C59 -> 1771.9373 | D60: =D59-C59 -> 1599.8736 | E60: =E59-D59 -> 1853.7254 | F60: =F59-E59 -> 2107.5771 | G60: =G59-F59 -> 2855.5431 | H60: =H59-G59 -> 3596.8651 | I60: =I59-H59 -> 3055.9904 | J60: =J59-I59 -> 2561.6423 | K60: =K59-J59 -> 3768.6449 | ... BN60: =BN59-BM59 -> 0
A61: Cumulative retention released | C61: {=SUMPRODUCT((Simulator!$N$8:$N$39+$B$26<=C$57)*Simulator!$P$8:$P$39)*$B$25} -> 0 | D61: {=SUMPRODUCT((Simulator!$N$8:$N$39+$B$26<=D$57)*Simulator!$P$8:$P$39)*$B$25} -> 0 | E61: {=SUMPRODUCT((Simulator!$N$8:$N$39+$B$26<=E$57)*Simulator!$P$8:$P$39)*$B$25} -> 0 | F61: {=SUMPRODUCT((Simulator!$N$8:$N$39+$B$26<=F$57)*Simulator!$P$8:$P$39)*$B$25} -> 0 | G61: {=SUMPRODUCT((Simulator!$N$8:$N$39+$B$26<=G$57)*Simulator!$P$8:$P$39)*$B$25} -> 0 | H61: {=SUMPRODUCT((Simulator!$N$8:$N$39+$B$26<=H$57)*Simulator!$P$8:$P$39)*$B$25} -> 0 | I61: {=SUMPRODUCT((Simulator!$N$8:$N$39+$B$26<=I$57)*Simulator!$P$8:$P$39)*$B$25} -> 0 | J61: {=SUMPRODUCT((Simulator!$N$8:$N$39+$B$26<=J$57)*Simulator!$P$8:$P$39)*$B$25} -> 0 | ... BN61: {=SUMPRODUCT((Simulator!$N$8:$N$39+$B$26<=BN$57)*Simulator!$P$8:$P$39)*$B$25} -> 2049.4404
A62: Retention released in month | C62: =C61 -> 0 | D62: =D61-C61 -> 0 | E62: =E61-D61 -> 0 | F62: =F61-E61 -> 0 | G62: =G61-F61 -> 0 | H62: =H61-G61 -> 0 | I62: =I61-H61 -> 0 | J62: =J61-I61 -> 0 | K62: =K61-J61 -> 0 | ... BN62: =BN61-BM61 -> 0
A63: Cumulative cost to complete incurred | C63: {=_xlfn.LET(_xlpm.m,C$57,_xlpm.cert,IF(Simulator!$H$8:$H$39+Simulator!$O$8:$O$39*_xlpm.m>100,100,Simulator!$H$8:$H$39+Simulator!$O$8:$O$39*_xlpm.m),SUMPRODUCT(Simulator!$P$8:$P$39*$B$20*(_xlpm.cert-Simulator!$H$8:$H$39)/100))} -> 1602.8568 | D63: {=_xlfn.LET(_xlpm.m,D$57,_xlpm.cert,IF(Simulator!$H$8:$H$39+Simulator!$O$8:$O$39*_xlpm.m>100,100,Simulator!$H$8:$H$39+Simulator!$O$8:$O$39*_xlpm.m),SUMPRODUCT(Simulator!$P$8:$P$39*$B$20*(_xlpm.cert-Simulator!$H$8:$H$39)/100))} -> 3205.7136 | E63: {=_xlfn.LET(_xlpm.m,E$57,_xlpm.cert,IF(Simulator!$H$8:$H$39+Simulator!$O$8:$O$39*_xlpm.m>100,100,Simulator!$H$8:$H$39+Simulator!$O$8:$O$39*_xlpm.m),SUMPRODUCT(Simulator!$P$8:$P$39*$B$20*(_xlpm.cert-Simulator!$H$8:$H$39)/100))} -> 4808.5704 | F63: {=_xlfn.LET(_xlpm.m,F$57,_xlpm.cert,IF(Simulator!$H$8:$H$39+Simulator!$O$8:$O$39*_xlpm.m>100,100,Simulator!$H$8:$H$39+Simulator!$O$8:$O$39*_xlpm.m),SUMPRODUCT(Simulator!$P$8:$P$39*$B$20*(_xlpm.cert-Simulator!$H$8:$H$39)/100))} -> 6411.4272 | G63: {=_xlfn.LET(_xlpm.m,G$57,_xlpm.cert,IF(Simulator!$H$8:$H$39+Simulator!$O$8:$O$39*_xlpm.m>100,100,Simulator!$H$8:$H$39+Simulator!$O$8:$O$39*_xlpm.m),SUMPRODUCT(Simulator!$P$8:$P$39*$B$20*(_xlpm.cert-Simulator!$H$8:$H$39)/100))} -> 7953.0279 | H63: {=_xlfn.LET(_xlpm.m,H$57,_xlpm.cert,IF(Simulator!$H$8:$H$39+Simulator!$O$8:$O$39*_xlpm.m>100,100,Simulator!$H$8:$H$39+Simulator!$O$8:$O$39*_xlpm.m),SUMPRODUCT(Simulator!$P$8:$P$39*$B$20*(_xlpm.cert-Simulator!$H$8:$H$39)/100))} -> 9457.8749 | I63: {=_xlfn.LET(_xlpm.m,I$57,_xlpm.cert,IF(Simulator!$H$8:$H$39+Simulator!$O$8:$O$39*_xlpm.m>100,100,Simulator!$H$8:$H$39+Simulator!$O$8:$O$39*_xlpm.m),SUMPRODUCT(Simulator!$P$8:$P$39*$B$20*(_xlpm.cert-Simulator!$H$8:$H$39)/100))} -> 10777.418 | J63: {=_xlfn.LET(_xlpm.m,J$57,_xlpm.cert,IF(Simulator!$H$8:$H$39+Simulator!$O$8:$O$39*_xlpm.m>100,100,Simulator!$H$8:$H$39+Simulator!$O$8:$O$39*_xlpm.m),SUMPRODUCT(Simulator!$P$8:$P$39*$B$20*(_xlpm.cert-Simulator!$H$8:$H$39)/100))} -> 12034.535 | ... BN63: {=_xlfn.LET(_xlpm.m,BN$57,_xlpm.cert,IF(Simulator!$H$8:$H$39+Simulator!$O$8:$O$39*_xlpm.m>100,100,Simulator!$H$8:$H$39+Simulator!$O$8:$O$39*_xlpm.m),SUMPRODUCT(Simulator!$P$8:$P$39*$B$20*(_xlpm.cert-Simulator!$H$8:$H$39)/100))} -> 15555.128
A64: Construction cost in month | C64: =C63 -> 1602.8568 | D64: =D63-C63 -> 1602.8568 | E64: =E63-D63 -> 1602.8568 | F64: =F63-E63 -> 1602.8568 | G64: =G63-F63 -> 1541.6007 | H64: =H63-G63 -> 1504.847 | I64: =I63-H63 -> 1319.5432 | J64: =J63-I63 -> 1257.1166 | K64: =K63-J63 -> 1040.3271 | ... BN64: =BN63-BM63 -> 0
A65: Net project cash in month | C65: =C60+C62-C64 -> 169.08052 | D65: =D60+D62-D64 -> -2.98319 | E65: =E60+E62-E64 -> 250.86858 | F65: =F60+F62-F64 -> 504.72034 | G65: =G60+G62-G64 -> 1313.9424 | H65: =H60+H62-H64 -> 2092.018 | I65: =I60+I62-I64 -> 1736.4472 | J65: =J60+J62-J64 -> 1304.5257 | ... BN65: =BN60+BN62-BN64 -> 0
A66: Sukuk profit paid | C66: {=_xlfn.LET(_xlpm.mo,C$57,_xlpm.isSuk,($B$32:$B$39="Sukuk")*1,_xlpm.live,($G$32:$G$39>=_xlpm.mo)*1,_xlpm.rolled,IF($B$23="Yes",($G$32:$G$39<_xlpm.mo)*1,0),_xlpm.rate,$D$32:$D$39,SUMPRODUCT(_xlpm.isSuk*$C$32:$C$39*(_xlpm.live*_xlpm.rate+_xlpm.rolled*(_xlpm.rate+$B$24)))/12)} -> 51.835807 | D66: {=_xlfn.LET(_xlpm.mo,D$57,_xlpm.isSuk,($B$32:$B$39="Sukuk")*1,_xlpm.live,($G$32:$G$39>=_xlpm.mo)*1,_xlpm.rolled,IF($B$23="Yes",($G$32:$G$39<_xlpm.mo)*1,0),_xlpm.rate,$D$32:$D$39,SUMPRODUCT(_xlpm.isSuk*$C$32:$C$39*(_xlpm.live*_xlpm.rate+_xlpm.rolled*(_xlpm.rate+$B$24)))/12)} -> 51.835807 | E66: {=_xlfn.LET(_xlpm.mo,E$57,_xlpm.isSuk,($B$32:$B$39="Sukuk")*1,_xlpm.live,($G$32:$G$39>=_xlpm.mo)*1,_xlpm.rolled,IF($B$23="Yes",($G$32:$G$39<_xlpm.mo)*1,0),_xlpm.rate,$D$32:$D$39,SUMPRODUCT(_xlpm.isSuk*$C$32:$C$39*(_xlpm.live*_xlpm.rate+_xlpm.rolled*(_xlpm.rate+$B$24)))/12)} -> 51.835807 | F66: {=_xlfn.LET(_xlpm.mo,F$57,_xlpm.isSuk,($B$32:$B$39="Sukuk")*1,_xlpm.live,($G$32:$G$39>=_xlpm.mo)*1,_xlpm.rolled,IF($B$23="Yes",($G$32:$G$39<_xlpm.mo)*1,0),_xlpm.rate,$D$32:$D$39,SUMPRODUCT(_xlpm.isSuk*$C$32:$C$39*(_xlpm.live*_xlpm.rate+_xlpm.rolled*(_xlpm.rate+$B$24)))/12)} -> 51.835807 | G66: {=_xlfn.LET(_xlpm.mo,G$57,_xlpm.isSuk,($B$32:$B$39="Sukuk")*1,_xlpm.live,($G$32:$G$39>=_xlpm.mo)*1,_xlpm.rolled,IF($B$23="Yes",($G$32:$G$39<_xlpm.mo)*1,0),_xlpm.rate,$D$32:$D$39,SUMPRODUCT(_xlpm.isSuk*$C$32:$C$39*(_xlpm.live*_xlpm.rate+_xlpm.rolled*(_xlpm.rate+$B$24)))/12)} -> 51.835807 | H66: {=_xlfn.LET(_xlpm.mo,H$57,_xlpm.isSuk,($B$32:$B$39="Sukuk")*1,_xlpm.live,($G$32:$G$39>=_xlpm.mo)*1,_xlpm.rolled,IF($B$23="Yes",($G$32:$G$39<_xlpm.mo)*1,0),_xlpm.rate,$D$32:$D$39,SUMPRODUCT(_xlpm.isSuk*$C$32:$C$39*(_xlpm.live*_xlpm.rate+_xlpm.rolled*(_xlpm.rate+$B$24)))/12)} -> 37.107552 | I66: {=_xlfn.LET(_xlpm.mo,I$57,_xlpm.isSuk,($B$32:$B$39="Sukuk")*1,_xlpm.live,($G$32:$G$39>=_xlpm.mo)*1,_xlpm.rolled,IF($B$23="Yes",($G$32:$G$39<_xlpm.mo)*1,0),_xlpm.rate,$D$32:$D$39,SUMPRODUCT(_xlpm.isSuk*$C$32:$C$39*(_xlpm.live*_xlpm.rate+_xlpm.rolled*(_xlpm.rate+$B$24)))/12)} -> 37.107552 | J66: {=_xlfn.LET(_xlpm.mo,J$57,_xlpm.isSuk,($B$32:$B$39="Sukuk")*1,_xlpm.live,($G$32:$G$39>=_xlpm.mo)*1,_xlpm.rolled,IF($B$23="Yes",($G$32:$G$39<_xlpm.mo)*1,0),_xlpm.rate,$D$32:$D$39,SUMPRODUCT(_xlpm.isSuk*$C$32:$C$39*(_xlpm.live*_xlpm.rate+_xlpm.rolled*(_xlpm.rate+$B$24)))/12)} -> 37.107552 | ... BN66: {=_xlfn.LET(_xlpm.mo,BN$57,_xlpm.isSuk,($B$32:$B$39="Sukuk")*1,_xlpm.live,($G$32:$G$39>=_xlpm.mo)*1,_xlpm.rolled,IF($B$23="Yes",($G$32:$G$39<_xlpm.mo)*1,0),_xlpm.rate,$D$32:$D$39,SUMPRODUCT(_xlpm.isSuk*$C$32:$C$39*(_xlpm.live*_xlpm.rate+_xlpm.rolled*(_xlpm.rate+$B$24)))/12)} -> 0
A67: Bank interest paid | C67: {=_xlfn.LET(_xlpm.mo,C$57,_xlpm.isBank,($B$32:$B$39="Bank")*1,_xlpm.live,($G$32:$G$39>=_xlpm.mo)*1,SUMPRODUCT(_xlpm.isBank*_xlpm.live*$C$32:$C$39*$D$32:$D$39)/12)} -> 34.830859 | D67: {=_xlfn.LET(_xlpm.mo,D$57,_xlpm.isBank,($B$32:$B$39="Bank")*1,_xlpm.live,($G$32:$G$39>=_xlpm.mo)*1,SUMPRODUCT(_xlpm.isBank*_xlpm.live*$C$32:$C$39*$D$32:$D$39)/12)} -> 34.830859 | E67: {=_xlfn.LET(_xlpm.mo,E$57,_xlpm.isBank,($B$32:$B$39="Bank")*1,_xlpm.live,($G$32:$G$39>=_xlpm.mo)*1,SUMPRODUCT(_xlpm.isBank*_xlpm.live*$C$32:$C$39*$D$32:$D$39)/12)} -> 34.830859 | F67: {=_xlfn.LET(_xlpm.mo,F$57,_xlpm.isBank,($B$32:$B$39="Bank")*1,_xlpm.live,($G$32:$G$39>=_xlpm.mo)*1,SUMPRODUCT(_xlpm.isBank*_xlpm.live*$C$32:$C$39*$D$32:$D$39)/12)} -> 26.429596 | G67: {=_xlfn.LET(_xlpm.mo,G$57,_xlpm.isBank,($B$32:$B$39="Bank")*1,_xlpm.live,($G$32:$G$39>=_xlpm.mo)*1,SUMPRODUCT(_xlpm.isBank*_xlpm.live*$C$32:$C$39*$D$32:$D$39)/12)} -> 26.429596 | H67: {=_xlfn.LET(_xlpm.mo,H$57,_xlpm.isBank,($B$32:$B$39="Bank")*1,_xlpm.live,($G$32:$G$39>=_xlpm.mo)*1,SUMPRODUCT(_xlpm.isBank*_xlpm.live*$C$32:$C$39*$D$32:$D$39)/12)} -> 26.429596 | I67: {=_xlfn.LET(_xlpm.mo,I$57,_xlpm.isBank,($B$32:$B$39="Bank")*1,_xlpm.live,($G$32:$G$39>=_xlpm.mo)*1,SUMPRODUCT(_xlpm.isBank*_xlpm.live*$C$32:$C$39*$D$32:$D$39)/12)} -> 26.429596 | J67: {=_xlfn.LET(_xlpm.mo,J$57,_xlpm.isBank,($B$32:$B$39="Bank")*1,_xlpm.live,($G$32:$G$39>=_xlpm.mo)*1,SUMPRODUCT(_xlpm.isBank*_xlpm.live*$C$32:$C$39*$D$32:$D$39)/12)} -> 26.429596 | ... BN67: {=_xlfn.LET(_xlpm.mo,BN$57,_xlpm.isBank,($B$32:$B$39="Bank")*1,_xlpm.live,($G$32:$G$39>=_xlpm.mo)*1,SUMPRODUCT(_xlpm.isBank*_xlpm.live*$C$32:$C$39*$D$32:$D$39)/12)} -> 0
A68: Principal repaid at maturity | C68: {=SUMPRODUCT(($G$32:$G$39=C$57)*$C$32:$C$39)} -> 0 | D68: {=SUMPRODUCT(($G$32:$G$39=D$57)*$C$32:$C$39)} -> 0 | E68: {=SUMPRODUCT(($G$32:$G$39=E$57)*$C$32:$C$39)} -> 1031.9725 | F68: {=SUMPRODUCT(($G$32:$G$39=F$57)*$C$32:$C$39)} -> 0 | G68: {=SUMPRODUCT(($G$32:$G$39=G$57)*$C$32:$C$39)} -> 1836.25 | H68: {=SUMPRODUCT(($G$32:$G$39=H$57)*$C$32:$C$39)} -> 0 | I68: {=SUMPRODUCT(($G$32:$G$39=I$57)*$C$32:$C$39)} -> 0 | J68: {=SUMPRODUCT(($G$32:$G$39=J$57)*$C$32:$C$39)} -> 0 | ... BN68: {=SUMPRODUCT(($G$32:$G$39=BN$57)*$C$32:$C$39)} -> 0
A69: Refinancing proceeds | C69: {=IF($B$23="Yes",SUMPRODUCT(($G$32:$G$39=C$57)*($B$32:$B$39="Sukuk")*$C$32:$C$39),0)} -> 0 | D69: {=IF($B$23="Yes",SUMPRODUCT(($G$32:$G$39=D$57)*($B$32:$B$39="Sukuk")*$C$32:$C$39),0)} -> 0 | E69: {=IF($B$23="Yes",SUMPRODUCT(($G$32:$G$39=E$57)*($B$32:$B$39="Sukuk")*$C$32:$C$39),0)} -> 0 | F69: {=IF($B$23="Yes",SUMPRODUCT(($G$32:$G$39=F$57)*($B$32:$B$39="Sukuk")*$C$32:$C$39),0)} -> 0 | G69: {=IF($B$23="Yes",SUMPRODUCT(($G$32:$G$39=G$57)*($B$32:$B$39="Sukuk")*$C$32:$C$39),0)} -> 0 | H69: {=IF($B$23="Yes",SUMPRODUCT(($G$32:$G$39=H$57)*($B$32:$B$39="Sukuk")*$C$32:$C$39),0)} -> 0 | I69: {=IF($B$23="Yes",SUMPRODUCT(($G$32:$G$39=I$57)*($B$32:$B$39="Sukuk")*$C$32:$C$39),0)} -> 0 | J69: {=IF($B$23="Yes",SUMPRODUCT(($G$32:$G$39=J$57)*($B$32:$B$39="Sukuk")*$C$32:$C$39),0)} -> 0 | ... BN69: {=IF($B$23="Yes",SUMPRODUCT(($G$32:$G$39=BN$57)*($B$32:$B$39="Sukuk")*$C$32:$C$39),0)} -> 0
A70: Net cash flow in month | C70: =C65-C66-C67-C68+C69 -> 82.413856 | D70: =D65-D66-D67-D68+D69 -> -89.649857 | E70: =E65-E66-E67-E68+E69 -> -867.77059 | F70: =F65-F66-F67-F68+F69 -> 426.45494 | G70: =G65-G66-G67-G68+G69 -> -600.57299 | H70: =H65-H66-H67-H68+H69 -> 2028.4809 | I70: =I65-I66-I67-I68+I69 -> 1672.9101 | J70: =J65-J66-J67-J68+J69 -> 1240.9885 | ... BN70: =BN65-BN66-BN67-BN68+BN69 -> 0
A71: Closing cash outside escrow | C71: =$B$19+C70 -> 768.98975 | D71: =C71+D70 -> 679.3399 | E71: =D71+E70 -> -188.43069 | F71: =E71+F70 -> 238.02424 | G71: =F71+G70 -> -362.54875 | H71: =G71+H70 -> 1665.9322 | I71: =H71+I70 -> 3338.8422 | J71: =I71+J70 -> 4579.8307 | K71: =J71+K70 -> 6554.1814 | ... BN71: =BM71+BN70 -> 8071.1908
A72: Towers completing in month | C72: {=SUMPRODUCT((Simulator!$N$8:$N$39=C$57)*1)} -> 1 | D72: {=SUMPRODUCT((Simulator!$N$8:$N$39=D$57)*1)} -> 0 | E72: {=SUMPRODUCT((Simulator!$N$8:$N$39=E$57)*1)} -> 3 | F72: {=SUMPRODUCT((Simulator!$N$8:$N$39=F$57)*1)} -> 0 | G72: {=SUMPRODUCT((Simulator!$N$8:$N$39=G$57)*1)} -> 1 | H72: {=SUMPRODUCT((Simulator!$N$8:$N$39=H$57)*1)} -> 18 | I72: {=SUMPRODUCT((Simulator!$N$8:$N$39=I$57)*1)} -> 1 | J72: {=SUMPRODUCT((Simulator!$N$8:$N$39=J$57)*1)} -> 1 | ... BN72: {=SUMPRODUCT((Simulator!$N$8:$N$39=BN$57)*1)} -> 0
A74: 5. ANNUAL SUMMARY (AED m)
A75: 2026 is the fourth quarter only; 2032 is January only. Closing cash is at the end of the period shown.
A76: Year | C76: 2026 | D76: 2027 | E76: 2028 | F76: 2029 | G76: 2030 | H76: 2031 | I76: 2032
A77: Escrow release | C77: {=SUMPRODUCT((YEAR($C$58:$BN$58)=C$76)*$C$60:$BN$60)} -> 5225.5363 | D77: {=SUMPRODUCT((YEAR($C$58:$BN$58)=D$76)*$C$60:$BN$60)} -> 27418.788 | E77: {=SUMPRODUCT((YEAR($C$58:$BN$58)=E$76)*$C$60:$BN$60)} -> 2141.7672 | F77: {=SUMPRODUCT((YEAR($C$58:$BN$58)=F$76)*$C$60:$BN$60)} -> 0 | G77: {=SUMPRODUCT((YEAR($C$58:$BN$58)=G$76)*$C$60:$BN$60)} -> 0 | H77: {=SUMPRODUCT((YEAR($C$58:$BN$58)=H$76)*$C$60:$BN$60)} -> 0 | I77: {=SUMPRODUCT((YEAR($C$58:$BN$58)=I$76)*$C$60:$BN$60)} -> 0
A78: Retention released | C78: {=SUMPRODUCT((YEAR($C$58:$BN$58)=C$76)*$C$62:$BN$62)} -> 0 | D78: {=SUMPRODUCT((YEAR($C$58:$BN$58)=D$76)*$C$62:$BN$62)} -> 545.041 | E78: {=SUMPRODUCT((YEAR($C$58:$BN$58)=E$76)*$C$62:$BN$62)} -> 1318.733 | F78: {=SUMPRODUCT((YEAR($C$58:$BN$58)=F$76)*$C$62:$BN$62)} -> 185.66646 | G78: {=SUMPRODUCT((YEAR($C$58:$BN$58)=G$76)*$C$62:$BN$62)} -> 0 | H78: {=SUMPRODUCT((YEAR($C$58:$BN$58)=H$76)*$C$62:$BN$62)} -> 0 | I78: {=SUMPRODUCT((YEAR($C$58:$BN$58)=I$76)*$C$62:$BN$62)} -> 0
A79: Construction cost to complete | C79: {=SUMPRODUCT((YEAR($C$58:$BN$58)=C$76)*$C$64:$BN$64)} -> 4808.5704 | D79: {=SUMPRODUCT((YEAR($C$58:$BN$58)=D$76)*$C$64:$BN$64)} -> 10195.168 | E79: {=SUMPRODUCT((YEAR($C$58:$BN$58)=E$76)*$C$64:$BN$64)} -> 551.38878 | F79: {=SUMPRODUCT((YEAR($C$58:$BN$58)=F$76)*$C$64:$BN$64)} -> 0 | G79: {=SUMPRODUCT((YEAR($C$58:$BN$58)=G$76)*$C$64:$BN$64)} -> 0 | H79: {=SUMPRODUCT((YEAR($C$58:$BN$58)=H$76)*$C$64:$BN$64)} -> 0 | I79: {=SUMPRODUCT((YEAR($C$58:$BN$58)=I$76)*$C$64:$BN$64)} -> 0
A80: Net project cash | C80: =C77+C78-C79 -> 416.96591 | D80: =D77+D78-D79 -> 17768.661 | E80: =E77+E78-E79 -> 2909.1114 | F80: =F77+F78-F79 -> 185.66646 | G80: =G77+G78-G79 -> 0 | H80: =H77+H78-H79 -> 0 | I80: =I77+I78-I79 -> 0
A81: Sukuk profit paid | C81: {=SUMPRODUCT((YEAR($C$58:$BN$58)=C$76)*$C$66:$BN$66)} -> 155.50742 | D81: {=SUMPRODUCT((YEAR($C$58:$BN$58)=D$76)*$C$66:$BN$66)} -> 474.74714 | E81: {=SUMPRODUCT((YEAR($C$58:$BN$58)=E$76)*$C$66:$BN$66)} -> 445.29062 | F81: {=SUMPRODUCT((YEAR($C$58:$BN$58)=F$76)*$C$66:$BN$66)} -> 385.99505 | G81: {=SUMPRODUCT((YEAR($C$58:$BN$58)=G$76)*$C$66:$BN$66)} -> 253.24948 | H81: {=SUMPRODUCT((YEAR($C$58:$BN$58)=H$76)*$C$66:$BN$66)} -> 102.52396 | I81: {=SUMPRODUCT((YEAR($C$58:$BN$58)=I$76)*$C$66:$BN$66)} -> 0
A82: Bank interest paid | C82: {=SUMPRODUCT((YEAR($C$58:$BN$58)=C$76)*$C$67:$BN$67)} -> 104.49258 | D82: {=SUMPRODUCT((YEAR($C$58:$BN$58)=D$76)*$C$67:$BN$67)} -> 283.43051 | E82: {=SUMPRODUCT((YEAR($C$58:$BN$58)=E$76)*$C$67:$BN$67)} -> 67.090514 | F82: {=SUMPRODUCT((YEAR($C$58:$BN$58)=F$76)*$C$67:$BN$67)} -> 0 | G82: {=SUMPRODUCT((YEAR($C$58:$BN$58)=G$76)*$C$67:$BN$67)} -> 0 | H82: {=SUMPRODUCT((YEAR($C$58:$BN$58)=H$76)*$C$67:$BN$67)} -> 0 | I82: {=SUMPRODUCT((YEAR($C$58:$BN$58)=I$76)*$C$67:$BN$67)} -> 0
A83: Principal repaid | C83: {=SUMPRODUCT((YEAR($C$58:$BN$58)=C$76)*$C$68:$BN$68)} -> 1031.9725 | D83: {=SUMPRODUCT((YEAR($C$58:$BN$58)=D$76)*$C$68:$BN$68)} -> 3709.225 | E83: {=SUMPRODUCT((YEAR($C$58:$BN$58)=E$76)*$C$68:$BN$68)} -> 1373.515 | F83: {=SUMPRODUCT((YEAR($C$58:$BN$58)=F$76)*$C$68:$BN$68)} -> 1836.25 | G83: {=SUMPRODUCT((YEAR($C$58:$BN$58)=G$76)*$C$68:$BN$68)} -> 1836.25 | H83: {=SUMPRODUCT((YEAR($C$58:$BN$58)=H$76)*$C$68:$BN$68)} -> 1836.25 | I83: {=SUMPRODUCT((YEAR($C$58:$BN$58)=I$76)*$C$68:$BN$68)} -> 0
A84: Refinancing proceeds | C84: {=SUMPRODUCT((YEAR($C$58:$BN$58)=C$76)*$C$69:$BN$69)} -> 0 | D84: {=SUMPRODUCT((YEAR($C$58:$BN$58)=D$76)*$C$69:$BN$69)} -> 0 | E84: {=SUMPRODUCT((YEAR($C$58:$BN$58)=E$76)*$C$69:$BN$69)} -> 0 | F84: {=SUMPRODUCT((YEAR($C$58:$BN$58)=F$76)*$C$69:$BN$69)} -> 0 | G84: {=SUMPRODUCT((YEAR($C$58:$BN$58)=G$76)*$C$69:$BN$69)} -> 0 | H84: {=SUMPRODUCT((YEAR($C$58:$BN$58)=H$76)*$C$69:$BN$69)} -> 0 | I84: {=SUMPRODUCT((YEAR($C$58:$BN$58)=I$76)*$C$69:$BN$69)} -> 0
A85: Net cash flow | C85: =C80-C81-C82-C83+C84 -> -875.00659 | D85: =D80-D81-D82-D83+D84 -> 13301.258 | E85: =E80-E81-E82-E83+E84 -> 1023.2153 | F85: =F80-F81-F82-F83+F84 -> -2036.5786 | G85: =G80-G81-G82-G83+G84 -> -2089.4995 | H85: =H80-H81-H82-H83+H84 -> -1938.774 | I85: =I80-I81-I82-I83+I84 -> 0
A86: Closing cash outside escrow | C86: {=LOOKUP(2,1/(YEAR($C$58:$BN$58)=C$76),$C$71:$BN$71)} -> -188.43069 | D86: {=LOOKUP(2,1/(YEAR($C$58:$BN$58)=D$76),$C$71:$BN$71)} -> 13112.828 | E86: {=LOOKUP(2,1/(YEAR($C$58:$BN$58)=E$76),$C$71:$BN$71)} -> 14136.043 | F86: {=LOOKUP(2,1/(YEAR($C$58:$BN$58)=F$76),$C$71:$BN$71)} -> 12099.464 | G86: {=LOOKUP(2,1/(YEAR($C$58:$BN$58)=G$76),$C$71:$BN$71)} -> 10009.965 | H86: {=LOOKUP(2,1/(YEAR($C$58:$BN$58)=H$76),$C$71:$BN$71)} -> 8071.1908 | I86: {=LOOKUP(2,1/(YEAR($C$58:$BN$58)=I$76),$C$71:$BN$71)} -> 8071.1908
A87: Lowest cash point during the year | C87: =_xlfn.MINIFS($C$71:$BN$71,$C$58:$BN$58,">="&DATE(C$76,1,1),$C$58:$BN$58,"<="&DATE(C$76,12,31)) -> -188.43069 | D87: =_xlfn.MINIFS($C$71:$BN$71,$C$58:$BN$58,">="&DATE(D$76,1,1),$C$58:$BN$58,"<="&DATE(D$76,12,31)) -> -362.54875 | E87: =_xlfn.MINIFS($C$71:$BN$71,$C$58:$BN$58,">="&DATE(E$76,1,1),$C$58:$BN$58,"<="&DATE(E$76,12,31)) -> 12948.672 | F87: =_xlfn.MINIFS($C$71:$BN$71,$C$58:$BN$58,">="&DATE(F$76,1,1),$C$58:$BN$58,"<="&DATE(F$76,12,31)) -> 12014.792 | G87: =_xlfn.MINIFS($C$71:$BN$71,$C$58:$BN$58,">="&DATE(G$76,1,1),$C$58:$BN$58,"<="&DATE(G$76,12,31)) -> 10009.965 | H87: =_xlfn.MINIFS($C$71:$BN$71,$C$58:$BN$58,">="&DATE(H$76,1,1),$C$58:$BN$58,"<="&DATE(H$76,12,31)) -> 8071.1908 | I87: =_xlfn.MINIFS($C$71:$BN$71,$C$58:$BN$58,">="&DATE(I$76,1,1),$C$58:$BN$58,"<="&DATE(I$76,12,31)) -> 8071.1908
A88: Debt maturing in the year | C88: {=SUMPRODUCT((YEAR($E$32:$E$39)=C$76)*$C$32:$C$39)} -> 1031.9725 | D88: {=SUMPRODUCT((YEAR($E$32:$E$39)=D$76)*$C$32:$C$39)} -> 3709.225 | E88: {=SUMPRODUCT((YEAR($E$32:$E$39)=E$76)*$C$32:$C$39)} -> 1373.515 | F88: {=SUMPRODUCT((YEAR($E$32:$E$39)=F$76)*$C$32:$C$39)} -> 1836.25 | G88: {=SUMPRODUCT((YEAR($E$32:$E$39)=G$76)*$C$32:$C$39)} -> 1836.25 | H88: {=SUMPRODUCT((YEAR($E$32:$E$39)=H$76)*$C$32:$C$39)} -> 1836.25 | I88: {=SUMPRODUCT((YEAR($E$32:$E$39)=I$76)*$C$32:$C$39)} -> 0
A89: Towers completing | C89: {=SUMPRODUCT((YEAR($C$58:$BN$58)=C$76)*$C$72:$BN$72)} -> 4 | D89: {=SUMPRODUCT((YEAR($C$58:$BN$58)=D$76)*$C$72:$BN$72)} -> 24 | E89: {=SUMPRODUCT((YEAR($C$58:$BN$58)=E$76)*$C$72:$BN$72)} -> 4 | F89: {=SUMPRODUCT((YEAR($C$58:$BN$58)=F$76)*$C$72:$BN$72)} -> 0 | G89: {=SUMPRODUCT((YEAR($C$58:$BN$58)=G$76)*$C$72:$BN$72)} -> 0 | H89: {=SUMPRODUCT((YEAR($C$58:$BN$58)=H$76)*$C$72:$BN$72)} -> 0 | I89: {=SUMPRODUCT((YEAR($C$58:$BN$58)=I$76)*$C$72:$BN$72)} -> 0
A91: 6. EVERY MATURITY, COVERED OR NOT
A92: Cash available is the closing balance in the maturity month before that principal is paid. Coverage below 1.00x means the maturity cannot be met from modelled cash alone and needs a refinancing, an asset sale, or new presales the register cannot yet see.
A93: Instrument | B93: Maturity | C93: Amount | D93: Month | E93: Cash available | F93: Coverage | G93: Shortfall
A94: =A32 -> 9.625% sukuk due 28 Feb 2027 | B94: =E32 -> 46446 | C94: =C32 -> 1836.25 | D94: =G32 -> 5 | E94: =INDEX($C$71:$BN$71,1,MATCH($D94,$C$57:$BN$57,0))+INDEX($C$68:$BN$68,1,MATCH($D94,$C$57:$BN$57,0)) -> 1473.7013 | F94: =IF($C94>0,$E94/$C94,"") -> 0.80256025 | G94: =MAX(0,$C94-$E94) -> 362.54875
A95: =A33 -> 7.75% green sukuk due 2 Jul 2029 | B95: =E33 -> 47301 | C95: =C33 -> 1836.25 | D95: =G33 -> 34 | E95: =INDEX($C$71:$BN$71,1,MATCH($D95,$C$57:$BN$57,0))+INDEX($C$68:$BN$68,1,MATCH($D95,$C$57:$BN$57,0)) -> 13876.29 | F95: =IF($C95>0,$E95/$C95,"") -> 7.5568632 | G95: =MAX(0,$C95-$E95) -> 0
A96: =A34 -> 8.125% sukuk due 7 Aug 2030 | B96: =E34 -> 47702 | C96: =C34 -> 1836.25 | D96: =G34 -> 47 | E96: =INDEX($C$71:$BN$71,1,MATCH($D96,$C$57:$BN$57,0))+INDEX($C$68:$BN$68,1,MATCH($D96,$C$57:$BN$57,0)) -> 11897.477 | F96: =IF($C96>0,$E96/$C96,"") -> 6.4792249 | G96: =MAX(0,$C96-$E96) -> 0
A97: =A35 -> 8.375% sukuk due 12 Aug 2031 | B97: =E35 -> 48072 | C97: =C35 -> 1836.25 | D97: =G35 -> 59 | E97: =INDEX($C$71:$BN$71,1,MATCH($D97,$C$57:$BN$57,0))+INDEX($C$68:$BN$68,1,MATCH($D97,$C$57:$BN$57,0)) -> 9907.4408 | F97: =IF($C97>0,$E97/$C97,"") -> 5.3954749 | G97: =MAX(0,$C97-$E97) -> 0
A98: =A36 -> Secured bank debt — due H2 2026 | B98: =E36 -> 46387 | C98: =C36 -> 1031.9725 | D98: =G36 -> 3 | E98: =INDEX($C$71:$BN$71,1,MATCH($D98,$C$57:$BN$57,0))+INDEX($C$68:$BN$68,1,MATCH($D98,$C$57:$BN$57,0)) -> 843.54181 | F98: =IF($C98>0,$E98/$C98,"") -> 0.81740725 | G98: =MAX(0,$C98-$E98) -> 188.43069
A99: =A37 -> Secured bank debt — due H1 2027 | B99: =E37 -> 46568 | C99: =C37 -> 690.43 | D99: =G37 -> 9 | E99: =INDEX($C$71:$BN$71,1,MATCH($D99,$C$57:$BN$57,0))+INDEX($C$68:$BN$68,1,MATCH($D99,$C$57:$BN$57,0)) -> 7244.6114 | F99: =IF($C99>0,$E99/$C99,"") -> 10.492898 | G99: =MAX(0,$C99-$E99) -> 0
A100: =A38 -> Secured bank debt — due H2 2027 | B100: =E38 -> 46752 | C100: =C38 -> 1182.545 | D100: =G38 -> 15 | E100: =INDEX($C$71:$BN$71,1,MATCH($D100,$C$57:$BN$57,0))+INDEX($C$68:$BN$68,1,MATCH($D100,$C$57:$BN$57,0)) -> 14295.373 | F100: =IF($C100>0,$E100/$C100,"") -> 12.08865 | G100: =MAX(0,$C100-$E100) -> 0
A101: =A39 -> Secured bank debt — due 2028 | B101: =E39 -> 46934 | C101: =C39 -> 1373.515 | D101: =G39 -> 21 | E101: =INDEX($C$71:$BN$71,1,MATCH($D101,$C$57:$BN$57,0))+INDEX($C$68:$BN$68,1,MATCH($D101,$C$57:$BN$57,0)) -> 14322.187 | F101: =IF($C101>0,$E101/$C101,"") -> 10.427397 | G101: =MAX(0,$C101-$E101) -> 0
A103: 7. TIE-OUT CHECKS
A104: Check — month 28 escrow release against the Simulator | B104: =INDEX($C$59:$BN$59,1,28)-Simulator!$AW$40 -> 0 | C104: Must be zero. Proves the 64-month engine reproduces the Simulator over its own 28 months before extending past it.
A105: Check — debt stack against the Debt sheet | B105: =$C$40-Debt!$E$14 -> 0 | C105: Must be zero.
A106: Check — towers completing against live project count | B106: =SUM($C$72:$BN$72)-Dashboard!$B$82 -> 0 | C106: Must be zero. Every live project completes within the horizon.
A107: Check — closing cash against opening plus net flows | B107: {=INDEX($C$71:$BN$71,1,$B$27)-($B$19+SUM($C$70:$BN$70))} -> 0 | C107: Must be zero. Confirms the cash waterfall does not leak.
A108: Check — principal repaid against the full stack | B108: =SUM($C$68:$BN$68)-$C$40 -> 0 | C108: Must be zero. Every instrument repaid exactly once within the horizon.
A110: 8. CROSS-SHEET AGREEMENT — EVERY HEADLINE MUST MATCH
A111: The workbook carries two coverage measures and they give different answers, which is legitimate only if every sheet is explicit about which one it is reporting. These checks confirm the cash test agrees wherever it appears, and that the headroom measure agrees wherever that appears. All must be zero.
A112: Check | B112: Difference | C112: What it proves
...

Sheet Handover check
A1: Handover check: what has actually been delivered since 30 June 2026
A2: The company states that AED 1.8bn came in from three handovers after the balance sheet date. This tab tests that claim against the DLD register. Project status read 30 Aug 2026; transactions read 9 Sep 2026. Nothing here is an opinion - it is what the register does and does not record.
A4: 1. Every Binghatti tower that could plausibly have handed over since 30 June
A5: Project | B5: Units | C5: Sold | D5: Contracted AED m | E5: Certified % | F5: Registered completion | G5: Register status | H5: Ready sales since 30 Jun | I5: Mortgages since 30 Jun | J5: Gross escrow release if complete | K5: Already released at certified % | L5: Incremental cash on handover | M5: What the register shows
A6: Binghatti Apex | B6: 552 | C6: 484 | D6: 446 | E6: 100 | F6: 46135 | G6: FINISHED | H6: 86 | I6: 35 | J6: =D6*(1-Scenarios!$F$13) -> 423.7 | K6: =D6*(Scenarios!$F$11+(1-Scenarios!$F$11-Scenarios!$F$12)*E6/100)*(E6/100)*(1-Scenarios!$F$13) -> 296.59 | L6: =J6-K6 -> 127.11 | M6: Handed over BEFORE the balance sheet date - its escrow release is already inside the 30 June cash
A7: Binghatti Pinnacle | B7: 178 | C7: 145 | D7: 337 | E7: 100 | F7: 46233 | G7: FINISHED | H7: 4 | I7: 0 | J7: =D7*(1-Scenarios!$F$13) -> 320.15 | K7: =D7*(Scenarios!$F$11+(1-Scenarios!$F$11-Scenarios!$F$12)*E7/100)*(E7/100)*(1-Scenarios!$F$13) -> 224.105 | L7: =J7-K7 -> 96.045 | M7: CONFIRMED handover after 30 June. The only one.
A8: Binghatti Ghost | B8: 785 | C8: 695 | D8: 864 | E8: 99 | F8: 46112 | G8: ACTIVE | H8: 0 | I8: 1 | J8: =D8*(1-Scenarios!$F$13) -> 820.8 | K8: =D8*(Scenarios!$F$11+(1-Scenarios!$F$11-Scenarios!$F$12)*E8/100)*(E8/100)*(1-Scenarios!$F$13) -> 563.93885 | L8: =J8-K8 -> 256.86115 | M8: Past due since 31 March, 99% certified - the likeliest candidate, but the register has not marked it finished and no ready market has opened
A9: Binghatti Grove | B9: 404 | C9: 359 | D9: 611 | E9: 84 | F9: 46112 | G9: ACTIVE | H9: 0 | I9: 0 | J9: =D9*(1-Scenarios!$F$13) -> 580.45 | K9: =D9*(Scenarios!$F$11+(1-Scenarios!$F$11-Scenarios!$F$12)*E9/100)*(E9/100)*(1-Scenarios!$F$13) -> 294.49711 | L9: =J9-K9 -> 285.95289 | M9: Past due since 31 March. No handover recorded, no ready market
A10: Binghatti Haven | B10: 501 | C10: 471 | D10: 636 | E10: 76 | F10: 46112 | G10: ACTIVE | H10: 0 | I10: 0 | J10: =D10*(1-Scenarios!$F$13) -> 604.2 | K10: =D10*(Scenarios!$F$11+(1-Scenarios!$F$11-Scenarios!$F$12)*E10/100)*(E10/100)*(1-Scenarios!$F$13) -> 255.31075 | L10: =J10-K10 -> 348.88925 | M10: Past due since 31 March. No handover recorded, no ready market
A11: Binghatti Hillside | B11: 411 | C11: 288 | D11: 280 | E11: 70 | F11: 46203 | G11: ACTIVE | H11: 0 | I11: 0 | J11: =D11*(1-Scenarios!$F$13) -> 266 | K11: =D11*(Scenarios!$F$11+(1-Scenarios!$F$11-Scenarios!$F$12)*E11/100)*(E11/100)*(1-Scenarios!$F$13) -> 96.824 | L11: =J11-K11 -> 169.176 | M11: Past due since 30 June. No handover recorded
A12: Binghatti Starlight | B12: 511 | C12: 469 | D12: 529 | E12: 63 | F12: 46112 | G12: ACTIVE | H12: 0 | I12: 0 | J12: =D12*(1-Scenarios!$F$13) -> 502.55 | K12: =D12*(Scenarios!$F$11+(1-Scenarios!$F$11-Scenarios!$F$12)*E12/100)*(E12/100)*(1-Scenarios!$F$13) -> 151.33791 | L12: =J12-K12 -> 351.21209 | M12: Past due since 31 March. No handover recorded
A13: Mercedes-Benz Places | B13: 163 | C13: 117 | D13: 1802 | E13: 65 | F13: 46387 | G13: ACTIVE | H13: 0 | I13: 1 | J13: =D13*(1-Scenarios!$F$13) -> 1711.9 | K13: =D13*(Scenarios!$F$11+(1-Scenarios!$F$11-Scenarios!$F$12)*E13/100)*(E13/100)*(1-Scenarios!$F$13) -> 545.24015 | L13: =J13-K13 -> 1166.6598 | M13: Not due until Dec 2026. Note the contracted value is almost exactly the AED 1.8bn claimed - worth ruling out as a coincidence
A15: 2. Calibration: what a real handover looks like in the transaction register
A16: Ready (Existing Properties) sales registered per month. A tower that hands over starts trading on the secondary market within weeks, and mortgages follow.
A17: Project | B17: Mar | C17: Apr | D17: May | E17: Jun | F17: Jul | G17: Aug | H17: Sep (to 9th) | I17: Mortgages since May
A18: Binghatti Apex (completed 23 Apr) | B18: 0 | C18: 0 | D18: 14 | E18: 55 | F18: 42 | G18: 35 | H18: 9 | I18: 46
A19: Binghatti Pinnacle (completed 30 Jul) | B19: 0 | C19: 0 | D19: 0 | E19: 0 | F19: 0 | G19: 0 | H19: 4 | I19: 0
A20: Binghatti Ghost (99% certified) | B20: 0 | C20: 0 | D20: 0 | E20: 0 | F20: 0 | G20: 0 | H20: 0 | I20: 1
A21: Grove / Haven / Starlight / Hillside | B21: 0 | C21: 0 | D21: 0 | E21: 0 | F21: 0 | G21: 0 | H21: 0 | I21: 0
A22: Read it this way: Apex produced 14 ready sales within five weeks of handover and 46 mortgages since. Ghost is a larger tower at 99% certified; if it had handed over in July there would be a ready market by now. There is none, in any of the candidates.
A24: 3. What the register supports, and what it does not (AED m)
A25: Certified % of Pinnacle at 30 June 2026 - CHANGE ME | B25: 30.46 | C25: The 15 June register reading, and it is not trustworthy: the same dump showed Apex at 45% two months after Apex had completed. If Pinnacle was in fact near completion at 30 June, more of its escrow had already been released and the figure in B28 falls. Try 80 to see the low end.
A26: Gross escrow release on completion, Pinnacle | B26: =J7 -> 320.15 | C26: Contracted value less the 5% RERA retention held for a year after completion.
A27: less: released to the developer before 30 June at that certified % | B27: =D7*(Scenarios!$F$11+(1-Scenarios!$F$11-Scenarios!$F$12)*B25/100)*(B25/100)*(1-Scenarios!$F$13) -> 27.574102
A28: CASH ARRIVING AFTER 30 JUNE THAT THE REGISTER SUPPORTS | B28: =B26-B27 -> 292.5759 | C28: This is what feeds the Dashboard. Pinnacle is marked FINISHED so the Simulator no longer models it - counting it here is not double counting.
A29: Claimed by the company | B29: 1800 | C29: Company statement reported in the Moody's August review. Not traceable to any filing, and not attributed to named towers.
A30: Unverified gap | B30: =B29-B28 -> 1507.4241 | C30: Three towers of roughly AED 1.9bn contracted value releasing full escrow would produce about AED 1.8bn. So the claim is arithmetically plausible - but two of those three are still ACTIVE in the register with no ready market.
A31: For reference: Ghost + Haven + Pinnacle at full escrow release | B31: =J7+J8+J10 -> 1745.15 | C31: Three towers of roughly AED 1.9bn contracted value releasing full escrow would produce about AED 1.8bn, so the claim is arithmetically plausible. But Ghost and Haven are still ACTIVE in the register and show no ready market.
A32: Double-counting warning | C32: Ghost, Grove, Haven, Starlight and Hillside remain live in the Simulator, which already models their escrow releasing forward. Adding their handover cash to the Dashboard as well would count it twice.
A34: 4. What the answer is worth: the February 2027 sukuk under each assumption
A35: Cash counted as received since 30 June (AED m) | B35: Cash available at 28 Feb 2027 | C35: Coverage on the cash test | D35: Shortfall (AED m) | E35: Verdict
A36: 0 | B36: =('Cash flow'!$E$94-Dashboard!$D$5)+$A36 -> 1181.1254 | C36: =IF('Cash flow'!$C$94>0,$B36/'Cash flow'!$C$94,"") -> 0.64322688 | D36: =MAX(0,'Cash flow'!$C$94-$B36) -> 655.12465 | E36: ="Nothing counted — "&IF($C36>=1,"covered","NOT covered") -> Nothing counted — NOT covered
A37: =$B$28 -> 292.5759 | B37: =('Cash flow'!$E$94-Dashboard!$D$5)+$A37 -> 1473.7013 | C37: =IF('Cash flow'!$C$94>0,$B37/'Cash flow'!$C$94,"") -> 0.80256025 | D37: =MAX(0,'Cash flow'!$C$94-$B37) -> 362.54875 | E37: ="What the register supports — "&IF($C37>=1,"covered","NOT covered") -> What the register supports — NOT covered
A38: =$B$29 -> 1800 | B38: =('Cash flow'!$E$94-Dashboard!$D$5)+$A38 -> 2981.1254 | C38: =IF('Cash flow'!$C$94>0,$B38/'Cash flow'!$C$94,"") -> 1.6234856 | D38: =MAX(0,'Cash flow'!$C$94-$B38) -> 0 | E38: ="The company's claim at face value — "&IF($C38>=1,"covered","NOT covered") -> The company's claim at face value — covered
A39: Check — the middle row against the live Dashboard | B39: =($C37-Dashboard!$C$12)+($D37-Dashboard!$D$12) -> 0 | C39: Must be zero. Confirms the register-supported row reproduces what the Dashboard and Cash flow sheets actually report, rather than drifting as a hardcoded figure. An earlier version of this row added the gross escrow release instead of the net and overstated coverage; the row is now a formula.
A40: This single number decides the question. On the register's evidence the 9.625% sukuk due 28 February 2027 is not covered from modelled cash; on the company's unverified claim it is covered 1.6 times. Everything between those two lines is the gap between what Binghatti says it has collected and what the Dubai Land Department records show has been delivered.
A42: 5. The one test that would settle it
A43: A handover shows up in the transaction register within weeks and cannot be hidden: units begin trading as Existing Properties and mortgages are registered against them. Apex produced 14 ready sales inside five weeks and 46 mortgages since. Watch Ghost, Grove and Haven in the daily refresh - the first ready sale in any of them is the confirmation that a handover has actually happened. As of 9 September there is not one.

Sheet Scenarios
A1: Scenario inputs — the only cells the escrow model reads
A2: Blue cells are yours to change. Column F is the scenario currently driving the Simulator and the Dashboard. Nothing here is a forecast by DPI: the base column is the register plus the issuer's own disclosed payment terms.
A3: Active scenario (1–4) | B3: 1 | C3: {=INDEX($B$4:$E$4,1,$B$3)} -> Base
A4: Input | B4: Base | C4: Delayed handovers | D4: Cancellation spike | E4: Price cut | F4: Active | G4: What it does
A5: Handover delay added to every registered completion date (months) | B5: 0 | C5: 6 | D5: 0 | E5: 0 | F5: {=INDEX($B5:$E5,1,$B$3)} -> 0 | G5: The register date is what the developer filed. Base takes it at face value; "delayed" pushes every tower back by this many months.
A6: Months to completion for projects already past their registered date | B6: 6 | C6: 12 | D6: 6 | E6: 6 | F6: {=INDEX($B6:$E6,1,$B$3)} -> 6 | G6: A tower whose date has passed has no useful date in the register. This is how long the model gives it from today.
A7: Months to completion for projects with no registered date | B7: 24 | C7: 30 | D7: 24 | E7: 24 | F7: {=INDEX($B7:$E7,1,$B$3)} -> 24 | G7: Four active towers carry no completion date at all.
A8: Cancellation rate — share of contracted value that is never collected | B8: 0 | C8: 0 | D8: 0.15 | E8: 0.05 | F8: {=INDEX($B8:$E8,1,$B$3)} -> 0 | G8: Buyers who default on instalments. Applied to the remaining collections on every project.
A9: Sell-through of unsold units before completion | B9: 0.6 | C9: 0.4 | D9: 0.4 | E9: 0.6 | F9: {=INDEX($B9:$E9,1,$B$3)} -> 0.6 | G9: Share of currently unsold units that sell (and start paying) before handover.
A10: Price change on those future sales | B10: 0 | C10: 0 | D10: 0 | E10: -0.15 | F10: {=INDEX($B10:$E10,1,$B$3)} -> 0 | G10: Applied to the average ticket of each project for units still to be sold.
A11: Share of price collected at sale (booking) | B11: 0.1 | C11: 0.1 | D11: 0.1 | E11: 0.1 | F11: {=INDEX($B11:$E11,1,$B$3)} -> 0.1 | G11: Issuer discloses ~70% collected during construction including booking; 10/60/30 is the plan shape used here. Change it to the plan you know.
A12: Share of price collected at handover | B12: 0.3 | C12: 0.3 | D12: 0.3 | E12: 0.3 | F12: {=INDEX($B12:$E12,1,$B$3)} -> 0.3 | G12: The final instalment. Between booking and handover, collections track certified progress.
A13: RERA escrow retention held until one year after completion | B13: 0.05 | C13: 0.05 | D13: 0.05 | E13: 0.05 | F13: {=INDEX($B13:$E13,1,$B$3)} -> 0.05 | G13: Not released within the model horizon; treated as unavailable cash.
A14: Maximum certified progress per month (percentage points) | B14: 8 | C14: 6 | D14: 8 | E14: 8 | F14: {=INDEX($B14:$E14,1,$B$3)} -> 8 | G14: A tower cannot be certified faster than it can be built. Caps the pace the model implies from the completion date.
A15: Cost to complete, share of contracted value | B15: 0.55 | C15: 0.55 | D15: 0.55 | E15: 0.55 | F15: {=INDEX($B15:$E15,1,$B$3)} -> 0.55 | G15: CONFIRM THIS. Derived, not disclosed: reported gross margin runs 45% FY24, 44% FY25, 45% H1-26, implying cost at about 55% of contracted value. Spent in step with certified progress. Override if you have cost-to-complete data.
A16: 3M EIBOR assumption for bank debt | B16: 0.042 | C16: 0.042 | D16: 0.042 | E16: 0.042 | F16: {=INDEX($B16:$E16,1,$B$3)} -> 0.042 | G16: CONFIRM THIS. Not taken from a rate source. Bank debt prices at 3M EIBOR plus a margin per the Debt sheet; the margin is the next row.
A17: Bank margin over EIBOR | B17: 0.0238 | C17: 0.0238 | D17: 0.0238 | E17: 0.0238 | F17: {=INDEX($B17:$E17,1,$B$3)} -> 0.0238 | G17: Midpoint of the 2.00-2.75% range the Debt sheet cites from the financing notes.
A18: Refinance sukuk at maturity instead of repaying cash | B18: No | C18: No | D18: No | E18: No | F18: {=INDEX($B18:$E18,1,$B$3)} -> No | G18: Type Yes or No. No is the hard test: every maturity must be met from cash. Yes rolls each sukuk at maturity at the spread below, so only profit payments stay a cash cost.
A19: Refinancing spread over the maturing coupon | B19: 0.02 | C19: 0.03 | D19: 0.04 | E19: 0.03 | F19: {=INDEX($B19:$E19,1,$B$3)} -> 0.02 | G19: Only used when the row above is Yes. Added to the maturing instrument's coupon to price the replacement.
A21: How the model turns these into cash
A22: For each live project: collected-to-date = contracted value × (booking + (1 − booking − handover) × certified %). Future months: certified % rises at the pace implied by the projected completion date (capped), collections follow, and at 100% the handover share is paid. Escrow does not hand the developer what has been collected: RERA releases collections in step with certified progress, so released = collected × certified %, less the retention — which is why the company reports AED 10.2 bn still sitting in escrow. Monthly release = the change in that cumulative figure. Contracted value = sold units × average registered ticket, plus future sales of unsold units at the sell-through and price change above.

Sheet Simulator
A1: Escrow release simulator — live projects
A2: Register facts in blue (change them if you know better); everything to the right is arithmetic on the active scenario. AED millions unless stated.
A3: As of | C3: 46275 | E3: Register readings: certified % and dates are the latest observation per project (DLD register 15 Jun 2026, updated by the 30 Aug 2026 register extract where available). Units and sales are from the DLD transactions register to the as-of date.
A4: Active scenario | C4: =Scenarios!$C$3 -> Base
V5: Cumulative future escrow release under the active scenario, AED m (month index in the row below) | AY5: Scenario 1: Base | BF5: Scenario 2: Delayed handovers | BM5: Scenario 3: Cancellation spike | BT5: Scenario 4: Price cut
V6: 1 | W6: 2 | X6: 3 | Y6: 4 | Z6: 5 | AA6: 6 | AB6: 7 | AC6: 8 | AD6: 9 | AE6: 10 | AF6: 11 | AG6: 12 | AH6: 13 | AI6: 14 | AJ6: 15 | AK6: 16 | AL6: 17 | AM6: 18 | AN6: 19 | AO6: 20 | AP6: 21 | AQ6: 22 | AR6: 23 | AS6: 24 | AT6: 25 | AU6: 26 | AV6: 27 | AW6: 28
A7: Project no. | B7: Project | C7: Status | D7: Last read | E7: Units | F7: Sold units | G7: Avg ticket (AED) | H7: Certified % | I7: Registered completion | J7: Contracted value | K7: Unsold units | L7: Sold % | M7: Projected completion | N7: Months to go | O7: Pace %/mo | P7: Effective contracted value | Q7: Released from escrow to date (est.) | R7: Release by 28 Feb 2027 | S7: Release by 31 Dec 2027 | T7: Release by 31 Dec 2028 | U7: Collected to date (est.) | V7: 46296 | W7: 46327 | X7: 46357 | Y7: 46388 | Z7: 46419 | AA7: 46447 | AB7: 46478 | AC7: 46508 | AD7: 46539 | AE7: 46569 | AF7: 46600 | AG7: 46631 | AH7: 46661 | AI7: 46692 | AJ7: 46722 | AK7: 46753 | AL7: 46784 | AM7: 46813 | AN7: 46844 | AO7: 46874 | AP7: 46905 | AQ7: 46935 | AR7: 46966 | AS7: 46997 | AT7: 47027 | AU7: 47058 | AV7: 47088 | AW7: 47119 | AY7: Months | AZ7: Pace | BA7: Eff. value | BB7: Released to date | BC7: By Feb-27 | BD7: By Dec-27 | BE7: By Dec-28 | BF7: Months | BG7: Pace | BH7: Eff. value | BI7: Released to date | BJ7: By Feb-27 | BK7: By Dec-27 | BL7: By Dec-28 | BM7: Months | BN7: Pace | BO7: Eff. value | BP7: Released to date | BQ7: By Feb-27 | BR7: By Dec-27 | BS7: By Dec-28 | BT7: Months | BU7: Pace | BV7: Eff. value | BW7: Released to date | BX7: By Feb-27 | BY7: By Dec-27 | BZ7: By Dec-28 | CA7: rank key
